{"2019-20": {"20": {"kurtic j": {"squadra": "parma", "ruolo": "C", "fantavoto": 5.5, "voto": 6.0, "gol_fatti_subiti": 0.0, "ammonizioni": -0.5, "espulsioni": 0.0, "rigori_parati_segnati": 0.0, "autogol": 0.0, "portiere_imbattuto": 0.0, "nome_giocatore": "kurtic j"}, "nicola": {"squadra": "genoa", "ruolo": "0", "fantavoto": 6.0, "voto": 6.0, "gol_fatti_subiti": 0.0, "ammonizioni": 0.0, "espulsioni": 0.0, "rigori_parati_segnati": 0.0, "autogol": 0.0, "portiere_imbattuto": 0.0, "nome_giocatore": "nicola"}, "kumbulla m": {"squadra": "verona", "ruolo": "D", "fantavoto": 5.0, "voto": 5.0, "gol_fatti_subiti": 0.0, "ammonizioni": 0.0, "espulsioni": 0.0, "rigori_parati_segnati": 0.0, "autogol": 0.0, "portiere_imbattuto": 0.0, "nome_giocatore": "kumbulla m"}, "ceccherini f": {"squadra": "fiorentina", "ruolo": "D", "fantavoto": NaN, "voto": NaN, "gol_fatti_subiti": 0.0, "ammonizioni": 0.0, "espulsioni": 0.0, "rigori_parati_segnati": 0.0, "autogol": 0.0, "portiere_imbattuto": 0.0, "nome_giocatore": "ceccherini f"}, "castillejo s": {"squadra": "milan", "ruolo": "A", "fantavoto": 7.0, "voto": 7.5, "gol_fatti_subiti": 0.0, "ammonizioni": -0.5, "espulsioni": 0.0, "rigori_parati_segnati": 0.0, "autogol": 0.0, "portiere_imbattuto": 0.0, "nome_giocatore": "castillejo s"}, "becao r": {"squadra": "udinese", "ruolo": "D", "fantavoto": 6.0, "voto": 6.0, "gol_fatti_subiti": 0.0, "ammonizioni": 0.0, "espulsioni": 0.0, "rigori_parati_segnati": 0.0, "autogol": 0.0, "portiere_imbattuto": 0.0, "nome_giocatore": "becao r"}, "farago p": {"squadra": "cagliari", "ruolo": "C", "fantavoto": 6.0, "voto": 6.0, "gol_fatti_subiti": 0.0, "ammonizioni": 0.0, "espulsioni": 0.0, "rigori_parati_segnati": 0.0, "autogol": 0.0, "portiere_imbattuto": 0.0, "nome_giocatore": "farago p"}, "allan m": {"squadra": "napoli", "ruolo": "C", "fantavoto": 4.5, "voto": 4.5, "gol_fatti_subiti": 0.0, "ammonizioni": 0.0, "espulsioni": 0.0, "rigori_parati_segnati": 0.0, "autogol": 0.0, "portiere_imbattuto": 0.0, "nome_giocatore": "allan m"}, "bereszynski b": {"squadra": "sampdoria", "ruolo": "D", "fantavoto": 4.5, "voto": 4.5, "gol_fatti_subiti": 0.0, "ammonizioni": 0.0, "espulsioni": 0.0, "rigori_parati_segnati": 0.0, "autogol": 0.0, "portiere_imbattuto": 0.0, "nome_giocatore": "bereszynski b"}, "lazovic d": {"squadra": "verona", "ruolo": "C", "fantavoto": 8.0, "voto": 7.0, "gol_fatti_subiti": 0.0, "ammonizioni": 0.0, "espulsioni": 0.0, "rigori_parati_segnati": 0.0, "autogol": 0.0, "portiere_imbattuto": 1.0, "nome_giocatore": "lazovic d"}, "pau lopez": {"squadra": "roma", "ruolo": "P", "fantavoto": 6.0, "voto": 7.5, "gol_fatti_subiti": -1.0, "ammonizioni": -0.5, "espulsioni": 0.0, "rigori_parati_segnati": 0.0, "autogol": 0.0, "portiere_imbattuto": 0.0, "nome_giocatore": "pau lopez"}, "rog m": {"squadra": "cagliari", "ruolo": "C", "fantavoto": 5.0, "voto": 5.0, "gol_fatti_subiti": 0.0, "ammonizioni": 0.0, "espulsioni": 0.0, "rigori_parati_segnati": 0.0, "autogol": 0.0, "portiere_imbattuto": 0.0, "nome_giocatore": "rog m"}, "d aversa": {"squadra": "parma", "ruolo": "0", "fantavoto": 6.0, "voto": 6.0, "gol_fatti_subiti": 0.0, "ammonizioni": 0.0, "espulsioni": 0.0, "rigori_parati_segnati": 0.0, "autogol": 0.0, "portiere_imbattuto": 0.0, "nome_giocatore": "d aversa"}, "caprari g": {"squadra": "sampdoria", "ruolo": "A", "fantavoto": 5.5, "voto": 5.5, "gol_fatti_subiti": 0.0, "ammonizioni": 0.0, "espulsioni": 0.0, "rigori_parati_segnati": 0.0, "autogol": 0.0, "portiere_imbattuto": 0.0, "nome_giocatore": "caprari g"}, "strakosha t": {"squadra": "lazio", "ruolo": "P", "fantavoto": 5.0, "voto": 6.0, "gol_fatti_subiti": -1.0, "ammonizioni": 0.0, "espulsioni": 0.0, "rigori_parati_segnati": 0.0, "autogol": 0.0, "portiere_imbattuto": 0.0, "nome_giocatore": "strakosha t"}, "ruiz f": {"squadra": "napoli", "ruolo": "C", "fantavoto": 5.0, "voto": 5.0, "gol_fatti_subiti": 0.0, "ammonizioni": 0.0, "espulsioni": 0.0, "rigori_parati_segnati": 0.0, "autogol": 0.0, "portiere_imbattuto": 0.0, "nome_giocatore": "ruiz f"}, "rispoli a": {"squadra": "lecce", "ruolo": "D", "fantavoto": 6.5, "voto": 6.5, "gol_fatti_subiti": 0.0, "ammonizioni": 0.0, "espulsioni": 0.0, "rigori_parati_segnati": 0.0, "autogol": 0.0, "portiere_imbattuto": 0.0, "nome_giocatore": "rispoli a"}, "milinkovic s": {"squadra": "lazio", "ruolo": "C", "fantavoto": 7.5, "voto": 7.5, "gol_fatti_subiti": 0.0, "ammonizioni": 0.0, "espulsioni": 0.0, "rigori_parati_segnati": 0.0, "autogol": 0.0, "portiere_imbattuto": 0.0, "nome_giocatore": "milinkovic s"}, "lazzari m": {"squadra": "lazio", "ruolo": "C", "fantavoto": 8.0, "voto": 8.0, "gol_fatti_subiti": 0.0, "ammonizioni": 0.0, "espulsioni": 0.0, "rigori_parati_segnati": 0.0, "autogol": 0.0, "portiere_imbattuto": 0.0, "nome_giocatore": "lazzari m"}, "darmian m": {"squadra": "parma", "ruolo": "D", "fantavoto": 5.0, "voto": 5.0, "gol_fatti_subiti": 0.0, "ammonizioni": 0.0, "espulsioni": 0.0, "rigori_parati_segnati": 0.0, "autogol": 0.0, "portiere_imbattuto": 0.0, "nome_giocatore": "darmian m"}, "ekdal a": {"squadra": "sampdoria", "ruolo": "C", "fantavoto": 5.0, "voto": 5.0, "gol_fatti_subiti": 0.0, "ammonizioni": 0.0, "espulsioni": 0.0, "rigori_parati_segnati": 0.0, "autogol": 0.0, "portiere_imbattuto": 0.0, "nome_giocatore": "ekdal a"}, "audero e": {"squadra": "sampdoria", "ruolo": "P", "fantavoto": 0.5, "voto": 5.5, "gol_fatti_subiti": -5.0, "ammonizioni": 0.0, "espulsioni": 0.0, "rigori_parati_segnati": 0.0, "autogol": 0.0, "portiere_imbattuto": 0.0, "nome_giocatore": "audero e"}, "pisacane f": {"squadra": "cagliari", "ruolo": "D", "fantavoto": 6.0, "voto": 6.5, "gol_fatti_subiti": 0.0, "ammonizioni": -0.5, "espulsioni": 0.0, "rigori_parati_segnati": 0.0, "autogol": 0.0, "portiere_imbattuto": 0.0, "nome_giocatore": "pisacane f"}, "insigne l": {"squadra": "napoli", "ruolo": "A", "fantavoto": 4.5, "voto": 4.5, "gol_fatti_subiti": 0.0, "ammonizioni": 0.0, "espulsioni": 0.0, "rigori_parati_segnati": 0.0, "autogol": 0.0, "portiere_imbattuto": 0.0, "nome_giocatore": "insigne l"}, "leiva l": {"squadra": "lazio", "ruolo": "C", "fantavoto": 8.5, "voto": 7.5, "gol_fatti_subiti": 0.0, "ammonizioni": 0.0, "espulsioni": 0.0, "rigori_parati_segnati": 0.0, "autogol": 0.0, "portiere_imbattuto": 1.0, "nome_giocatore": "leiva l"}, "missiroli s": {"squadra": "spal", "ruolo": "C", "fantavoto": 7.0, "voto": 7.0, "gol_fatti_subiti": 0.0, "ammonizioni": 0.0, "espulsioni": 0.0, "rigori_parati_segnati": 0.0, "autogol": 0.0, "portiere_imbattuto": 0.0, "nome_giocatore": "missiroli s"}, "laxalt d": {"squadra": "torino", "ruolo": "C", "fantavoto": 5.0, "voto": 5.0, "gol_fatti_subiti": 0.0, "ammonizioni": 0.0, "espulsioni": 0.0, "rigori_parati_segnati": 0.0, "autogol": 0.0, "portiere_imbattuto": 0.0, "nome_giocatore": "laxalt d"}, "di lorenzo g": {"squadra": "napoli", "ruolo": "D", "fantavoto": 4.5, "voto": 4.5, "gol_fatti_subiti": 0.0, "ammonizioni": 0.0, "espulsioni": 0.0, "rigori_parati_segnati": 0.0, "autogol": 0.0, "portiere_imbattuto": 0.0, "nome_giocatore": "di lorenzo g"}, "radu s": {"squadra": "lazio", "ruolo": "D", "fantavoto": 7.5, "voto": 7.5, "gol_fatti_subiti": 0.0, "ammonizioni": 0.0, "espulsioni": 0.0, "rigori_parati_segnati": 0.0, "autogol": 0.0, "portiere_imbattuto": 0.0, "nome_giocatore": "radu s"}, "handanovic s": {"squadra": "inter", "ruolo": "P", "fantavoto": 5.0, "voto": 6.0, "gol_fatti_subiti": -1.0, "ammonizioni": 0.0, "espulsioni": 0.0, "rigori_parati_segnati": 0.0, "autogol": 0.0, "portiere_imbattuto": 0.0, "nome_giocatore": "handanovic s"}, "adekanye b": {"squadra": "lazio", "ruolo": "A", "fantavoto": 6.0, "voto": 6.5, "gol_fatti_subiti": 0.0, "ammonizioni": -0.5, "espulsioni": 0.0, "rigori_parati_segnati": 0.0, "autogol": 0.0, "portiere_imbattuto": 0.0, "nome_giocatore": "adekanye b"}, "tomovic n": {"squadra": "spal", "ruolo": "D", "fantavoto": NaN, "voto": NaN, "gol_fatti_subiti": 0.0, "ammonizioni": 0.0, "espulsioni": 0.0, "rigori_parati_segnati": 0.0, "autogol": 0.0, "portiere_imbattuto": 0.0, "nome_giocatore": "tomovic n"}, "alberto l": {"squadra": "lazio", "ruolo": "C", "fantavoto": 7.5, "voto": 7.5, "gol_fatti_subiti": 0.0, "ammonizioni": 0.0, "espulsioni": 0.0, "rigori_parati_segnati": 0.0, "autogol": 0.0, "portiere_imbattuto": 0.0, "nome_giocatore": "alberto l"}, "perin m": {"squadra": "genoa", "ruolo": "P", "fantavoto": 1.5, "voto": 4.5, "gol_fatti_subiti": -3.0, "ammonizioni": 0.0, "espulsioni": 0.0, "rigori_parati_segnati": 0.0, "autogol": 0.0, "portiere_imbattuto": 0.0, "nome_giocatore": "perin m"}, "szczesny w": {"squadra": "juventus", "ruolo": "P", "fantavoto": 5.0, "voto": 6.0, "gol_fatti_subiti": -1.0, "ammonizioni": 0.0, "espulsioni": 0.0, "rigori_parati_segnati": 0.0, "autogol": 0.0, "portiere_imbattuto": 0.0, "nome_giocatore": "szczesny w"}, "b peres": {"squadra": "roma", "ruolo": "D", "fantavoto": NaN, "voto": NaN, "gol_fatti_subiti": 0.0, "ammonizioni": 0.0, "espulsioni": 0.0, "rigori_parati_segnati": 0.0, "autogol": 0.0, "portiere_imbattuto": 0.0, "nome_giocatore": "b peres"}, "manolas k": {"squadra": "napoli", "ruolo": "D", "fantavoto": 5.0, "voto": 5.0, "gol_fatti_subiti": 0.0, "ammonizioni": 0.0, "espulsioni": 0.0, "rigori_parati_segnati": 0.0, "autogol": 0.0, "portiere_imbattuto": 0.0, "nome_giocatore": "manolas k"}, "gotti": {"squadra": "udinese", "ruolo": "0", "fantavoto": 6.0, "voto": 6.0, "gol_fatti_subiti": 0.0, "ammonizioni": 0.0, "espulsioni": 0.0, "rigori_parati_segnati": 0.0, "autogol": 0.0, "portiere_imbattuto": 0.0, "nome_giocatore": "gotti"}, "de zerbi": {"squadra": "sassuolo", "ruolo": "0", "fantavoto": 7.0, "voto": 7.0, "gol_fatti_subiti": 0.0, "ammonizioni": 0.0, "espulsioni": 0.0, "rigori_parati_segnati": 0.0, "autogol": 0.0, "portiere_imbattuto": 0.0, "nome_giocatore": "de zerbi"}, "gattuso": {"squadra": "napoli", "ruolo": "0", "fantavoto": 4.0, "voto": 4.0, "gol_fatti_subiti": 0.0, "ammonizioni": 0.0, "espulsioni": 0.0, "rigori_parati_segnati": 0.0, "autogol": 0.0, "portiere_imbattuto": 0.0, "nome_giocatore": "gattuso"}, "spalek n": {"squadra": "brescia", "ruolo": "C", "fantavoto": 5.0, "voto": 5.0, "gol_fatti_subiti": 0.0, "ammonizioni": 0.0, "espulsioni": 0.0, "rigori_parati_segnati": 0.0, "autogol": 0.0, "portiere_imbattuto": 0.0, "nome_giocatore": "spalek n"}, "vlahovic d": {"squadra": "fiorentina", "ruolo": "A", "fantavoto": 10.0, "voto": 7.0, "gol_fatti_subiti": 3.0, "ammonizioni": 0.0, "espulsioni": 0.0, "rigori_parati_segnati": 0.0, "autogol": 0.0, "portiere_imbattuto": 0.0, "nome_giocatore": "vlahovic d"}, "sprocati m": {"squadra": "parma", "ruolo": "C", "fantavoto": 6.0, "voto": 6.0, "gol_fatti_subiti": 0.0, "ammonizioni": 0.0, "espulsioni": 0.0, "rigori_parati_segnati": 0.0, "autogol": 0.0, "portiere_imbattuto": 0.0, "nome_giocatore": "sprocati m"}, "inglese r": {"squadra": "parma", "ruolo": "A", "fantavoto": 5.0, "voto": 5.0, "gol_fatti_subiti": 0.0, "ammonizioni": 0.0, "espulsioni": 0.0, "rigori_parati_segnati": 0.0, "autogol": 0.0, "portiere_imbattuto": 0.0, "nome_giocatore": "inglese r"}, "amrabat s": {"squadra": "verona", "ruolo": "C", "fantavoto": 6.0, "voto": 6.5, "gol_fatti_subiti": 0.0, "ammonizioni": -0.5, "espulsioni": 0.0, "rigori_parati_segnati": 0.0, "autogol": 0.0, "portiere_imbattuto": 0.0, "nome_giocatore": "amrabat s"}, "romulo": {"squadra": "brescia", "ruolo": "C", "fantavoto": 6.0, "voto": 6.0, "gol_fatti_subiti": 0.0, "ammonizioni": 0.0, "espulsioni": 0.0, "rigori_parati_segnati": 0.0, "autogol": 0.0, "portiere_imbattuto": 0.0, "nome_giocatore": "romulo"}, "vavro d": {"squadra": "lazio", "ruolo": "D", "fantavoto": 6.0, "voto": 6.0, "gol_fatti_subiti": 0.0, "ammonizioni": 0.0, "espulsioni": 0.0, "rigori_parati_segnati": 0.0, "autogol": 0.0, "portiere_imbattuto": 0.0, "nome_giocatore": "vavro d"}, "veretout j": {"squadra": "roma", "ruolo": "C", "fantavoto": 5.0, "voto": 5.5, "gol_fatti_subiti": 0.0, "ammonizioni": -0.5, "espulsioni": 0.0, "rigori_parati_segnati": 0.0, "autogol": 0.0, "portiere_imbattuto": 0.0, "nome_giocatore": "veretout j"}, "zielinski p": {"squadra": "napoli", "ruolo": "C", "fantavoto": 4.5, "voto": 4.5, "gol_fatti_subiti": 0.0, "ammonizioni": 0.0, "espulsioni": 0.0, "rigori_parati_segnati": 0.0, "autogol": 0.0, "portiere_imbattuto": 0.0, "nome_giocatore": "zielinski p"}, "reca a": {"squadra": "spal", "ruolo": "D", "fantavoto": 8.0, "voto": 7.0, "gol_fatti_subiti": 0.0, "ammonizioni": 0.0, "espulsioni": 0.0, "rigori_parati_segnati": 0.0, "autogol": 0.0, "portiere_imbattuto": 1.0, "nome_giocatore": "reca a"}, "ronaldo c": {"squadra": "juventus", "ruolo": "A", "fantavoto": 13.5, "voto": 7.5, "gol_fatti_subiti": 6.0, "ammonizioni": 0.0, "espulsioni": 0.0, "rigori_parati_segnati": 0.0, "autogol": 0.0, "portiere_imbattuto": 0.0, "nome_giocatore": "ronaldo c"}, "maran": {"squadra": "cagliari", "ruolo": "0", "fantavoto": 6.0, "voto": 6.0, "gol_fatti_subiti": 0.0, "ammonizioni": 0.0, "espulsioni": 0.0, "rigori_parati_segnati": 0.0, "autogol": 0.0, "portiere_imbattuto": 0.0, "nome_giocatore": "maran"}, "caputo f": {"squadra": "sassuolo", "ruolo": "A", "fantavoto": 5.5, "voto": 5.5, "gol_fatti_subiti": 0.0, "ammonizioni": 0.0, "espulsioni": 0.0, "rigori_parati_segnati": 0.0, "autogol": 0.0, "portiere_imbattuto": 0.0, "nome_giocatore": "caputo f"}, "muriel l": {"squadra": "atalanta", "ruolo": "A", "fantavoto": 5.5, "voto": 5.5, "gol_fatti_subiti": 0.0, "ammonizioni": 0.0, "espulsioni": 0.0, "rigori_parati_segnati": 0.0, "autogol": 0.0, "portiere_imbattuto": 0.0, "nome_giocatore": "muriel l"}, "petagna a": {"squadra": "spal", "ruolo": "A", "fantavoto": 10.0, "voto": 7.0, "gol_fatti_subiti": 3.0, "ammonizioni": 0.0, "espulsioni": 0.0, "rigori_parati_segnati": 0.0, "autogol": 0.0, "portiere_imbattuto": 0.0, "nome_giocatore": "petagna a"}, "ospina d": {"squadra": "napoli", "ruolo": "P", "fantavoto": 5.0, "voto": 7.0, "gol_fatti_subiti": -2.0, "ammonizioni": 0.0, "espulsioni": 0.0, "rigori_parati_segnati": 0.0, "autogol": 0.0, "portiere_imbattuto": 0.0, "nome_giocatore": "ospina d"}, "conti a": {"squadra": "milan", "ruolo": "D", "fantavoto": 6.5, "voto": 6.0, "gol_fatti_subiti": 0.0, "ammonizioni": -0.5, "espulsioni": 0.0, "rigori_parati_segnati": 0.0, "autogol": 0.0, "portiere_imbattuto": 1.0, "nome_giocatore": "conti a"}, "klavan r": {"squadra": "cagliari", "ruolo": "D", "fantavoto": 5.5, "voto": 5.5, "gol_fatti_subiti": 0.0, "ammonizioni": 0.0, "espulsioni": 0.0, "rigori_parati_segnati": 0.0, "autogol": 0.0, "portiere_imbattuto": 0.0, "nome_giocatore": "klavan r"}, "mancini g": {"squadra": "roma", "ruolo": "D", "fantavoto": 6.0, "voto": 6.0, "gol_fatti_subiti": 0.0, "ammonizioni": 0.0, "espulsioni": 0.0, "rigori_parati_segnati": 0.0, "autogol": 0.0, "portiere_imbattuto": 0.0, "nome_giocatore": "mancini g"}, "corini": {"squadra": "brescia", "ruolo": "0", "fantavoto": 6.0, "voto": 6.0, "gol_fatti_subiti": 0.0, "ammonizioni": 0.0, "espulsioni": 0.0, "rigori_parati_segnati": 0.0, "autogol": 0.0, "portiere_imbattuto": 0.0, "nome_giocatore": "corini"}, "linetty k": {"squadra": "sampdoria", "ruolo": "C", "fantavoto": 9.0, "voto": 6.0, "gol_fatti_subiti": 3.0, "ammonizioni": 0.0, "espulsioni": 0.0, "rigori_parati_segnati": 0.0, "autogol": 0.0, "portiere_imbattuto": 0.0, "nome_giocatore": "linetty k"}, "jankto j": {"squadra": "sampdoria", "ruolo": "C", "fantavoto": 4.0, "voto": 4.0, "gol_fatti_subiti": 0.0, "ammonizioni": 0.0, "espulsioni": 0.0, "rigori_parati_segnati": 0.0, "autogol": 0.0, "portiere_imbattuto": 0.0, "nome_giocatore": "jankto j"}, "thorsby m": {"squadra": "sampdoria", "ruolo": "C", "fantavoto": 4.0, "voto": 4.0, "gol_fatti_subiti": 0.0, "ammonizioni": 0.0, "espulsioni": 0.0, "rigori_parati_segnati": 0.0, "autogol": 0.0, "portiere_imbattuto": 0.0, "nome_giocatore": "thorsby m"}, "schone l": {"squadra": "genoa", "ruolo": "C", "fantavoto": 7.5, "voto": 6.5, "gol_fatti_subiti": 0.0, "ammonizioni": 0.0, "espulsioni": 0.0, "rigori_parati_segnati": 0.0, "autogol": 0.0, "portiere_imbattuto": 1.0, "nome_giocatore": "schone l"}, "ilicic j": {"squadra": "atalanta", "ruolo": "C", "fantavoto": 9.5, "voto": 6.5, "gol_fatti_subiti": 3.0, "ammonizioni": 0.0, "espulsioni": 0.0, "rigori_parati_segnati": 0.0, "autogol": 0.0, "portiere_imbattuto": 0.0, "nome_giocatore": "ilicic j"}, "bastos": {"squadra": "lazio", "ruolo": "D", "fantavoto": 10.0, "voto": 7.0, "gol_fatti_subiti": 3.0, "ammonizioni": 0.0, "espulsioni": 0.0, "rigori_parati_segnati": 0.0, "autogol": 0.0, "portiere_imbattuto": 0.0, "nome_giocatore": "bastos"}, "jony r": {"squadra": "lazio", "ruolo": "C", "fantavoto": 7.5, "voto": 7.5, "gol_fatti_subiti": 0.0, "ammonizioni": 0.0, "espulsioni": 0.0, "rigori_parati_segnati": 0.0, "autogol": 0.0, "portiere_imbattuto": 0.0, "nome_giocatore": "jony r"}, "lapadula g": {"squadra": "lecce", "ruolo": "A", "fantavoto": 5.5, "voto": 5.5, "gol_fatti_subiti": 0.0, "ammonizioni": 0.0, "espulsioni": 0.0, "rigori_parati_segnati": 0.0, "autogol": 0.0, "portiere_imbattuto": 0.0, "nome_giocatore": "lapadula g"}, "luperto s": {"squadra": "napoli", "ruolo": "D", "fantavoto": 4.0, "voto": 4.0, "gol_fatti_subiti": 0.0, "ammonizioni": 0.0, "espulsioni": 0.0, "rigori_parati_segnati": 0.0, "autogol": 0.0, "portiere_imbattuto": 0.0, "nome_giocatore": "luperto s"}, "djimsiti b": {"squadra": "atalanta", "ruolo": "D", "fantavoto": 5.0, "voto": 5.0, "gol_fatti_subiti": 0.0, "ammonizioni": 0.0, "espulsioni": 0.0, "rigori_parati_segnati": 0.0, "autogol": 0.0, "portiere_imbattuto": 0.0, "nome_giocatore": "djimsiti b"}, "mangraviti m": {"squadra": "brescia", "ruolo": "C", "fantavoto": 5.5, "voto": 5.5, "gol_fatti_subiti": 0.0, "ammonizioni": 0.0, "espulsioni": 0.0, "rigori_parati_segnati": 0.0, "autogol": 0.0, "portiere_imbattuto": 0.0, "nome_giocatore": "mangraviti m"}, "benassi m": {"squadra": "fiorentina", "ruolo": "C", "fantavoto": 8.0, "voto": 7.0, "gol_fatti_subiti": 0.0, "ammonizioni": 0.0, "espulsioni": 0.0, "rigori_parati_segnati": 0.0, "autogol": 0.0, "portiere_imbattuto": 1.0, "nome_giocatore": "benassi m"}, "chancellor j": {"squadra": "brescia", "ruolo": "D", "fantavoto": 6.0, "voto": 6.0, "gol_fatti_subiti": 0.0, "ammonizioni": 0.0, "espulsioni": 0.0, "rigori_parati_segnati": 0.0, "autogol": 0.0, "portiere_imbattuto": 0.0, "nome_giocatore": "chancellor j"}, "barella n": {"squadra": "inter", "ruolo": "C", "fantavoto": 5.5, "voto": 5.5, "gol_fatti_subiti": 0.0, "ammonizioni": 0.0, "espulsioni": 0.0, "rigori_parati_segnati": 0.0, "autogol": 0.0, "portiere_imbattuto": 0.0, "nome_giocatore": "barella n"}, "mandragora r": {"squadra": "udinese", "ruolo": "C", "fantavoto": 5.5, "voto": 5.5, "gol_fatti_subiti": 0.0, "ammonizioni": 0.0, "espulsioni": 0.0, "rigori_parati_segnati": 0.0, "autogol": 0.0, "portiere_imbattuto": 0.0, "nome_giocatore": "mandragora r"}, "murru n": {"squadra": "sampdoria", "ruolo": "D", "fantavoto": 4.5, "voto": 4.5, "gol_fatti_subiti": 0.0, "ammonizioni": 0.0, "espulsioni": 0.0, "rigori_parati_segnati": 0.0, "autogol": 0.0, "portiere_imbattuto": 0.0, "nome_giocatore": "murru n"}, "vieira r": {"squadra": "sampdoria", "ruolo": "C", "fantavoto": 4.0, "voto": 4.5, "gol_fatti_subiti": 0.0, "ammonizioni": -0.5, "espulsioni": 0.0, "rigori_parati_segnati": 0.0, "autogol": 0.0, "portiere_imbattuto": 0.0, "nome_giocatore": "vieira r"}, "torregrossa e": {"squadra": "brescia", "ruolo": "A", "fantavoto": 13.5, "voto": 8.0, "gol_fatti_subiti": 6.0, "ammonizioni": -0.5, "espulsioni": 0.0, "rigori_parati_segnati": 0.0, "autogol": 0.0, "portiere_imbattuto": 0.0, "nome_giocatore": "torregrossa e"}, "rebic a": {"squadra": "milan", "ruolo": "A", "fantavoto": 14.0, "voto": 8.0, "gol_fatti_subiti": 6.0, "ammonizioni": 0.0, "espulsioni": 0.0, "rigori_parati_segnati": 0.0, "autogol": 0.0, "portiere_imbattuto": 0.0, "nome_giocatore": "rebic a"}, "patric": {"squadra": "lazio", "ruolo": "D", "fantavoto": 7.5, "voto": 7.5, "gol_fatti_subiti": 0.0, "ammonizioni": 0.0, "espulsioni": 0.0, "rigori_parati_segnati": 0.0, "autogol": 0.0, "portiere_imbattuto": 0.0, "nome_giocatore": "patric"}, "kessie f": {"squadra": "milan", "ruolo": "C", "fantavoto": 6.5, "voto": 6.5, "gol_fatti_subiti": 0.0, "ammonizioni": 0.0, "espulsioni": 0.0, "rigori_parati_segnati": 0.0, "autogol": 0.0, "portiere_imbattuto": 0.0, "nome_giocatore": "kessie f"}, "muldur m": {"squadra": "sassuolo", "ruolo": "D", "fantavoto": NaN, "voto": NaN, "gol_fatti_subiti": 0.0, "ammonizioni": 0.0, "espulsioni": 0.0, "rigori_parati_segnati": 0.0, "autogol": 0.0, "portiere_imbattuto": 0.0, "nome_giocatore": "muldur m"}, "cistana a": {"squadra": "brescia", "ruolo": "D", "fantavoto": 5.5, "voto": 5.5, "gol_fatti_subiti": 0.0, "ammonizioni": 0.0, "espulsioni": 0.0, "rigori_parati_segnati": 0.0, "autogol": 0.0, "portiere_imbattuto": 0.0, "nome_giocatore": "cistana a"}, "paz n": {"squadra": "bologna", "ruolo": "D", "fantavoto": 6.0, "voto": 6.0, "gol_fatti_subiti": 0.0, "ammonizioni": 0.0, "espulsioni": 0.0, "rigori_parati_segnati": 0.0, "autogol": 0.0, "portiere_imbattuto": 0.0, "nome_giocatore": "paz n"}, "iachini": {"squadra": "fiorentina", "ruolo": "0", "fantavoto": 7.5, "voto": 8.0, "gol_fatti_subiti": 0.0, "ammonizioni": -0.5, "espulsioni": 0.0, "rigori_parati_segnati": 0.0, "autogol": 0.0, "portiere_imbattuto": 0.0, "nome_giocatore": "iachini"}, "dalbert h": {"squadra": "fiorentina", "ruolo": "D", "fantavoto": 6.0, "voto": 6.5, "gol_fatti_subiti": 0.0, "ammonizioni": -0.5, "espulsioni": 0.0, "rigori_parati_segnati": 0.0, "autogol": 0.0, "portiere_imbattuto": 0.0, "nome_giocatore": "dalbert h"}, "mihajlovic": {"squadra": "bologna", "ruolo": "0", "fantavoto": 6.0, "voto": 6.0, "gol_fatti_subiti": 0.0, "ammonizioni": 0.0, "espulsioni": 0.0, "rigori_parati_segnati": 0.0, "autogol": 0.0, "portiere_imbattuto": 0.0, "nome_giocatore": "mihajlovic"}, "orsolini r": {"squadra": "bologna", "ruolo": "A", "fantavoto": 5.0, "voto": 5.0, "gol_fatti_subiti": 0.0, "ammonizioni": 0.0, "espulsioni": 0.0, "rigori_parati_segnati": 0.0, "autogol": 0.0, "portiere_imbattuto": 0.0, "nome_giocatore": "orsolini r"}, "sepe l": {"squadra": "parma", "ruolo": "P", "fantavoto": 4.5, "voto": 6.5, "gol_fatti_subiti": -2.0, "ammonizioni": 0.0, "espulsioni": 0.0, "rigori_parati_segnati": 0.0, "autogol": 0.0, "portiere_imbattuto": 0.0, "nome_giocatore": "sepe l"}, "danilo ds": {"squadra": "juventus", "ruolo": "D", "fantavoto": 6.5, "voto": 6.5, "gol_fatti_subiti": 0.0, "ammonizioni": 0.0, "espulsioni": 0.0, "rigori_parati_segnati": 0.0, "autogol": 0.0, "portiere_imbattuto": 0.0, "nome_giocatore": "danilo ds"}, "donati g": {"squadra": "lecce", "ruolo": "D", "fantavoto": 6.0, "voto": 6.5, "gol_fatti_subiti": 0.0, "ammonizioni": -0.5, "espulsioni": 0.0, "rigori_parati_segnati": 0.0, "autogol": 0.0, "portiere_imbattuto": 0.0, "nome_giocatore": "donati g"}, "nuytinck b": {"squadra": "udinese", "ruolo": "D", "fantavoto": 6.0, "voto": 6.0, "gol_fatti_subiti": 0.0, "ammonizioni": 0.0, "espulsioni": 0.0, "rigori_parati_segnati": 0.0, "autogol": 0.0, "portiere_imbattuto": 0.0, "nome_giocatore": "nuytinck b"}, "sensi s": {"squadra": "inter", "ruolo": "C", "fantavoto": 5.5, "voto": 5.5, "gol_fatti_subiti": 0.0, "ammonizioni": 0.0, "espulsioni": 0.0, "rigori_parati_segnati": 0.0, "autogol": 0.0, "portiere_imbattuto": 0.0, "nome_giocatore": "sensi s"}, "biraghi c": {"squadra": "inter", "ruolo": "D", "fantavoto": 7.0, "voto": 6.0, "gol_fatti_subiti": 0.0, "ammonizioni": 0.0, "espulsioni": 0.0, "rigori_parati_segnati": 0.0, "autogol": 0.0, "portiere_imbattuto": 1.0, "nome_giocatore": "biraghi c"}, "n koulou n": {"squadra": "torino", "ruolo": "D", "fantavoto": 6.0, "voto": 6.0, "gol_fatti_subiti": 0.0, "ammonizioni": 0.0, "espulsioni": 0.0, "rigori_parati_segnati": 0.0, "autogol": 0.0, "portiere_imbattuto": 0.0, "nome_giocatore": "n koulou n"}, "belotti a": {"squadra": "torino", "ruolo": "A", "fantavoto": 6.5, "voto": 6.5, "gol_fatti_subiti": 0.0, "ammonizioni": 0.0, "espulsioni": 0.0, "rigori_parati_segnati": 0.0, "autogol": 0.0, "portiere_imbattuto": 0.0, "nome_giocatore": "belotti a"}, "malinovskyi r": {"squadra": "atalanta", "ruolo": "C", "fantavoto": 5.0, "voto": 5.0, "gol_fatti_subiti": 0.0, "ammonizioni": 0.0, "espulsioni": 0.0, "rigori_parati_segnati": 0.0, "autogol": 0.0, "portiere_imbattuto": 0.0, "nome_giocatore": "malinovskyi r"}, "lirola p": {"squadra": "fiorentina", "ruolo": "D", "fantavoto": 8.0, "voto": 7.0, "gol_fatti_subiti": 0.0, "ammonizioni": 0.0, "espulsioni": 0.0, "rigori_parati_segnati": 0.0, "autogol": 0.0, "portiere_imbattuto": 1.0, "nome_giocatore": "lirola p"}, "scozzarella m": {"squadra": "parma", "ruolo": "C", "fantavoto": 5.5, "voto": 5.5, "gol_fatti_subiti": 0.0, "ammonizioni": 0.0, "espulsioni": 0.0, "rigori_parati_segnati": 0.0, "autogol": 0.0, "portiere_imbattuto": 0.0, "nome_giocatore": "scozzarella m"}, "mancosu m": {"squadra": "lecce", "ruolo": "C", "fantavoto": 10.0, "voto": 7.0, "gol_fatti_subiti": 3.0, "ammonizioni": 0.0, "espulsioni": 0.0, "rigori_parati_segnati": 0.0, "autogol": 0.0, "portiere_imbattuto": 0.0, "nome_giocatore": "mancosu m"}, "cionek t": {"squadra": "spal", "ruolo": "D", "fantavoto": 5.5, "voto": 5.5, "gol_fatti_subiti": 0.0, "ammonizioni": 0.0, "espulsioni": 0.0, "rigori_parati_segnati": 0.0, "autogol": 0.0, "portiere_imbattuto": 0.0, "nome_giocatore": "cionek t"}, "lucioni f": {"squadra": "lecce", "ruolo": "D", "fantavoto": 6.5, "voto": 6.5, "gol_fatti_subiti": 0.0, "ammonizioni": 0.0, "espulsioni": 0.0, "rigori_parati_segnati": 0.0, "autogol": 0.0, "portiere_imbattuto": 0.0, "nome_giocatore": "lucioni f"}, "ibrahimovic z": {"squadra": "milan", "ruolo": "A", "fantavoto": 6.0, "voto": 6.5, "gol_fatti_subiti": 0.0, "ammonizioni": -0.5, "espulsioni": 0.0, "rigori_parati_segnati": 0.0, "autogol": 0.0, "portiere_imbattuto": 0.0, "nome_giocatore": "ibrahimovic z"}, "majer z": {"squadra": "lecce", "ruolo": "C", "fantavoto": 7.5, "voto": 6.5, "gol_fatti_subiti": 0.0, "ammonizioni": 0.0, "espulsioni": 0.0, "rigori_parati_segnati": 0.0, "autogol": 0.0, "portiere_imbattuto": 1.0, "nome_giocatore": "majer z"}, "silvestri m": {"squadra": "verona", "ruolo": "P", "fantavoto": 4.5, "voto": 5.5, "gol_fatti_subiti": -1.0, "ammonizioni": 0.0, "espulsioni": 0.0, "rigori_parati_segnati": 0.0, "autogol": 0.0, "portiere_imbattuto": 0.0, "nome_giocatore": "silvestri m"}, "biraschi d": {"squadra": "genoa", "ruolo": "D", "fantavoto": 3.5, "voto": 5.5, "gol_fatti_subiti": 0.0, "ammonizioni": 0.0, "espulsioni": 0.0, "rigori_parati_segnati": 0.0, "autogol": -2.0, "portiere_imbattuto": 0.0, "nome_giocatore": "biraschi d"}, "palomino j": {"squadra": "atalanta", "ruolo": "D", "fantavoto": 5.0, "voto": 5.5, "gol_fatti_subiti": 0.0, "ammonizioni": -0.5, "espulsioni": 0.0, "rigori_parati_segnati": 0.0, "autogol": 0.0, "portiere_imbattuto": 0.0, "nome_giocatore": "palomino j"}, "berardi d": {"squadra": "sassuolo", "ruolo": "A", "fantavoto": 10.0, "voto": 7.0, "gol_fatti_subiti": 3.0, "ammonizioni": 0.0, "espulsioni": 0.0, "rigori_parati_segnati": 0.0, "autogol": 0.0, "portiere_imbattuto": 0.0, "nome_giocatore": "berardi d"}, "schouten j": {"squadra": "bologna", "ruolo": "C", "fantavoto": 5.5, "voto": 6.0, "gol_fatti_subiti": 0.0, "ammonizioni": -0.5, "espulsioni": 0.0, "rigori_parati_segnati": 0.0, "autogol": 0.0, "portiere_imbattuto": 0.0, "nome_giocatore": "schouten j"}, "sirigu s": {"squadra": "torino", "ruolo": "P", "fantavoto": 4.0, "voto": 6.0, "gol_fatti_subiti": -2.0, "ammonizioni": 0.0, "espulsioni": 0.0, "rigori_parati_segnati": 0.0, "autogol": 0.0, "portiere_imbattuto": 0.0, "nome_giocatore": "sirigu s"}, "ionita a": {"squadra": "cagliari", "ruolo": "C", "fantavoto": 5.5, "voto": 6.0, "gol_fatti_subiti": 0.0, "ammonizioni": -0.5, "espulsioni": 0.0, "rigori_parati_segnati": 0.0, "autogol": 0.0, "portiere_imbattuto": 0.0, "nome_giocatore": "ionita a"}, "higuain g": {"squadra": "juventus", "ruolo": "A", "fantavoto": 6.0, "voto": 6.0, "gol_fatti_subiti": 0.0, "ammonizioni": 0.0, "espulsioni": 0.0, "rigori_parati_segnati": 0.0, "autogol": 0.0, "portiere_imbattuto": 0.0, "nome_giocatore": "higuain g"}, "bastoni a": {"squadra": "inter", "ruolo": "D", "fantavoto": 9.0, "voto": 6.0, "gol_fatti_subiti": 3.0, "ammonizioni": 0.0, "espulsioni": 0.0, "rigori_parati_segnati": 0.0, "autogol": 0.0, "portiere_imbattuto": 0.0, "nome_giocatore": "bastoni a"}, "magnanelli f": {"squadra": "sassuolo", "ruolo": "C", "fantavoto": NaN, "voto": NaN, "gol_fatti_subiti": 0.0, "ammonizioni": 0.0, "espulsioni": 0.0, "rigori_parati_segnati": 0.0, "autogol": 0.0, "portiere_imbattuto": 0.0, "nome_giocatore": "magnanelli f"}, "barrow m": {"squadra": "bologna", "ruolo": "A", "fantavoto": 5.5, "voto": 5.5, "gol_fatti_subiti": 0.0, "ammonizioni": 0.0, "espulsioni": 0.0, "rigori_parati_segnati": 0.0, "autogol": 0.0, "portiere_imbattuto": 0.0, "nome_giocatore": "barrow m"}, "joao pedro": {"squadra": "cagliari", "ruolo": "C", "fantavoto": 13.5, "voto": 7.5, "gol_fatti_subiti": 6.0, "ammonizioni": 0.0, "espulsioni": 0.0, "rigori_parati_segnati": 0.0, "autogol": 0.0, "portiere_imbattuto": 0.0, "nome_giocatore": "joao pedro"}, "hernani j": {"squadra": "parma", "ruolo": "C", "fantavoto": 5.5, "voto": 5.5, "gol_fatti_subiti": 0.0, "ammonizioni": 0.0, "espulsioni": 0.0, "rigori_parati_segnati": 0.0, "autogol": 0.0, "portiere_imbattuto": 0.0, "nome_giocatore": "hernani j"}, "mazzarri": {"squadra": "torino", "ruolo": "0", "fantavoto": 5.0, "voto": 5.0, "gol_fatti_subiti": 0.0, "ammonizioni": 0.0, "espulsioni": 0.0, "rigori_parati_segnati": 0.0, "autogol": 0.0, "portiere_imbattuto": 0.0, "nome_giocatore": "mazzarri"}, "ekong t": {"squadra": "udinese", "ruolo": "D", "fantavoto": 5.5, "voto": 5.5, "gol_fatti_subiti": 0.0, "ammonizioni": 0.0, "espulsioni": 0.0, "rigori_parati_segnati": 0.0, "autogol": 0.0, "portiere_imbattuto": 0.0, "nome_giocatore": "ekong t"}, "meccariello b": {"squadra": "lecce", "ruolo": "D", "fantavoto": NaN, "voto": NaN, "gol_fatti_subiti": 0.0, "ammonizioni": -0.5, "espulsioni": 0.0, "rigori_parati_segnati": 0.0, "autogol": 0.0, "portiere_imbattuto": 0.0, "nome_giocatore": "meccariello b"}, "agudelo k": {"squadra": "genoa", "ruolo": "C", "fantavoto": NaN, "voto": NaN, "gol_fatti_subiti": 0.0, "ammonizioni": 0.0, "espulsioni": 0.0, "rigori_parati_segnati": 0.0, "autogol": 0.0, "portiere_imbattuto": 0.0, "nome_giocatore": "agudelo k"}, "berisha e": {"squadra": "spal", "ruolo": "P", "fantavoto": 6.0, "voto": 7.0, "gol_fatti_subiti": -1.0, "ammonizioni": 0.0, "espulsioni": 0.0, "rigori_parati_segnati": 0.0, "autogol": 0.0, "portiere_imbattuto": 0.0, "nome_giocatore": "berisha e"}, "babacar k": {"squadra": "lecce", "ruolo": "A", "fantavoto": 6.5, "voto": 6.5, "gol_fatti_subiti": 0.0, "ammonizioni": 0.0, "espulsioni": 0.0, "rigori_parati_segnati": 0.0, "autogol": 0.0, "portiere_imbattuto": 0.0, "nome_giocatore": "babacar k"}, "skorupski l": {"squadra": "bologna", "ruolo": "P", "fantavoto": 7.0, "voto": 8.0, "gol_fatti_subiti": -1.0, "ammonizioni": 0.0, "espulsioni": 0.0, "rigori_parati_segnati": 0.0, "autogol": 0.0, "portiere_imbattuto": 0.0, "nome_giocatore": "skorupski l"}, "sportiello m": {"squadra": "atalanta", "ruolo": "P", "fantavoto": 4.0, "voto": 6.0, "gol_fatti_subiti": -2.0, "ammonizioni": 0.0, "espulsioni": 0.0, "rigori_parati_segnati": 0.0, "autogol": 0.0, "portiere_imbattuto": 0.0, "nome_giocatore": "sportiello m"}, "pezzella ger": {"squadra": "fiorentina", "ruolo": "D", "fantavoto": 6.5, "voto": 6.5, "gol_fatti_subiti": 0.0, "ammonizioni": 0.0, "espulsioni": 0.0, "rigori_parati_segnati": 0.0, "autogol": 0.0, "portiere_imbattuto": 0.0, "nome_giocatore": "pezzella ger"}, "kucka j": {"squadra": "parma", "ruolo": "C", "fantavoto": 6.5, "voto": 6.5, "gol_fatti_subiti": 0.0, "ammonizioni": 0.0, "espulsioni": 0.0, "rigori_parati_segnati": 0.0, "autogol": 0.0, "portiere_imbattuto": 0.0, "nome_giocatore": "kucka j"}, "bani m": {"squadra": "bologna", "ruolo": "D", "fantavoto": 7.5, "voto": 5.5, "gol_fatti_subiti": 3.0, "ammonizioni": 0.0, "espulsioni": -1.0, "rigori_parati_segnati": 0.0, "autogol": 0.0, "portiere_imbattuto": 0.0, "nome_giocatore": "bani m"}, "vicari f": {"squadra": "spal", "ruolo": "D", "fantavoto": 5.0, "voto": 5.5, "gol_fatti_subiti": 0.0, "ammonizioni": -0.5, "espulsioni": 0.0, "rigori_parati_segnati": 0.0, "autogol": 0.0, "portiere_imbattuto": 0.0, "nome_giocatore": "vicari f"}, "kyriakopoulos g": {"squadra": "sassuolo", "ruolo": "D", "fantavoto": 5.5, "voto": 6.0, "gol_fatti_subiti": 0.0, "ammonizioni": -0.5, "espulsioni": 0.0, "rigori_parati_segnati": 0.0, "autogol": 0.0, "portiere_imbattuto": 0.0, "nome_giocatore": "kyriakopoulos g"}, "musso j": {"squadra": "udinese", "ruolo": "P", "fantavoto": 2.5, "voto": 5.5, "gol_fatti_subiti": -3.0, "ammonizioni": 0.0, "espulsioni": 0.0, "rigori_parati_segnati": 0.0, "autogol": 0.0, "portiere_imbattuto": 0.0, "nome_giocatore": "musso j"}, "faraoni d": {"squadra": "verona", "ruolo": "D", "fantavoto": 6.0, "voto": 6.0, "gol_fatti_subiti": 0.0, "ammonizioni": 0.0, "espulsioni": 0.0, "rigori_parati_segnati": 0.0, "autogol": 0.0, "portiere_imbattuto": 0.0, "nome_giocatore": "faraoni d"}, "olsen r": {"squadra": "cagliari", "ruolo": "P", "fantavoto": 4.0, "voto": 6.0, "gol_fatti_subiti": -2.0, "ammonizioni": 0.0, "espulsioni": 0.0, "rigori_parati_segnati": 0.0, "autogol": 0.0, "portiere_imbattuto": 0.0, "nome_giocatore": "olsen r"}, "lasagna k": {"squadra": "udinese", "ruolo": "A", "fantavoto": 10.0, "voto": 7.0, "gol_fatti_subiti": 3.0, "ammonizioni": 0.0, "espulsioni": 0.0, "rigori_parati_segnati": 0.0, "autogol": 0.0, "portiere_imbattuto": 0.0, "nome_giocatore": "lasagna k"}, "meite s": {"squadra": "torino", "ruolo": "C", "fantavoto": NaN, "voto": NaN, "gol_fatti_subiti": 0.0, "ammonizioni": 0.0, "espulsioni": 0.0, "rigori_parati_segnati": 0.0, "autogol": 0.0, "portiere_imbattuto": 0.0, "nome_giocatore": "meite s"}, "sottil r": {"squadra": "fiorentina", "ruolo": "A", "fantavoto": NaN, "voto": NaN, "gol_fatti_subiti": 0.0, "ammonizioni": 0.0, "espulsioni": 0.0, "rigori_parati_segnati": 0.0, "autogol": 0.0, "portiere_imbattuto": 0.0, "nome_giocatore": "sottil r"}, "freuler r": {"squadra": "atalanta", "ruolo": "C", "fantavoto": 5.0, "voto": 5.0, "gol_fatti_subiti": 0.0, "ammonizioni": 0.0, "espulsioni": 0.0, "rigori_parati_segnati": 0.0, "autogol": 0.0, "portiere_imbattuto": 0.0, "nome_giocatore": "freuler r"}, "locatelli m": {"squadra": "sassuolo", "ruolo": "C", "fantavoto": 4.5, "voto": 6.5, "gol_fatti_subiti": 0.0, "ammonizioni": 0.0, "espulsioni": 0.0, "rigori_parati_segnati": 0.0, "autogol": -2.0, "portiere_imbattuto": 0.0, "nome_giocatore": "locatelli m"}, "strefezza g": {"squadra": "spal", "ruolo": "C", "fantavoto": 6.5, "voto": 6.5, "gol_fatti_subiti": 0.0, "ammonizioni": 0.0, "espulsioni": 0.0, "rigori_parati_segnati": 0.0, "autogol": 0.0, "portiere_imbattuto": 0.0, "nome_giocatore": "strefezza g"}, "kulusevski d": {"squadra": "parma", "ruolo": "C", "fantavoto": 5.0, "voto": 5.0, "gol_fatti_subiti": 0.0, "ammonizioni": 0.0, "espulsioni": 0.0, "rigori_parati_segnati": 0.0, "autogol": 0.0, "portiere_imbattuto": 0.0, "nome_giocatore": "kulusevski d"}, "berenguer a": {"squadra": "torino", "ruolo": "C", "fantavoto": 5.5, "voto": 5.5, "gol_fatti_subiti": 0.0, "ammonizioni": 0.0, "espulsioni": 0.0, "rigori_parati_segnati": 0.0, "autogol": 0.0, "portiere_imbattuto": 0.0, "nome_giocatore": "berenguer a"}, "fofana s": {"squadra": "udinese", "ruolo": "C", "fantavoto": 6.0, "voto": 6.0, "gol_fatti_subiti": 0.0, "ammonizioni": 0.0, "espulsioni": 0.0, "rigori_parati_segnati": 0.0, "autogol": 0.0, "portiere_imbattuto": 0.0, "nome_giocatore": "fofana s"}, "pazzini g": {"squadra": "verona", "ruolo": "A", "fantavoto": NaN, "voto": NaN, "gol_fatti_subiti": 0.0, "ammonizioni": 0.0, "espulsioni": 0.0, "rigori_parati_segnati": 0.0, "autogol": 0.0, "portiere_imbattuto": 0.0, "nome_giocatore": "pazzini g"}, "mbaye i": {"squadra": "bologna", "ruolo": "D", "fantavoto": 5.0, "voto": 5.5, "gol_fatti_subiti": 0.0, "ammonizioni": -0.5, "espulsioni": 0.0, "rigori_parati_segnati": 0.0, "autogol": 0.0, "portiere_imbattuto": 0.0, "nome_giocatore": "mbaye i"}, "chabot j": {"squadra": "sampdoria", "ruolo": "D", "fantavoto": 2.0, "voto": 3.0, "gol_fatti_subiti": 0.0, "ammonizioni": 0.0, "espulsioni": -1.0, "rigori_parati_segnati": 0.0, "autogol": 0.0, "portiere_imbattuto": 0.0, "nome_giocatore": "chabot j"}, "caicedo f": {"squadra": "lazio", "ruolo": "A", "fantavoto": 10.0, "voto": 7.0, "gol_fatti_subiti": 3.0, "ammonizioni": 0.0, "espulsioni": 0.0, "rigori_parati_segnati": 0.0, "autogol": 0.0, "portiere_imbattuto": 0.0, "nome_giocatore": "caicedo f"}, "soriano r": {"squadra": "bologna", "ruolo": "C", "fantavoto": 6.0, "voto": 6.0, "gol_fatti_subiti": 0.0, "ammonizioni": 0.0, "espulsioni": 0.0, "rigori_parati_segnati": 0.0, "autogol": 0.0, "portiere_imbattuto": 0.0, "nome_giocatore": "soriano r"}, "djidji k": {"squadra": "torino", "ruolo": "D", "fantavoto": 4.5, "voto": 5.0, "gol_fatti_subiti": 0.0, "ammonizioni": -0.5, "espulsioni": 0.0, "rigori_parati_segnati": 0.0, "autogol": 0.0, "portiere_imbattuto": 0.0, "nome_giocatore": "djidji k"}, "matuidi b": {"squadra": "juventus", "ruolo": "C", "fantavoto": 6.0, "voto": 6.0, "gol_fatti_subiti": 0.0, "ammonizioni": 0.0, "espulsioni": 0.0, "rigori_parati_segnati": 0.0, "autogol": 0.0, "portiere_imbattuto": 0.0, "nome_giocatore": "matuidi b"}, "pellegrini lu": {"squadra": "cagliari", "ruolo": "D", "fantavoto": 4.5, "voto": 5.0, "gol_fatti_subiti": 0.0, "ammonizioni": -0.5, "espulsioni": 0.0, "rigori_parati_segnati": 0.0, "autogol": 0.0, "portiere_imbattuto": 0.0, "nome_giocatore": "pellegrini lu"}, "pandev g": {"squadra": "genoa", "ruolo": "A", "fantavoto": 10.0, "voto": 7.0, "gol_fatti_subiti": 3.0, "ammonizioni": 0.0, "espulsioni": 0.0, "rigori_parati_segnati": 0.0, "autogol": 0.0, "portiere_imbattuto": 0.0, "nome_giocatore": "pandev g"}, "bennacer i": {"squadra": "milan", "ruolo": "C", "fantavoto": 6.0, "voto": 6.5, "gol_fatti_subiti": 0.0, "ammonizioni": -0.5, "espulsioni": 0.0, "rigori_parati_segnati": 0.0, "autogol": 0.0, "portiere_imbattuto": 0.0, "nome_giocatore": "bennacer i"}, "kluivert j": {"squadra": "roma", "ruolo": "C", "fantavoto": 6.0, "voto": 6.0, "gol_fatti_subiti": 0.0, "ammonizioni": 0.0, "espulsioni": 0.0, "rigori_parati_segnati": 0.0, "autogol": 0.0, "portiere_imbattuto": 0.0, "nome_giocatore": "kluivert j"}, "pioli": {"squadra": "milan", "ruolo": "0", "fantavoto": 6.5, "voto": 7.0, "gol_fatti_subiti": 0.0, "ammonizioni": -0.5, "espulsioni": 0.0, "rigori_parati_segnati": 0.0, "autogol": 0.0, "portiere_imbattuto": 0.0, "nome_giocatore": "pioli"}, "zaccagni m": {"squadra": "verona", "ruolo": "C", "fantavoto": 5.5, "voto": 6.0, "gol_fatti_subiti": 0.0, "ammonizioni": -0.5, "espulsioni": 0.0, "rigori_parati_segnati": 0.0, "autogol": 0.0, "portiere_imbattuto": 0.0, "nome_giocatore": "zaccagni m"}, "conte": {"squadra": "inter", "ruolo": "0", "fantavoto": 5.5, "voto": 5.5, "gol_fatti_subiti": 0.0, "ammonizioni": 0.0, "espulsioni": 0.0, "rigori_parati_segnati": 0.0, "autogol": 0.0, "portiere_imbattuto": 0.0, "nome_giocatore": "conte"}, "larsen s": {"squadra": "udinese", "ruolo": "D", "fantavoto": 11.0, "voto": 7.0, "gol_fatti_subiti": 3.0, "ammonizioni": 0.0, "espulsioni": 0.0, "rigori_parati_segnati": 0.0, "autogol": 0.0, "portiere_imbattuto": 1.0, "nome_giocatore": "larsen s"}, "bonazzoli f": {"squadra": "sampdoria", "ruolo": "A", "fantavoto": 5.5, "voto": 5.5, "gol_fatti_subiti": 0.0, "ammonizioni": 0.0, "espulsioni": 0.0, "rigori_parati_segnati": 0.0, "autogol": 0.0, "portiere_imbattuto": 0.0, "nome_giocatore": "bonazzoli f"}, "barreca a": {"squadra": "genoa", "ruolo": "D", "fantavoto": 6.0, "voto": 6.0, "gol_fatti_subiti": 0.0, "ammonizioni": 0.0, "espulsioni": 0.0, "rigori_parati_segnati": 0.0, "autogol": 0.0, "portiere_imbattuto": 0.0, "nome_giocatore": "barreca a"}, "ranieri": {"squadra": "sampdoria", "ruolo": "0", "fantavoto": 5.0, "voto": 5.0, "gol_fatti_subiti": 0.0, "ammonizioni": 0.0, "espulsioni": 0.0, "rigori_parati_segnati": 0.0, "autogol": 0.0, "portiere_imbattuto": 0.0, "nome_giocatore": "ranieri"}, "danilo l": {"squadra": "bologna", "ruolo": "D", "fantavoto": 6.0, "voto": 6.0, "gol_fatti_subiti": 0.0, "ammonizioni": 0.0, "espulsioni": 0.0, "rigori_parati_segnati": 0.0, "autogol": 0.0, "portiere_imbattuto": 0.0, "nome_giocatore": "danilo l"}, "lukic s": {"squadra": "torino", "ruolo": "C", "fantavoto": 5.5, "voto": 5.5, "gol_fatti_subiti": 0.0, "ammonizioni": 0.0, "espulsioni": 0.0, "rigori_parati_segnati": 0.0, "autogol": 0.0, "portiere_imbattuto": 0.0, "nome_giocatore": "lukic s"}, "sturaro s": {"squadra": "genoa", "ruolo": "C", "fantavoto": 6.0, "voto": 6.0, "gol_fatti_subiti": 0.0, "ammonizioni": 0.0, "espulsioni": 0.0, "rigori_parati_segnati": 0.0, "autogol": 0.0, "portiere_imbattuto": 0.0, "nome_giocatore": "sturaro s"}, "peluso f": {"squadra": "sassuolo", "ruolo": "D", "fantavoto": 6.0, "voto": 6.0, "gol_fatti_subiti": 0.0, "ammonizioni": 0.0, "espulsioni": 0.0, "rigori_parati_segnati": 0.0, "autogol": 0.0, "portiere_imbattuto": 0.0, "nome_giocatore": "peluso f"}, "joronen j": {"squadra": "brescia", "ruolo": "P", "fantavoto": 6.0, "voto": 8.0, "gol_fatti_subiti": -2.0, "ammonizioni": 0.0, "espulsioni": 0.0, "rigori_parati_segnati": 0.0, "autogol": 0.0, "portiere_imbattuto": 0.0, "nome_giocatore": "joronen j"}, "okaka s": {"squadra": "udinese", "ruolo": "A", "fantavoto": 6.5, "voto": 6.5, "gol_fatti_subiti": 0.0, "ammonizioni": 0.0, "espulsioni": 0.0, "rigori_parati_segnati": 0.0, "autogol": 0.0, "portiere_imbattuto": 0.0, "nome_giocatore": "okaka s"}, "gomez a": {"squadra": "atalanta", "ruolo": "C", "fantavoto": 5.5, "voto": 5.5, "gol_fatti_subiti": 0.0, "ammonizioni": 0.0, "espulsioni": 0.0, "rigori_parati_segnati": 0.0, "autogol": 0.0, "portiere_imbattuto": 0.0, "nome_giocatore": "gomez a"}, "milenkovic n": {"squadra": "fiorentina", "ruolo": "D", "fantavoto": 7.0, "voto": 7.0, "gol_fatti_subiti": 0.0, "ammonizioni": 0.0, "espulsioni": 0.0, "rigori_parati_segnati": 0.0, "autogol": 0.0, "portiere_imbattuto": 0.0, "nome_giocatore": "milenkovic n"}, "colley o": {"squadra": "sampdoria", "ruolo": "D", "fantavoto": 3.5, "voto": 4.0, "gol_fatti_subiti": 0.0, "ammonizioni": -0.5, "espulsioni": 0.0, "rigori_parati_segnati": 0.0, "autogol": 0.0, "portiere_imbattuto": 0.0, "nome_giocatore": "colley o"}, "balotelli m": {"squadra": "brescia", "ruolo": "A", "fantavoto": 3.0, "voto": 4.0, "gol_fatti_subiti": 0.0, "ammonizioni": 0.0, "espulsioni": -1.0, "rigori_parati_segnati": 0.0, "autogol": 0.0, "portiere_imbattuto": 0.0, "nome_giocatore": "balotelli m"}, "immobile c": {"squadra": "lazio", "ruolo": "A", "fantavoto": 18.0, "voto": 9.0, "gol_fatti_subiti": 9.0, "ammonizioni": 0.0, "espulsioni": 0.0, "rigori_parati_segnati": 0.0, "autogol": 0.0, "portiere_imbattuto": 0.0, "nome_giocatore": "immobile c"}, "krunic r": {"squadra": "milan", "ruolo": "C", "fantavoto": 6.0, "voto": 6.0, "gol_fatti_subiti": 0.0, "ammonizioni": 0.0, "espulsioni": 0.0, "rigori_parati_segnati": 0.0, "autogol": 0.0, "portiere_imbattuto": 0.0, "nome_giocatore": "krunic r"}, "nestorovski i": {"squadra": "udinese", "ruolo": "A", "fantavoto": NaN, "voto": NaN, "gol_fatti_subiti": 0.0, "ammonizioni": 0.0, "espulsioni": 0.0, "rigori_parati_segnati": 0.0, "autogol": 0.0, "portiere_imbattuto": 0.0, "nome_giocatore": "nestorovski i"}, "cetin m": {"squadra": "roma", "ruolo": "D", "fantavoto": NaN, "voto": NaN, "gol_fatti_subiti": 0.0, "ammonizioni": 0.0, "espulsioni": 0.0, "rigori_parati_segnati": 0.0, "autogol": 0.0, "portiere_imbattuto": 0.0, "nome_giocatore": "cetin m"}, "de roon m": {"squadra": "atalanta", "ruolo": "C", "fantavoto": 4.5, "voto": 5.0, "gol_fatti_subiti": 0.0, "ammonizioni": -0.5, "espulsioni": 0.0, "rigori_parati_segnati": 0.0, "autogol": 0.0, "portiere_imbattuto": 0.0, "nome_giocatore": "de roon m"}, "caceres m": {"squadra": "fiorentina", "ruolo": "D", "fantavoto": 7.0, "voto": 7.0, "gol_fatti_subiti": 0.0, "ammonizioni": 0.0, "espulsioni": 0.0, "rigori_parati_segnati": 0.0, "autogol": 0.0, "portiere_imbattuto": 0.0, "nome_giocatore": "caceres m"}, "gosens r": {"squadra": "atalanta", "ruolo": "D", "fantavoto": 6.0, "voto": 6.0, "gol_fatti_subiti": 0.0, "ammonizioni": 0.0, "espulsioni": 0.0, "rigori_parati_segnati": 0.0, "autogol": 0.0, "portiere_imbattuto": 0.0, "nome_giocatore": "gosens r"}, "castrovilli g": {"squadra": "fiorentina", "ruolo": "C", "fantavoto": 7.5, "voto": 7.5, "gol_fatti_subiti": 0.0, "ammonizioni": 0.0, "espulsioni": 0.0, "rigori_parati_segnati": 0.0, "autogol": 0.0, "portiere_imbattuto": 0.0, "nome_giocatore": "castrovilli g"}, "milik a": {"squadra": "napoli", "ruolo": "A", "fantavoto": 5.0, "voto": 5.0, "gol_fatti_subiti": 0.0, "ammonizioni": 0.0, "espulsioni": 0.0, "rigori_parati_segnati": 0.0, "autogol": 0.0, "portiere_imbattuto": 0.0, "nome_giocatore": "milik a"}, "ndoj e": {"squadra": "brescia", "ruolo": "C", "fantavoto": 5.0, "voto": 5.5, "gol_fatti_subiti": 0.0, "ammonizioni": -0.5, "espulsioni": 0.0, "rigori_parati_segnati": 0.0, "autogol": 0.0, "portiere_imbattuto": 0.0, "nome_giocatore": "ndoj e"}, "ghiglione p": {"squadra": "genoa", "ruolo": "D", "fantavoto": 5.5, "voto": 5.5, "gol_fatti_subiti": 0.0, "ammonizioni": 0.0, "espulsioni": 0.0, "rigori_parati_segnati": 0.0, "autogol": 0.0, "portiere_imbattuto": 0.0, "nome_giocatore": "ghiglione p"}, "simeone g": {"squadra": "cagliari", "ruolo": "A", "fantavoto": 6.0, "voto": 6.0, "gol_fatti_subiti": 0.0, "ammonizioni": 0.0, "espulsioni": 0.0, "rigori_parati_segnati": 0.0, "autogol": 0.0, "portiere_imbattuto": 0.0, "nome_giocatore": "simeone g"}, "sarri": {"squadra": "juventus", "ruolo": "0", "fantavoto": 6.5, "voto": 6.5, "gol_fatti_subiti": 0.0, "ammonizioni": 0.0, "espulsioni": 0.0, "rigori_parati_segnati": 0.0, "autogol": 0.0, "portiere_imbattuto": 0.0, "nome_giocatore": "sarri"}, "de silvestri l": {"squadra": "torino", "ruolo": "D", "fantavoto": 5.5, "voto": 5.5, "gol_fatti_subiti": 0.0, "ammonizioni": 0.0, "espulsioni": 0.0, "rigori_parati_segnati": 0.0, "autogol": 0.0, "portiere_imbattuto": 0.0, "nome_giocatore": "de silvestri l"}, "hernandez t": {"squadra": "milan", "ruolo": "D", "fantavoto": 10.5, "voto": 7.5, "gol_fatti_subiti": 3.0, "ammonizioni": 0.0, "espulsioni": 0.0, "rigori_parati_segnati": 0.0, "autogol": 0.0, "portiere_imbattuto": 0.0, "nome_giocatore": "hernandez t"}, "chiesa f": {"squadra": "fiorentina", "ruolo": "C", "fantavoto": 11.0, "voto": 8.0, "gol_fatti_subiti": 3.0, "ammonizioni": 0.0, "espulsioni": 0.0, "rigori_parati_segnati": 0.0, "autogol": 0.0, "portiere_imbattuto": 0.0, "nome_giocatore": "chiesa f"}, "cristante b": {"squadra": "roma", "ruolo": "C", "fantavoto": 6.0, "voto": 6.0, "gol_fatti_subiti": 0.0, "ammonizioni": 0.0, "espulsioni": 0.0, "rigori_parati_segnati": 0.0, "autogol": 0.0, "portiere_imbattuto": 0.0, "nome_giocatore": "cristante b"}, "di francesco f": {"squadra": "spal", "ruolo": "C", "fantavoto": 5.5, "voto": 6.0, "gol_fatti_subiti": 0.0, "ammonizioni": -0.5, "espulsioni": 0.0, "rigori_parati_segnati": 0.0, "autogol": 0.0, "portiere_imbattuto": 0.0, "nome_giocatore": "di francesco f"}, "dragowski b": {"squadra": "fiorentina", "ruolo": "P", "fantavoto": 6.5, "voto": 6.5, "gol_fatti_subiti": 0.0, "ammonizioni": 0.0, "espulsioni": 0.0, "rigori_parati_segnati": 0.0, "autogol": 0.0, "portiere_imbattuto": 0.0, "nome_giocatore": "dragowski b"}, "sansone n": {"squadra": "bologna", "ruolo": "A", "fantavoto": 6.0, "voto": 6.5, "gol_fatti_subiti": 0.0, "ammonizioni": -0.5, "espulsioni": 0.0, "rigori_parati_segnati": 0.0, "autogol": 0.0, "portiere_imbattuto": 0.0, "nome_giocatore": "sansone n"}, "spinazzola l": {"squadra": "roma", "ruolo": "D", "fantavoto": 7.0, "voto": 7.0, "gol_fatti_subiti": 0.0, "ammonizioni": 0.0, "espulsioni": 0.0, "rigori_parati_segnati": 0.0, "autogol": 0.0, "portiere_imbattuto": 0.0, "nome_giocatore": "spinazzola l"}, "consigli a": {"squadra": "sassuolo", "ruolo": "P", "fantavoto": 5.0, "voto": 6.0, "gol_fatti_subiti": -1.0, "ammonizioni": 0.0, "espulsioni": 0.0, "rigori_parati_segnati": 0.0, "autogol": 0.0, "portiere_imbattuto": 0.0, "nome_giocatore": "consigli a"}, "rabiot a": {"squadra": "juventus", "ruolo": "C", "fantavoto": 6.0, "voto": 6.0, "gol_fatti_subiti": 0.0, "ammonizioni": 0.0, "espulsioni": 0.0, "rigori_parati_segnati": 0.0, "autogol": 0.0, "portiere_imbattuto": 0.0, "nome_giocatore": "rabiot a"}, "tomiyasu t": {"squadra": "bologna", "ruolo": "D", "fantavoto": 5.0, "voto": 5.0, "gol_fatti_subiti": 0.0, "ammonizioni": 0.0, "espulsioni": 0.0, "rigori_parati_segnati": 0.0, "autogol": 0.0, "portiere_imbattuto": 0.0, "nome_giocatore": "tomiyasu t"}, "caldara m": {"squadra": "atalanta", "ruolo": "D", "fantavoto": 5.0, "voto": 5.0, "gol_fatti_subiti": 0.0, "ammonizioni": 0.0, "espulsioni": 0.0, "rigori_parati_segnati": 0.0, "autogol": 0.0, "portiere_imbattuto": 0.0, "nome_giocatore": "caldara m"}, "dzeko e": {"squadra": "roma", "ruolo": "A", "fantavoto": 9.0, "voto": 6.5, "gol_fatti_subiti": 3.0, "ammonizioni": -0.5, "espulsioni": 0.0, "rigori_parati_segnati": 0.0, "autogol": 0.0, "portiere_imbattuto": 0.0, "nome_giocatore": "dzeko e"}, "ramsey a": {"squadra": "juventus", "ruolo": "C", "fantavoto": 5.5, "voto": 5.5, "gol_fatti_subiti": 0.0, "ammonizioni": 0.0, "espulsioni": 0.0, "rigori_parati_segnati": 0.0, "autogol": 0.0, "portiere_imbattuto": 0.0, "nome_giocatore": "ramsey a"}, "martinez l": {"squadra": "inter", "ruolo": "A", "fantavoto": 5.0, "voto": 5.0, "gol_fatti_subiti": 0.0, "ammonizioni": 0.0, "espulsioni": 0.0, "rigori_parati_segnati": 0.0, "autogol": 0.0, "portiere_imbattuto": 0.0, "nome_giocatore": "martinez l"}, "rrahmani a": {"squadra": "verona", "ruolo": "D", "fantavoto": 6.0, "voto": 6.0, "gol_fatti_subiti": 0.0, "ammonizioni": 0.0, "espulsioni": 0.0, "rigori_parati_segnati": 0.0, "autogol": 0.0, "portiere_imbattuto": 0.0, "nome_giocatore": "rrahmani a"}, "cuadrado j": {"squadra": "juventus", "ruolo": "C", "fantavoto": 6.0, "voto": 6.0, "gol_fatti_subiti": 0.0, "ammonizioni": 0.0, "espulsioni": 0.0, "rigori_parati_segnati": 0.0, "autogol": 0.0, "portiere_imbattuto": 0.0, "nome_giocatore": "cuadrado j"}, "pjanic m": {"squadra": "juventus", "ruolo": "C", "fantavoto": 5.0, "voto": 5.0, "gol_fatti_subiti": 0.0, "ammonizioni": 0.0, "espulsioni": 0.0, "rigori_parati_segnati": 0.0, "autogol": 0.0, "portiere_imbattuto": 0.0, "nome_giocatore": "pjanic m"}, "bjarnason b": {"squadra": "brescia", "ruolo": "C", "fantavoto": 6.0, "voto": 6.0, "gol_fatti_subiti": 0.0, "ammonizioni": 0.0, "espulsioni": 0.0, "rigori_parati_segnati": 0.0, "autogol": 0.0, "portiere_imbattuto": 0.0, "nome_giocatore": "bjarnason b"}, "borini f": {"squadra": "verona", "ruolo": "C", "fantavoto": 10.0, "voto": 7.0, "gol_fatti_subiti": 3.0, "ammonizioni": 0.0, "espulsioni": 0.0, "rigori_parati_segnati": 0.0, "autogol": 0.0, "portiere_imbattuto": 0.0, "nome_giocatore": "borini f"}, "iacoponi s": {"squadra": "parma", "ruolo": "D", "fantavoto": 6.0, "voto": 6.0, "gol_fatti_subiti": 0.0, "ammonizioni": 0.0, "espulsioni": 0.0, "rigori_parati_segnati": 0.0, "autogol": 0.0, "portiere_imbattuto": 0.0, "nome_giocatore": "iacoponi s"}, "sema k": {"squadra": "udinese", "ruolo": "D", "fantavoto": 5.0, "voto": 5.5, "gol_fatti_subiti": 0.0, "ammonizioni": -0.5, "espulsioni": 0.0, "rigori_parati_segnati": 0.0, "autogol": 0.0, "portiere_imbattuto": 0.0, "nome_giocatore": "sema k"}, "millico v": {"squadra": "torino", "ruolo": "A", "fantavoto": 6.0, "voto": 6.0, "gol_fatti_subiti": 0.0, "ammonizioni": 0.0, "espulsioni": 0.0, "rigori_parati_segnati": 0.0, "autogol": 0.0, "portiere_imbattuto": 0.0, "nome_giocatore": "millico v"}, "petriccione j": {"squadra": "lecce", "ruolo": "C", "fantavoto": 7.0, "voto": 7.0, "gol_fatti_subiti": 0.0, "ammonizioni": 0.0, "espulsioni": 0.0, "rigori_parati_segnati": 0.0, "autogol": 0.0, "portiere_imbattuto": 0.0, "nome_giocatore": "petriccione j"}, "santon d": {"squadra": "roma", "ruolo": "D", "fantavoto": 6.0, "voto": 6.0, "gol_fatti_subiti": 0.0, "ammonizioni": 0.0, "espulsioni": 0.0, "rigori_parati_segnati": 0.0, "autogol": 0.0, "portiere_imbattuto": 0.0, "nome_giocatore": "santon d"}, "romero c": {"squadra": "genoa", "ruolo": "D", "fantavoto": 4.0, "voto": 4.5, "gol_fatti_subiti": 0.0, "ammonizioni": -0.5, "espulsioni": 0.0, "rigori_parati_segnati": 0.0, "autogol": 0.0, "portiere_imbattuto": 0.0, "nome_giocatore": "romero c"}, "lozano h": {"squadra": "napoli", "ruolo": "A", "fantavoto": 5.5, "voto": 5.5, "gol_fatti_subiti": 0.0, "ammonizioni": 0.0, "espulsioni": 0.0, "rigori_parati_segnati": 0.0, "autogol": 0.0, "portiere_imbattuto": 0.0, "nome_giocatore": "lozano h"}, "cornelius a": {"squadra": "parma", "ruolo": "A", "fantavoto": 9.5, "voto": 6.5, "gol_fatti_subiti": 3.0, "ammonizioni": 0.0, "espulsioni": 0.0, "rigori_parati_segnati": 0.0, "autogol": 0.0, "portiere_imbattuto": 0.0, "nome_giocatore": "cornelius a"}, "igor j": {"squadra": "spal", "ruolo": "D", "fantavoto": 6.0, "voto": 6.0, "gol_fatti_subiti": 0.0, "ammonizioni": 0.0, "espulsioni": 0.0, "rigori_parati_segnati": 0.0, "autogol": 0.0, "portiere_imbattuto": 0.0, "nome_giocatore": "igor j"}, "brozovic m": {"squadra": "inter", "ruolo": "C", "fantavoto": 6.5, "voto": 6.5, "gol_fatti_subiti": 0.0, "ammonizioni": 0.0, "espulsioni": 0.0, "rigori_parati_segnati": 0.0, "autogol": 0.0, "portiere_imbattuto": 0.0, "nome_giocatore": "brozovic m"}, "obiang p": {"squadra": "sassuolo", "ruolo": "C", "fantavoto": 6.0, "voto": 6.0, "gol_fatti_subiti": 0.0, "ammonizioni": 0.0, "espulsioni": 0.0, "rigori_parati_segnati": 0.0, "autogol": 0.0, "portiere_imbattuto": 0.0, "nome_giocatore": "obiang p"}, "bonucci l": {"squadra": "juventus", "ruolo": "D", "fantavoto": 6.5, "voto": 6.5, "gol_fatti_subiti": 0.0, "ammonizioni": 0.0, "espulsioni": 0.0, "rigori_parati_segnati": 0.0, "autogol": 0.0, "portiere_imbattuto": 0.0, "nome_giocatore": "bonucci l"}, "veloso m": {"squadra": "verona", "ruolo": "C", "fantavoto": 6.0, "voto": 6.0, "gol_fatti_subiti": 0.0, "ammonizioni": 0.0, "espulsioni": 0.0, "rigori_parati_segnati": 0.0, "autogol": 0.0, "portiere_imbattuto": 0.0, "nome_giocatore": "veloso m"}, "favilli a": {"squadra": "genoa", "ruolo": "A", "fantavoto": 5.5, "voto": 5.5, "gol_fatti_subiti": 0.0, "ammonizioni": 0.0, "espulsioni": 0.0, "rigori_parati_segnati": 0.0, "autogol": 0.0, "portiere_imbattuto": 0.0, "nome_giocatore": "favilli a"}, "dybala p": {"squadra": "juventus", "ruolo": "A", "fantavoto": 7.5, "voto": 6.5, "gol_fatti_subiti": 0.0, "ammonizioni": 0.0, "espulsioni": 0.0, "rigori_parati_segnati": 0.0, "autogol": 0.0, "portiere_imbattuto": 1.0, "nome_giocatore": "dybala p"}, "deiola a": {"squadra": "lecce", "ruolo": "C", "fantavoto": 5.5, "voto": 5.5, "gol_fatti_subiti": 0.0, "ammonizioni": 0.0, "espulsioni": 0.0, "rigori_parati_segnati": 0.0, "autogol": 0.0, "portiere_imbattuto": 0.0, "nome_giocatore": "deiola a"}, "gagliolo r": {"squadra": "parma", "ruolo": "D", "fantavoto": 5.5, "voto": 5.5, "gol_fatti_subiti": 0.0, "ammonizioni": 0.0, "espulsioni": 0.0, "rigori_parati_segnati": 0.0, "autogol": 0.0, "portiere_imbattuto": 0.0, "nome_giocatore": "gagliolo r"}, "tonali s": {"squadra": "brescia", "ruolo": "C", "fantavoto": 5.5, "voto": 6.0, "gol_fatti_subiti": 0.0, "ammonizioni": -0.5, "espulsioni": 0.0, "rigori_parati_segnati": 0.0, "autogol": 0.0, "portiere_imbattuto": 0.0, "nome_giocatore": "tonali s"}, "valoti m": {"squadra": "spal", "ruolo": "C", "fantavoto": 10.0, "voto": 7.5, "gol_fatti_subiti": 3.0, "ammonizioni": -0.5, "espulsioni": 0.0, "rigori_parati_segnati": 0.0, "autogol": 0.0, "portiere_imbattuto": 0.0, "nome_giocatore": "valoti m"}, "toljan j": {"squadra": "sassuolo", "ruolo": "D", "fantavoto": 5.5, "voto": 6.0, "gol_fatti_subiti": 0.0, "ammonizioni": -0.5, "espulsioni": 0.0, "rigori_parati_segnati": 0.0, "autogol": 0.0, "portiere_imbattuto": 0.0, "nome_giocatore": "toljan j"}, "cutrone p": {"squadra": "fiorentina", "ruolo": "A", "fantavoto": 6.5, "voto": 6.5, "gol_fatti_subiti": 0.0, "ammonizioni": 0.0, "espulsioni": 0.0, "rigori_parati_segnati": 0.0, "autogol": 0.0, "portiere_imbattuto": 0.0, "nome_giocatore": "cutrone p"}, "demme d": {"squadra": "napoli", "ruolo": "C", "fantavoto": 5.0, "voto": 5.5, "gol_fatti_subiti": 0.0, "ammonizioni": -0.5, "espulsioni": 0.0, "rigori_parati_segnati": 0.0, "autogol": 0.0, "portiere_imbattuto": 0.0, "nome_giocatore": "demme d"}, "oliva c": {"squadra": "cagliari", "ruolo": "C", "fantavoto": 6.0, "voto": 6.0, "gol_fatti_subiti": 0.0, "ammonizioni": 0.0, "espulsioni": 0.0, "rigori_parati_segnati": 0.0, "autogol": 0.0, "portiere_imbattuto": 0.0, "nome_giocatore": "oliva c"}, "de vrij s": {"squadra": "inter", "ruolo": "D", "fantavoto": 6.5, "voto": 6.5, "gol_fatti_subiti": 0.0, "ammonizioni": 0.0, "espulsioni": 0.0, "rigori_parati_segnati": 0.0, "autogol": 0.0, "portiere_imbattuto": 0.0, "nome_giocatore": "de vrij s"}, "valero b": {"squadra": "inter", "ruolo": "C", "fantavoto": NaN, "voto": NaN, "gol_fatti_subiti": 0.0, "ammonizioni": -0.5, "espulsioni": 0.0, "rigori_parati_segnati": 0.0, "autogol": 0.0, "portiere_imbattuto": 0.0, "nome_giocatore": "valero b"}, "romagnoli a": {"squadra": "milan", "ruolo": "D", "fantavoto": 6.5, "voto": 6.5, "gol_fatti_subiti": 0.0, "ammonizioni": 0.0, "espulsioni": 0.0, "rigori_parati_segnati": 0.0, "autogol": 0.0, "portiere_imbattuto": 0.0, "nome_giocatore": "romagnoli a"}, "inzaghi s": {"squadra": "lazio", "ruolo": "0", "fantavoto": 8.0, "voto": 8.0, "gol_fatti_subiti": 0.0, "ammonizioni": 0.0, "espulsioni": 0.0, "rigori_parati_segnati": 0.0, "autogol": 0.0, "portiere_imbattuto": 0.0, "nome_giocatore": "inzaghi s"}, "sabelli s": {"squadra": "brescia", "ruolo": "D", "fantavoto": 6.5, "voto": 6.5, "gol_fatti_subiti": 0.0, "ammonizioni": 0.0, "espulsioni": 0.0, "rigori_parati_segnati": 0.0, "autogol": 0.0, "portiere_imbattuto": 0.0, "nome_giocatore": "sabelli s"}, "boga j": {"squadra": "sassuolo", "ruolo": "C", "fantavoto": 11.5, "voto": 7.5, "gol_fatti_subiti": 3.0, "ammonizioni": 0.0, "espulsioni": 0.0, "rigori_parati_segnati": 0.0, "autogol": 0.0, "portiere_imbattuto": 1.0, "nome_giocatore": "boga j"}, "pellegrini lo": {"squadra": "roma", "ruolo": "C", "fantavoto": 8.0, "voto": 7.0, "gol_fatti_subiti": 0.0, "ammonizioni": 0.0, "espulsioni": 0.0, "rigori_parati_segnati": 0.0, "autogol": 0.0, "portiere_imbattuto": 1.0, "nome_giocatore": "pellegrini lo"}, "valdifiori m": {"squadra": "spal", "ruolo": "C", "fantavoto": NaN, "voto": NaN, "gol_fatti_subiti": 0.0, "ammonizioni": 0.0, "espulsioni": 0.0, "rigori_parati_segnati": 0.0, "autogol": 0.0, "portiere_imbattuto": 0.0, "nome_giocatore": "valdifiori m"}, "semplici": {"squadra": "spal", "ruolo": "0", "fantavoto": 7.0, "voto": 7.0, "gol_fatti_subiti": 0.0, "ammonizioni": 0.0, "espulsioni": 0.0, "rigori_parati_segnati": 0.0, "autogol": 0.0, "portiere_imbattuto": 0.0, "nome_giocatore": "semplici"}, "de maio s": {"squadra": "udinese", "ruolo": "D", "fantavoto": NaN, "voto": NaN, "gol_fatti_subiti": 0.0, "ammonizioni": 0.0, "espulsioni": 0.0, "rigori_parati_segnati": 0.0, "autogol": 0.0, "portiere_imbattuto": 0.0, "nome_giocatore": "de maio s"}, "pessina m": {"squadra": "verona", "ruolo": "C", "fantavoto": 6.0, "voto": 6.0, "gol_fatti_subiti": 0.0, "ammonizioni": 0.0, "espulsioni": 0.0, "rigori_parati_segnati": 0.0, "autogol": 0.0, "portiere_imbattuto": 0.0, "nome_giocatore": "pessina m"}, "alex sandro": {"squadra": "juventus", "ruolo": "D", "fantavoto": 6.0, "voto": 6.0, "gol_fatti_subiti": 0.0, "ammonizioni": 0.0, "espulsioni": 0.0, "rigori_parati_segnati": 0.0, "autogol": 0.0, "portiere_imbattuto": 0.0, "nome_giocatore": "alex sandro"}, "santander f": {"squadra": "bologna", "ruolo": "A", "fantavoto": 5.5, "voto": 5.5, "gol_fatti_subiti": 0.0, "ammonizioni": 0.0, "espulsioni": 0.0, "rigori_parati_segnati": 0.0, "autogol": 0.0, "portiere_imbattuto": 0.0, "nome_giocatore": "santander f"}, "dessena d": {"squadra": "brescia", "ruolo": "C", "fantavoto": 6.0, "voto": 6.0, "gol_fatti_subiti": 0.0, "ammonizioni": 0.0, "espulsioni": 0.0, "rigori_parati_segnati": 0.0, "autogol": 0.0, "portiere_imbattuto": 0.0, "nome_giocatore": "dessena d"}, "llorente f": {"squadra": "napoli", "ruolo": "A", "fantavoto": NaN, "voto": NaN, "gol_fatti_subiti": 0.0, "ammonizioni": 0.0, "espulsioni": 0.0, "rigori_parati_segnati": 0.0, "autogol": 0.0, "portiere_imbattuto": 0.0, "nome_giocatore": "llorente f"}, "radovanovic i": {"squadra": "genoa", "ruolo": "C", "fantavoto": NaN, "voto": NaN, "gol_fatti_subiti": 0.0, "ammonizioni": 0.0, "espulsioni": 0.0, "rigori_parati_segnati": 0.0, "autogol": 0.0, "portiere_imbattuto": 0.0, "nome_giocatore": "radovanovic i"}, "costa do": {"squadra": "juventus", "ruolo": "C", "fantavoto": NaN, "voto": NaN, "gol_fatti_subiti": 0.0, "ammonizioni": 0.0, "espulsioni": 0.0, "rigori_parati_segnati": 0.0, "autogol": 0.0, "portiere_imbattuto": 0.0, "nome_giocatore": "costa do"}, "cigarini l": {"squadra": "cagliari", "ruolo": "C", "fantavoto": 5.5, "voto": 5.5, "gol_fatti_subiti": 0.0, "ammonizioni": 0.0, "espulsioni": 0.0, "rigori_parati_segnati": 0.0, "autogol": 0.0, "portiere_imbattuto": 0.0, "nome_giocatore": "cigarini l"}, "augello t": {"squadra": "sampdoria", "ruolo": "D", "fantavoto": 5.0, "voto": 5.0, "gol_fatti_subiti": 0.0, "ammonizioni": 0.0, "espulsioni": 0.0, "rigori_parati_segnati": 0.0, "autogol": 0.0, "portiere_imbattuto": 0.0, "nome_giocatore": "augello t"}, "sanabria a": {"squadra": "genoa", "ruolo": "A", "fantavoto": 5.0, "voto": 5.0, "gol_fatti_subiti": 0.0, "ammonizioni": 0.0, "espulsioni": 0.0, "rigori_parati_segnati": 0.0, "autogol": 0.0, "portiere_imbattuto": 0.0, "nome_giocatore": "sanabria a"}, "ter avest": {"squadra": "udinese", "ruolo": "D", "fantavoto": NaN, "voto": NaN, "gol_fatti_subiti": 0.0, "ammonizioni": 0.0, "espulsioni": 0.0, "rigori_parati_segnati": 0.0, "autogol": 0.0, "portiere_imbattuto": 0.0, "nome_giocatore": "ter avest"}, "gunter k": {"squadra": "verona", "ruolo": "D", "fantavoto": 6.0, "voto": 6.0, "gol_fatti_subiti": 0.0, "ammonizioni": 0.0, "espulsioni": 0.0, "rigori_parati_segnati": 0.0, "autogol": 0.0, "portiere_imbattuto": 0.0, "nome_giocatore": "gunter k"}, "diawara a": {"squadra": "roma", "ruolo": "C", "fantavoto": 6.5, "voto": 6.5, "gol_fatti_subiti": 0.0, "ammonizioni": 0.0, "espulsioni": 0.0, "rigori_parati_segnati": 0.0, "autogol": 0.0, "portiere_imbattuto": 0.0, "nome_giocatore": "diawara a"}, "gabbiadini m": {"squadra": "sampdoria", "ruolo": "A", "fantavoto": 5.5, "voto": 5.5, "gol_fatti_subiti": 0.0, "ammonizioni": 0.0, "espulsioni": 0.0, "rigori_parati_segnati": 0.0, "autogol": 0.0, "portiere_imbattuto": 0.0, "nome_giocatore": "gabbiadini m"}, "fonseca": {"squadra": "roma", "ruolo": "0", "fantavoto": 6.5, "voto": 6.5, "gol_fatti_subiti": 0.0, "ammonizioni": 0.0, "espulsioni": 0.0, "rigori_parati_segnati": 0.0, "autogol": 0.0, "portiere_imbattuto": 0.0, "nome_giocatore": "fonseca"}, "poli a": {"squadra": "bologna", "ruolo": "C", "fantavoto": 4.5, "voto": 5.0, "gol_fatti_subiti": 0.0, "ammonizioni": -0.5, "espulsioni": 0.0, "rigori_parati_segnati": 0.0, "autogol": 0.0, "portiere_imbattuto": 0.0, "nome_giocatore": "poli a"}, "acerbi f": {"squadra": "lazio", "ruolo": "D", "fantavoto": 9.0, "voto": 8.0, "gol_fatti_subiti": 0.0, "ammonizioni": 0.0, "espulsioni": 0.0, "rigori_parati_segnati": 0.0, "autogol": 0.0, "portiere_imbattuto": 1.0, "nome_giocatore": "acerbi f"}, "nainggolan r": {"squadra": "cagliari", "ruolo": "C", "fantavoto": 7.5, "voto": 7.5, "gol_fatti_subiti": 0.0, "ammonizioni": 0.0, "espulsioni": 0.0, "rigori_parati_segnati": 0.0, "autogol": 0.0, "portiere_imbattuto": 0.0, "nome_giocatore": "nainggolan r"}, "zapata d": {"squadra": "atalanta", "ruolo": "A", "fantavoto": 7.0, "voto": 6.0, "gol_fatti_subiti": 0.0, "ammonizioni": 0.0, "espulsioni": 0.0, "rigori_parati_segnati": 0.0, "autogol": 0.0, "portiere_imbattuto": 1.0, "nome_giocatore": "zapata d"}, "dominguez n": {"squadra": "bologna", "ruolo": "C", "fantavoto": 6.0, "voto": 6.0, "gol_fatti_subiti": 0.0, "ammonizioni": 0.0, "espulsioni": 0.0, "rigori_parati_segnati": 0.0, "autogol": 0.0, "portiere_imbattuto": 0.0, "nome_giocatore": "dominguez n"}, "cassata f": {"squadra": "genoa", "ruolo": "C", "fantavoto": 5.0, "voto": 5.5, "gol_fatti_subiti": 0.0, "ammonizioni": -0.5, "espulsioni": 0.0, "rigori_parati_segnati": 0.0, "autogol": 0.0, "portiere_imbattuto": 0.0, "nome_giocatore": "cassata f"}, "dawidowicz p": {"squadra": "verona", "ruolo": "D", "fantavoto": 6.0, "voto": 6.0, "gol_fatti_subiti": 0.0, "ammonizioni": 0.0, "espulsioni": 0.0, "rigori_parati_segnati": 0.0, "autogol": 0.0, "portiere_imbattuto": 0.0, "nome_giocatore": "dawidowicz p"}, "bonaventura g": {"squadra": "milan", "ruolo": "C", "fantavoto": 6.0, "voto": 6.0, "gol_fatti_subiti": 0.0, "ammonizioni": 0.0, "espulsioni": 0.0, "rigori_parati_segnati": 0.0, "autogol": 0.0, "portiere_imbattuto": 0.0, "nome_giocatore": "bonaventura g"}, "nandez n": {"squadra": "cagliari", "ruolo": "C", "fantavoto": 6.5, "voto": 6.0, "gol_fatti_subiti": 0.0, "ammonizioni": -0.5, "espulsioni": 0.0, "rigori_parati_segnati": 0.0, "autogol": 0.0, "portiere_imbattuto": 1.0, "nome_giocatore": "nandez n"}, "goldaniga e": {"squadra": "genoa", "ruolo": "D", "fantavoto": 6.5, "voto": 6.5, "gol_fatti_subiti": 0.0, "ammonizioni": 0.0, "espulsioni": 0.0, "rigori_parati_segnati": 0.0, "autogol": 0.0, "portiere_imbattuto": 0.0, "nome_giocatore": "goldaniga e"}, "liverani": {"squadra": "lecce", "ruolo": "0", "fantavoto": 7.0, "voto": 7.0, "gol_fatti_subiti": 0.0, "ammonizioni": 0.0, "espulsioni": 0.0, "rigori_parati_segnati": 0.0, "autogol": 0.0, "portiere_imbattuto": 0.0, "nome_giocatore": "liverani"}, "callejon j": {"squadra": "napoli", "ruolo": "C", "fantavoto": 5.0, "voto": 5.0, "gol_fatti_subiti": 0.0, "ammonizioni": 0.0, "espulsioni": 0.0, "rigori_parati_segnati": 0.0, "autogol": 0.0, "portiere_imbattuto": 0.0, "nome_giocatore": "callejon j"}, "siligardi l": {"squadra": "parma", "ruolo": "A", "fantavoto": NaN, "voto": NaN, "gol_fatti_subiti": 0.0, "ammonizioni": 0.0, "espulsioni": 0.0, "rigori_parati_segnati": 0.0, "autogol": 0.0, "portiere_imbattuto": 0.0, "nome_giocatore": "siligardi l"}, "rossettini l": {"squadra": "lecce", "ruolo": "D", "fantavoto": 6.5, "voto": 6.5, "gol_fatti_subiti": 0.0, "ammonizioni": 0.0, "espulsioni": 0.0, "rigori_parati_segnati": 0.0, "autogol": 0.0, "portiere_imbattuto": 0.0, "nome_giocatore": "rossettini l"}, "smalling c": {"squadra": "roma", "ruolo": "D", "fantavoto": 6.5, "voto": 6.5, "gol_fatti_subiti": 0.0, "ammonizioni": 0.0, "espulsioni": 0.0, "rigori_parati_segnati": 0.0, "autogol": 0.0, "portiere_imbattuto": 0.0, "nome_giocatore": "smalling c"}, "dabo b": {"squadra": "spal", "ruolo": "C", "fantavoto": 6.5, "voto": 6.5, "gol_fatti_subiti": 0.0, "ammonizioni": 0.0, "espulsioni": 0.0, "rigori_parati_segnati": 0.0, "autogol": 0.0, "portiere_imbattuto": 0.0, "nome_giocatore": "dabo b"}, "gabriel f": {"squadra": "lecce", "ruolo": "P", "fantavoto": 5.5, "voto": 6.5, "gol_fatti_subiti": -1.0, "ammonizioni": 0.0, "espulsioni": 0.0, "rigori_parati_segnati": 0.0, "autogol": 0.0, "portiere_imbattuto": 0.0, "nome_giocatore": "gabriel f"}, "pasalic m": {"squadra": "atalanta", "ruolo": "C", "fantavoto": 5.5, "voto": 5.5, "gol_fatti_subiti": 0.0, "ammonizioni": 0.0, "espulsioni": 0.0, "rigori_parati_segnati": 0.0, "autogol": 0.0, "portiere_imbattuto": 0.0, "nome_giocatore": "pasalic m"}, "sanchez a": {"squadra": "inter", "ruolo": "A", "fantavoto": NaN, "voto": NaN, "gol_fatti_subiti": 0.0, "ammonizioni": 0.0, "espulsioni": 0.0, "rigori_parati_segnati": 0.0, "autogol": 0.0, "portiere_imbattuto": 0.0, "nome_giocatore": "sanchez a"}, "cerri a": {"squadra": "cagliari", "ruolo": "A", "fantavoto": NaN, "voto": NaN, "gol_fatti_subiti": 0.0, "ammonizioni": 0.0, "espulsioni": 0.0, "rigori_parati_segnati": 0.0, "autogol": 0.0, "portiere_imbattuto": 0.0, "nome_giocatore": "cerri a"}, "izzo a": {"squadra": "torino", "ruolo": "D", "fantavoto": 6.0, "voto": 6.0, "gol_fatti_subiti": 0.0, "ammonizioni": 0.0, "espulsioni": 0.0, "rigori_parati_segnati": 0.0, "autogol": 0.0, "portiere_imbattuto": 0.0, "nome_giocatore": "izzo a"}, "skriniar m": {"squadra": "inter", "ruolo": "D", "fantavoto": 5.5, "voto": 5.5, "gol_fatti_subiti": 0.0, "ammonizioni": 0.0, "espulsioni": 0.0, "rigori_parati_segnati": 0.0, "autogol": 0.0, "portiere_imbattuto": 0.0, "nome_giocatore": "skriniar m"}, "de paul r": {"squadra": "udinese", "ruolo": "C", "fantavoto": 7.0, "voto": 7.0, "gol_fatti_subiti": 0.0, "ammonizioni": 0.0, "espulsioni": 0.0, "rigori_parati_segnati": 0.0, "autogol": 0.0, "portiere_imbattuto": 0.0, "nome_giocatore": "de paul r"}, "lukaku r": {"squadra": "inter", "ruolo": "A", "fantavoto": 5.5, "voto": 5.5, "gol_fatti_subiti": 0.0, "ammonizioni": 0.0, "espulsioni": 0.0, "rigori_parati_segnati": 0.0, "autogol": 0.0, "portiere_imbattuto": 0.0, "nome_giocatore": "lukaku r"}, "candreva a": {"squadra": "inter", "ruolo": "C", "fantavoto": 4.5, "voto": 5.0, "gol_fatti_subiti": 0.0, "ammonizioni": -0.5, "espulsioni": 0.0, "rigori_parati_segnati": 0.0, "autogol": 0.0, "portiere_imbattuto": 0.0, "nome_giocatore": "candreva a"}, "djuricic f": {"squadra": "sassuolo", "ruolo": "C", "fantavoto": 6.0, "voto": 6.0, "gol_fatti_subiti": 0.0, "ammonizioni": 0.0, "espulsioni": 0.0, "rigori_parati_segnati": 0.0, "autogol": 0.0, "portiere_imbattuto": 0.0, "nome_giocatore": "djuricic f"}, "godin d": {"squadra": "inter", "ruolo": "D", "fantavoto": 6.0, "voto": 6.0, "gol_fatti_subiti": 0.0, "ammonizioni": 0.0, "espulsioni": 0.0, "rigori_parati_segnati": 0.0, "autogol": 0.0, "portiere_imbattuto": 0.0, "nome_giocatore": "godin d"}, "pulgar e": {"squadra": "fiorentina", "ruolo": "C", "fantavoto": 6.5, "voto": 6.5, "gol_fatti_subiti": 0.0, "ammonizioni": 0.0, "espulsioni": 0.0, "rigori_parati_segnati": 0.0, "autogol": 0.0, "portiere_imbattuto": 0.0, "nome_giocatore": "pulgar e"}, "verdi s": {"squadra": "torino", "ruolo": "C", "fantavoto": 4.0, "voto": 4.5, "gol_fatti_subiti": 0.0, "ammonizioni": -0.5, "espulsioni": 0.0, "rigori_parati_segnati": 0.0, "autogol": 0.0, "portiere_imbattuto": 0.0, "nome_giocatore": "verdi s"}, "di carmine s": {"squadra": "verona", "ruolo": "A", "fantavoto": 5.5, "voto": 5.5, "gol_fatti_subiti": 0.0, "ammonizioni": 0.0, "espulsioni": 0.0, "rigori_parati_segnati": 0.0, "autogol": 0.0, "portiere_imbattuto": 0.0, "nome_giocatore": "di carmine s"}, "falco f": {"squadra": "lecce", "ruolo": "A", "fantavoto": 6.0, "voto": 6.0, "gol_fatti_subiti": 0.0, "ammonizioni": 0.0, "espulsioni": 0.0, "rigori_parati_segnati": 0.0, "autogol": 0.0, "portiere_imbattuto": 0.0, "nome_giocatore": "falco f"}, "gasperini": {"squadra": "atalanta", "ruolo": "0", "fantavoto": 5.0, "voto": 5.0, "gol_fatti_subiti": 0.0, "ammonizioni": 0.0, "espulsioni": 0.0, "rigori_parati_segnati": 0.0, "autogol": 0.0, "portiere_imbattuto": 0.0, "nome_giocatore": "gasperini"}, "romagna f": {"squadra": "sassuolo", "ruolo": "D", "fantavoto": 6.0, "voto": 6.0, "gol_fatti_subiti": 0.0, "ammonizioni": 0.0, "espulsioni": 0.0, "rigori_parati_segnati": 0.0, "autogol": 0.0, "portiere_imbattuto": 0.0, "nome_giocatore": "romagna f"}, "donnarumma al": {"squadra": "brescia", "ruolo": "A", "fantavoto": 5.0, "voto": 5.0, "gol_fatti_subiti": 0.0, "ammonizioni": 0.0, "espulsioni": 0.0, "rigori_parati_segnati": 0.0, "autogol": 0.0, "portiere_imbattuto": 0.0, "nome_giocatore": "donnarumma al"}, "rincon t": {"squadra": "torino", "ruolo": "C", "fantavoto": 5.5, "voto": 6.0, "gol_fatti_subiti": 0.0, "ammonizioni": -0.5, "espulsioni": 0.0, "rigori_parati_segnati": 0.0, "autogol": 0.0, "portiere_imbattuto": 0.0, "nome_giocatore": "rincon t"}, "donnarumma g": {"squadra": "milan", "ruolo": "P", "fantavoto": 5.0, "voto": 7.0, "gol_fatti_subiti": -2.0, "ammonizioni": 0.0, "espulsioni": 0.0, "rigori_parati_segnati": 0.0, "autogol": 0.0, "portiere_imbattuto": 0.0, "nome_giocatore": "donnarumma g"}, "traore j": {"squadra": "sassuolo", "ruolo": "C", "fantavoto": 6.0, "voto": 6.0, "gol_fatti_subiti": 0.0, "ammonizioni": 0.0, "espulsioni": 0.0, "rigori_parati_segnati": 0.0, "autogol": 0.0, "portiere_imbattuto": 0.0, "nome_giocatore": "traore j"}, "alves b": {"squadra": "parma", "ruolo": "D", "fantavoto": 6.0, "voto": 6.0, "gol_fatti_subiti": 0.0, "ammonizioni": 0.0, "espulsioni": 0.0, "rigori_parati_segnati": 0.0, "autogol": 0.0, "portiere_imbattuto": 0.0, "nome_giocatore": "alves b"}, "juric": {"squadra": "verona", "ruolo": "0", "fantavoto": 6.5, "voto": 7.0, "gol_fatti_subiti": 0.0, "ammonizioni": -0.5, "espulsioni": 0.0, "rigori_parati_segnati": 0.0, "autogol": 0.0, "portiere_imbattuto": 0.0, "nome_giocatore": "juric"}, "aina o": {"squadra": "torino", "ruolo": "D", "fantavoto": 4.5, "voto": 5.0, "gol_fatti_subiti": 0.0, "ammonizioni": -0.5, "espulsioni": 0.0, "rigori_parati_segnati": 0.0, "autogol": 0.0, "portiere_imbattuto": 0.0, "nome_giocatore": "aina o"}, "de ligt": {"squadra": "juventus", "ruolo": "D", "fantavoto": 7.0, "voto": 7.0, "gol_fatti_subiti": 0.0, "ammonizioni": 0.0, "espulsioni": 0.0, "rigori_parati_segnati": 0.0, "autogol": 0.0, "portiere_imbattuto": 0.0, "nome_giocatore": "de ligt"}, "kjaer s": {"squadra": "milan", "ruolo": "D", "fantavoto": 6.5, "voto": 6.5, "gol_fatti_subiti": 0.0, "ammonizioni": 0.0, "espulsioni": 0.0, "rigori_parati_segnati": 0.0, "autogol": 0.0, "portiere_imbattuto": 0.0, "nome_giocatore": "kjaer s"}, "under c": {"squadra": "roma", "ruolo": "C", "fantavoto": 9.0, "voto": 6.0, "gol_fatti_subiti": 3.0, "ammonizioni": 0.0, "espulsioni": 0.0, "rigori_parati_segnati": 0.0, "autogol": 0.0, "portiere_imbattuto": 0.0, "nome_giocatore": "under c"}, "leao r": {"squadra": "milan", "ruolo": "A", "fantavoto": 7.5, "voto": 7.5, "gol_fatti_subiti": 0.0, "ammonizioni": 0.0, "espulsioni": 0.0, "rigori_parati_segnati": 0.0, "autogol": 0.0, "portiere_imbattuto": 0.0, "nome_giocatore": "leao r"}, "toloi r": {"squadra": "atalanta", "ruolo": "D", "fantavoto": 5.5, "voto": 5.5, "gol_fatti_subiti": 0.0, "ammonizioni": 0.0, "espulsioni": 0.0, "rigori_parati_segnati": 0.0, "autogol": 0.0, "portiere_imbattuto": 0.0, "nome_giocatore": "toloi r"}, "dell orco c": {"squadra": "lecce", "ruolo": "D", "fantavoto": 6.5, "voto": 6.5, "gol_fatti_subiti": 0.0, "ammonizioni": 0.0, "espulsioni": 0.0, "rigori_parati_segnati": 0.0, "autogol": 0.0, "portiere_imbattuto": 0.0, "nome_giocatore": "dell orco c"}, "floccari s": {"squadra": "spal", "ruolo": "A", "fantavoto": NaN, "voto": NaN, "gol_fatti_subiti": 0.0, "ammonizioni": 0.0, "espulsioni": 0.0, "rigori_parati_segnati": 0.0, "autogol": 0.0, "portiere_imbattuto": 0.0, "nome_giocatore": "floccari s"}, "hysaj e": {"squadra": "napoli", "ruolo": "D", "fantavoto": 4.5, "voto": 5.0, "gol_fatti_subiti": 0.0, "ammonizioni": -0.5, "espulsioni": 0.0, "rigori_parati_segnati": 0.0, "autogol": 0.0, "portiere_imbattuto": 0.0, "nome_giocatore": "hysaj e"}}}}