{"2018-19": {"24": {"sala j": {"squadra": "sampdoria", "ruolo": "D", "fantavoto": NaN, "voto": NaN, "gol_fatti_subiti": 0.0, "ammonizioni": 0.0, "espulsioni": 0.0, "rigori_parati_segnati": 0.0, "autogol": 0.0, "portiere_imbattuto": 0.0, "nome_giocatore": "sala j"}, "pinamonti a": {"squadra": "frosinone", "ruolo": "A", "fantavoto": 5.5, "voto": 5.5, "gol_fatti_subiti": 0.0, "ammonizioni": 0.0, "espulsioni": 0.0, "rigori_parati_segnati": 0.0, "autogol": 0.0, "portiere_imbattuto": 0.0, "nome_giocatore": "pinamonti a"}, "perisic i": {"squadra": "inter", "ruolo": "C", "fantavoto": 6.5, "voto": 7.0, "gol_fatti_subiti": 0.0, "ammonizioni": -0.5, "espulsioni": 0.0, "rigori_parati_segnati": 0.0, "autogol": 0.0, "portiere_imbattuto": 0.0, "nome_giocatore": "perisic i"}, "viviano e": {"squadra": "spal", "ruolo": "P", "fantavoto": 2.0, "voto": 6.0, "gol_fatti_subiti": -4.0, "ammonizioni": 0.0, "espulsioni": 0.0, "rigori_parati_segnati": 0.0, "autogol": 0.0, "portiere_imbattuto": 0.0, "nome_giocatore": "viviano e"}, "paganini l": {"squadra": "frosinone", "ruolo": "C", "fantavoto": NaN, "voto": NaN, "gol_fatti_subiti": 0.0, "ammonizioni": 0.0, "espulsioni": 0.0, "rigori_parati_segnati": 0.0, "autogol": 0.0, "portiere_imbattuto": 0.0, "nome_giocatore": "paganini l"}, "falcinelli d": {"squadra": "bologna", "ruolo": "A", "fantavoto": NaN, "voto": NaN, "gol_fatti_subiti": 0.0, "ammonizioni": 0.0, "espulsioni": 0.0, "rigori_parati_segnati": 0.0, "autogol": 0.0, "portiere_imbattuto": 0.0, "nome_giocatore": "falcinelli d"}, "praet d": {"squadra": "sampdoria", "ruolo": "C", "fantavoto": 6.0, "voto": 6.0, "gol_fatti_subiti": 0.0, "ammonizioni": 0.0, "espulsioni": 0.0, "rigori_parati_segnati": 0.0, "autogol": 0.0, "portiere_imbattuto": 0.0, "nome_giocatore": "praet d"}, "silvestre m": {"squadra": "empoli", "ruolo": "D", "fantavoto": 6.5, "voto": 6.5, "gol_fatti_subiti": 0.0, "ammonizioni": 0.0, "espulsioni": 0.0, "rigori_parati_segnati": 0.0, "autogol": 0.0, "portiere_imbattuto": 0.0, "nome_giocatore": "silvestre m"}, "biraschi d": {"squadra": "genoa", "ruolo": "D", "fantavoto": 6.5, "voto": 6.5, "gol_fatti_subiti": 0.0, "ammonizioni": 0.0, "espulsioni": 0.0, "rigori_parati_segnati": 0.0, "autogol": 0.0, "portiere_imbattuto": 0.0, "nome_giocatore": "biraschi d"}, "berisha e": {"squadra": "atalanta", "ruolo": "P", "fantavoto": 2.0, "voto": 5.0, "gol_fatti_subiti": -3.0, "ammonizioni": 0.0, "espulsioni": 0.0, "rigori_parati_segnati": 0.0, "autogol": 0.0, "portiere_imbattuto": 0.0, "nome_giocatore": "berisha e"}, "szczesny w": {"squadra": "juventus", "ruolo": "P", "fantavoto": 7.0, "voto": 6.0, "gol_fatti_subiti": 0.0, "ammonizioni": 0.0, "espulsioni": 0.0, "rigori_parati_segnati": 0.0, "autogol": 0.0, "portiere_imbattuto": 1.0, "nome_giocatore": "szczesny w"}, "bonifazi k": {"squadra": "spal", "ruolo": "D", "fantavoto": 6.0, "voto": 6.0, "gol_fatti_subiti": 0.0, "ammonizioni": 0.0, "espulsioni": 0.0, "rigori_parati_segnati": 0.0, "autogol": 0.0, "portiere_imbattuto": 0.0, "nome_giocatore": "bonifazi k"}, "el shaarawy s": {"squadra": "roma", "ruolo": "A", "fantavoto": 7.0, "voto": 7.0, "gol_fatti_subiti": 0.0, "ammonizioni": 0.0, "espulsioni": 0.0, "rigori_parati_segnati": 0.0, "autogol": 0.0, "portiere_imbattuto": 0.0, "nome_giocatore": "el shaarawy s"}, "salamon b": {"squadra": "frosinone", "ruolo": "D", "fantavoto": 5.0, "voto": 5.5, "gol_fatti_subiti": 0.0, "ammonizioni": -0.5, "espulsioni": 0.0, "rigori_parati_segnati": 0.0, "autogol": 0.0, "portiere_imbattuto": 0.0, "nome_giocatore": "salamon b"}, "zampano f": {"squadra": "frosinone", "ruolo": "D", "fantavoto": 5.5, "voto": 5.5, "gol_fatti_subiti": 0.0, "ammonizioni": 0.0, "espulsioni": 0.0, "rigori_parati_segnati": 0.0, "autogol": 0.0, "portiere_imbattuto": 0.0, "nome_giocatore": "zampano f"}, "poli a": {"squadra": "bologna", "ruolo": "C", "fantavoto": 6.5, "voto": 6.5, "gol_fatti_subiti": 0.0, "ammonizioni": 0.0, "espulsioni": 0.0, "rigori_parati_segnati": 0.0, "autogol": 0.0, "portiere_imbattuto": 0.0, "nome_giocatore": "poli a"}, "nzonzi": {"squadra": "roma", "ruolo": "C", "fantavoto": 6.0, "voto": 6.0, "gol_fatti_subiti": 0.0, "ammonizioni": 0.0, "espulsioni": 0.0, "rigori_parati_segnati": 0.0, "autogol": 0.0, "portiere_imbattuto": 0.0, "nome_giocatore": "nzonzi"}, "floccari s": {"squadra": "spal", "ruolo": "A", "fantavoto": NaN, "voto": NaN, "gol_fatti_subiti": 0.0, "ammonizioni": 0.0, "espulsioni": 0.0, "rigori_parati_segnati": 0.0, "autogol": 0.0, "portiere_imbattuto": 0.0, "nome_giocatore": "floccari s"}, "audero e": {"squadra": "sampdoria", "ruolo": "P", "fantavoto": 3.5, "voto": 5.5, "gol_fatti_subiti": -2.0, "ammonizioni": 0.0, "espulsioni": 0.0, "rigori_parati_segnati": 0.0, "autogol": 0.0, "portiere_imbattuto": 0.0, "nome_giocatore": "audero e"}, "strakosha t": {"squadra": "lazio", "ruolo": "P", "fantavoto": 4.5, "voto": 6.5, "gol_fatti_subiti": -2.0, "ammonizioni": 0.0, "espulsioni": 0.0, "rigori_parati_segnati": 0.0, "autogol": 0.0, "portiere_imbattuto": 0.0, "nome_giocatore": "strakosha t"}, "petagna a": {"squadra": "spal", "ruolo": "A", "fantavoto": 9.5, "voto": 6.5, "gol_fatti_subiti": 3.0, "ammonizioni": 0.0, "espulsioni": 0.0, "rigori_parati_segnati": 0.0, "autogol": 0.0, "portiere_imbattuto": 0.0, "nome_giocatore": "petagna a"}, "aina o": {"squadra": "torino", "ruolo": "D", "fantavoto": 5.5, "voto": 6.0, "gol_fatti_subiti": 0.0, "ammonizioni": -0.5, "espulsioni": 0.0, "rigori_parati_segnati": 0.0, "autogol": 0.0, "portiere_imbattuto": 0.0, "nome_giocatore": "aina o"}, "nainggolan r": {"squadra": "inter", "ruolo": "C", "fantavoto": 10.0, "voto": 7.0, "gol_fatti_subiti": 3.0, "ammonizioni": 0.0, "espulsioni": 0.0, "rigori_parati_segnati": 0.0, "autogol": 0.0, "portiere_imbattuto": 0.0, "nome_giocatore": "nainggolan r"}, "parigini v": {"squadra": "torino", "ruolo": "A", "fantavoto": NaN, "voto": NaN, "gol_fatti_subiti": 0.0, "ammonizioni": 0.0, "espulsioni": 0.0, "rigori_parati_segnati": 0.0, "autogol": 0.0, "portiere_imbattuto": 0.0, "nome_giocatore": "parigini v"}, "gervinho": {"squadra": "parma", "ruolo": "A", "fantavoto": 4.5, "voto": 4.5, "gol_fatti_subiti": 0.0, "ammonizioni": 0.0, "espulsioni": 0.0, "rigori_parati_segnati": 0.0, "autogol": 0.0, "portiere_imbattuto": 0.0, "nome_giocatore": "gervinho"}, "padoin s": {"squadra": "cagliari", "ruolo": "C", "fantavoto": 6.5, "voto": 6.5, "gol_fatti_subiti": 0.0, "ammonizioni": 0.0, "espulsioni": 0.0, "rigori_parati_segnati": 0.0, "autogol": 0.0, "portiere_imbattuto": 0.0, "nome_giocatore": "padoin s"}, "felipe": {"squadra": "spal", "ruolo": "D", "fantavoto": 5.5, "voto": 5.5, "gol_fatti_subiti": 0.0, "ammonizioni": 0.0, "espulsioni": 0.0, "rigori_parati_segnati": 0.0, "autogol": 0.0, "portiere_imbattuto": 0.0, "nome_giocatore": "felipe"}, "spalletti": {"squadra": "inter", "ruolo": "0", "fantavoto": 6.5, "voto": 6.5, "gol_fatti_subiti": 0.0, "ammonizioni": 0.0, "espulsioni": 0.0, "rigori_parati_segnati": 0.0, "autogol": 0.0, "portiere_imbattuto": 0.0, "nome_giocatore": "spalletti"}, "veseli f": {"squadra": "empoli", "ruolo": "D", "fantavoto": 6.5, "voto": 6.5, "gol_fatti_subiti": 0.0, "ammonizioni": 0.0, "espulsioni": 0.0, "rigori_parati_segnati": 0.0, "autogol": 0.0, "portiere_imbattuto": 0.0, "nome_giocatore": "veseli f"}, "florenzi a": {"squadra": "roma", "ruolo": "D", "fantavoto": 5.5, "voto": 6.0, "gol_fatti_subiti": 0.0, "ammonizioni": -0.5, "espulsioni": 0.0, "rigori_parati_segnati": 0.0, "autogol": 0.0, "portiere_imbattuto": 0.0, "nome_giocatore": "florenzi a"}, "toloi r": {"squadra": "atalanta", "ruolo": "D", "fantavoto": 5.5, "voto": 5.5, "gol_fatti_subiti": 0.0, "ammonizioni": 0.0, "espulsioni": 0.0, "rigori_parati_segnati": 0.0, "autogol": 0.0, "portiere_imbattuto": 0.0, "nome_giocatore": "toloi r"}, "tonelli l": {"squadra": "sampdoria", "ruolo": "D", "fantavoto": 5.5, "voto": 5.5, "gol_fatti_subiti": 0.0, "ammonizioni": 0.0, "espulsioni": 0.0, "rigori_parati_segnati": 0.0, "autogol": 0.0, "portiere_imbattuto": 0.0, "nome_giocatore": "tonelli l"}, "paqueta l": {"squadra": "milan", "ruolo": "C", "fantavoto": 6.0, "voto": 6.0, "gol_fatti_subiti": 0.0, "ammonizioni": 0.0, "espulsioni": 0.0, "rigori_parati_segnati": 0.0, "autogol": 0.0, "portiere_imbattuto": 0.0, "nome_giocatore": "paqueta l"}, "pulgar e": {"squadra": "bologna", "ruolo": "C", "fantavoto": 5.5, "voto": 6.0, "gol_fatti_subiti": 0.0, "ammonizioni": -0.5, "espulsioni": 0.0, "rigori_parati_segnati": 0.0, "autogol": 0.0, "portiere_imbattuto": 0.0, "nome_giocatore": "pulgar e"}, "pjanic m": {"squadra": "juventus", "ruolo": "C", "fantavoto": NaN, "voto": NaN, "gol_fatti_subiti": 0.0, "ammonizioni": 0.0, "espulsioni": 0.0, "rigori_parati_segnati": 0.0, "autogol": 0.0, "portiere_imbattuto": 0.0, "nome_giocatore": "pjanic m"}, "piatek k": {"squadra": "milan", "ruolo": "A", "fantavoto": 14.0, "voto": 8.0, "gol_fatti_subiti": 6.0, "ammonizioni": 0.0, "espulsioni": 0.0, "rigori_parati_segnati": 0.0, "autogol": 0.0, "portiere_imbattuto": 0.0, "nome_giocatore": "piatek k"}, "pavoletti l": {"squadra": "cagliari", "ruolo": "A", "fantavoto": 13.5, "voto": 8.0, "gol_fatti_subiti": 6.0, "ammonizioni": -0.5, "espulsioni": 0.0, "rigori_parati_segnati": 0.0, "autogol": 0.0, "portiere_imbattuto": 0.0, "nome_giocatore": "pavoletti l"}, "acerbi f": {"squadra": "lazio", "ruolo": "D", "fantavoto": 6.0, "voto": 6.0, "gol_fatti_subiti": 0.0, "ammonizioni": 0.0, "espulsioni": 0.0, "rigori_parati_segnati": 0.0, "autogol": 0.0, "portiere_imbattuto": 0.0, "nome_giocatore": "acerbi f"}, "ekong t": {"squadra": "udinese", "ruolo": "D", "fantavoto": 5.5, "voto": 5.5, "gol_fatti_subiti": 0.0, "ammonizioni": 0.0, "espulsioni": 0.0, "rigori_parati_segnati": 0.0, "autogol": 0.0, "portiere_imbattuto": 0.0, "nome_giocatore": "ekong t"}, "pandev g": {"squadra": "genoa", "ruolo": "A", "fantavoto": 6.5, "voto": 7.0, "gol_fatti_subiti": 0.0, "ammonizioni": -0.5, "espulsioni": 0.0, "rigori_parati_segnati": 0.0, "autogol": 0.0, "portiere_imbattuto": 0.0, "nome_giocatore": "pandev g"}, "murgia a": {"squadra": "spal", "ruolo": "C", "fantavoto": 5.5, "voto": 5.5, "gol_fatti_subiti": 0.0, "ammonizioni": 0.0, "espulsioni": 0.0, "rigori_parati_segnati": 0.0, "autogol": 0.0, "portiere_imbattuto": 0.0, "nome_giocatore": "murgia a"}, "pucciarelli m": {"squadra": "chievo", "ruolo": "A", "fantavoto": NaN, "voto": NaN, "gol_fatti_subiti": 0.0, "ammonizioni": 0.0, "espulsioni": 0.0, "rigori_parati_segnati": 0.0, "autogol": 0.0, "portiere_imbattuto": 0.0, "nome_giocatore": "pucciarelli m"}, "farias d": {"squadra": "empoli", "ruolo": "A", "fantavoto": 11.0, "voto": 8.0, "gol_fatti_subiti": 3.0, "ammonizioni": 0.0, "espulsioni": 0.0, "rigori_parati_segnati": 0.0, "autogol": 0.0, "portiere_imbattuto": 0.0, "nome_giocatore": "farias d"}, "pellegrini lo": {"squadra": "roma", "ruolo": "C", "fantavoto": 6.0, "voto": 6.0, "gol_fatti_subiti": 0.0, "ammonizioni": 0.0, "espulsioni": 0.0, "rigori_parati_segnati": 0.0, "autogol": 0.0, "portiere_imbattuto": 0.0, "nome_giocatore": "pellegrini lo"}, "fazio f": {"squadra": "roma", "ruolo": "D", "fantavoto": 9.0, "voto": 6.0, "gol_fatti_subiti": 3.0, "ammonizioni": 0.0, "espulsioni": 0.0, "rigori_parati_segnati": 0.0, "autogol": 0.0, "portiere_imbattuto": 0.0, "nome_giocatore": "fazio f"}, "politano m": {"squadra": "inter", "ruolo": "A", "fantavoto": 6.0, "voto": 6.0, "gol_fatti_subiti": 0.0, "ammonizioni": 0.0, "espulsioni": 0.0, "rigori_parati_segnati": 0.0, "autogol": 0.0, "portiere_imbattuto": 0.0, "nome_giocatore": "politano m"}, "gabbiadini m": {"squadra": "sampdoria", "ruolo": "A", "fantavoto": 9.5, "voto": 6.5, "gol_fatti_subiti": 3.0, "ammonizioni": 0.0, "espulsioni": 0.0, "rigori_parati_segnati": 0.0, "autogol": 0.0, "portiere_imbattuto": 0.0, "nome_giocatore": "gabbiadini m"}, "santon d": {"squadra": "roma", "ruolo": "D", "fantavoto": 5.5, "voto": 5.5, "gol_fatti_subiti": 0.0, "ammonizioni": 0.0, "espulsioni": 0.0, "rigori_parati_segnati": 0.0, "autogol": 0.0, "portiere_imbattuto": 0.0, "nome_giocatore": "santon d"}, "skriniar m": {"squadra": "inter", "ruolo": "D", "fantavoto": 5.0, "voto": 5.5, "gol_fatti_subiti": 0.0, "ammonizioni": -0.5, "espulsioni": 0.0, "rigori_parati_segnati": 0.0, "autogol": 0.0, "portiere_imbattuto": 0.0, "nome_giocatore": "skriniar m"}, "gobbi m": {"squadra": "parma", "ruolo": "D", "fantavoto": 6.0, "voto": 6.0, "gol_fatti_subiti": 0.0, "ammonizioni": 0.0, "espulsioni": 0.0, "rigori_parati_segnati": 0.0, "autogol": 0.0, "portiere_imbattuto": 0.0, "nome_giocatore": "gobbi m"}, "bonucci l": {"squadra": "juventus", "ruolo": "D", "fantavoto": 10.0, "voto": 7.0, "gol_fatti_subiti": 3.0, "ammonizioni": 0.0, "espulsioni": 0.0, "rigori_parati_segnati": 0.0, "autogol": 0.0, "portiere_imbattuto": 0.0, "nome_giocatore": "bonucci l"}, "stulac l": {"squadra": "parma", "ruolo": "C", "fantavoto": 6.0, "voto": 6.0, "gol_fatti_subiti": 0.0, "ammonizioni": 0.0, "espulsioni": 0.0, "rigori_parati_segnati": 0.0, "autogol": 0.0, "portiere_imbattuto": 0.0, "nome_giocatore": "stulac l"}, "radovanovic i": {"squadra": "genoa", "ruolo": "C", "fantavoto": 5.5, "voto": 5.5, "gol_fatti_subiti": 0.0, "ammonizioni": 0.0, "espulsioni": 0.0, "rigori_parati_segnati": 0.0, "autogol": 0.0, "portiere_imbattuto": 0.0, "nome_giocatore": "radovanovic i"}, "matri a": {"squadra": "sassuolo", "ruolo": "A", "fantavoto": NaN, "voto": NaN, "gol_fatti_subiti": 0.0, "ammonizioni": 0.0, "espulsioni": 0.0, "rigori_parati_segnati": 0.0, "autogol": 0.0, "portiere_imbattuto": 0.0, "nome_giocatore": "matri a"}, "magnani g": {"squadra": "sassuolo", "ruolo": "D", "fantavoto": 4.5, "voto": 4.5, "gol_fatti_subiti": 0.0, "ammonizioni": 0.0, "espulsioni": 0.0, "rigori_parati_segnati": 0.0, "autogol": 0.0, "portiere_imbattuto": 0.0, "nome_giocatore": "magnani g"}, "lykogiannis c": {"squadra": "cagliari", "ruolo": "D", "fantavoto": 5.5, "voto": 5.5, "gol_fatti_subiti": 0.0, "ammonizioni": 0.0, "espulsioni": 0.0, "rigori_parati_segnati": 0.0, "autogol": 0.0, "portiere_imbattuto": 0.0, "nome_giocatore": "lykogiannis c"}, "fofana s": {"squadra": "udinese", "ruolo": "C", "fantavoto": 5.5, "voto": 6.0, "gol_fatti_subiti": 0.0, "ammonizioni": -0.5, "espulsioni": 0.0, "rigori_parati_segnati": 0.0, "autogol": 0.0, "portiere_imbattuto": 0.0, "nome_giocatore": "fofana s"}, "meggiorini r": {"squadra": "chievo", "ruolo": "A", "fantavoto": 5.0, "voto": 5.0, "gol_fatti_subiti": 0.0, "ammonizioni": 0.0, "espulsioni": 0.0, "rigori_parati_segnati": 0.0, "autogol": 0.0, "portiere_imbattuto": 0.0, "nome_giocatore": "meggiorini r"}, "biabiany j": {"squadra": "parma", "ruolo": "C", "fantavoto": 5.5, "voto": 5.5, "gol_fatti_subiti": 0.0, "ammonizioni": 0.0, "espulsioni": 0.0, "rigori_parati_segnati": 0.0, "autogol": 0.0, "portiere_imbattuto": 0.0, "nome_giocatore": "biabiany j"}, "fares m": {"squadra": "spal", "ruolo": "C", "fantavoto": 5.5, "voto": 6.0, "gol_fatti_subiti": 0.0, "ammonizioni": -0.5, "espulsioni": 0.0, "rigori_parati_segnati": 0.0, "autogol": 0.0, "portiere_imbattuto": 0.0, "nome_giocatore": "fares m"}, "kluivert j": {"squadra": "roma", "ruolo": "A", "fantavoto": 5.0, "voto": 5.0, "gol_fatti_subiti": 0.0, "ammonizioni": 0.0, "espulsioni": 0.0, "rigori_parati_segnati": 0.0, "autogol": 0.0, "portiere_imbattuto": 0.0, "nome_giocatore": "kluivert j"}, "dragowski b": {"squadra": "empoli", "ruolo": "P", "fantavoto": 8.0, "voto": 7.0, "gol_fatti_subiti": 0.0, "ammonizioni": 0.0, "espulsioni": 0.0, "rigori_parati_segnati": 0.0, "autogol": 0.0, "portiere_imbattuto": 1.0, "nome_giocatore": "dragowski b"}, "ceccherini f": {"squadra": "fiorentina", "ruolo": "D", "fantavoto": 6.0, "voto": 6.0, "gol_fatti_subiti": 0.0, "ammonizioni": 0.0, "espulsioni": 0.0, "rigori_parati_segnati": 0.0, "autogol": 0.0, "portiere_imbattuto": 0.0, "nome_giocatore": "ceccherini f"}, "bessa d": {"squadra": "genoa", "ruolo": "C", "fantavoto": 6.5, "voto": 6.5, "gol_fatti_subiti": 0.0, "ammonizioni": 0.0, "espulsioni": 0.0, "rigori_parati_segnati": 0.0, "autogol": 0.0, "portiere_imbattuto": 0.0, "nome_giocatore": "bessa d"}, "inzaghi s": {"squadra": "lazio", "ruolo": "0", "fantavoto": 5.5, "voto": 5.5, "gol_fatti_subiti": 0.0, "ammonizioni": 0.0, "espulsioni": 0.0, "rigori_parati_segnati": 0.0, "autogol": 0.0, "portiere_imbattuto": 0.0, "nome_giocatore": "inzaghi s"}, "valoti m": {"squadra": "spal", "ruolo": "C", "fantavoto": 5.5, "voto": 5.5, "gol_fatti_subiti": 0.0, "ammonizioni": 0.0, "espulsioni": 0.0, "rigori_parati_segnati": 0.0, "autogol": 0.0, "portiere_imbattuto": 0.0, "nome_giocatore": "valoti m"}, "freuler r": {"squadra": "atalanta", "ruolo": "C", "fantavoto": 9.5, "voto": 6.5, "gol_fatti_subiti": 3.0, "ammonizioni": 0.0, "espulsioni": 0.0, "rigori_parati_segnati": 0.0, "autogol": 0.0, "portiere_imbattuto": 0.0, "nome_giocatore": "freuler r"}, "zapata d": {"squadra": "atalanta", "ruolo": "A", "fantavoto": 5.0, "voto": 5.0, "gol_fatti_subiti": 0.0, "ammonizioni": 0.0, "espulsioni": 0.0, "rigori_parati_segnati": 0.0, "autogol": 0.0, "portiere_imbattuto": 0.0, "nome_giocatore": "zapata d"}, "caputo f": {"squadra": "empoli", "ruolo": "A", "fantavoto": 6.0, "voto": 6.0, "gol_fatti_subiti": 0.0, "ammonizioni": 0.0, "espulsioni": 0.0, "rigori_parati_segnati": 0.0, "autogol": 0.0, "portiere_imbattuto": 0.0, "nome_giocatore": "caputo f"}, "vecino m": {"squadra": "inter", "ruolo": "C", "fantavoto": NaN, "voto": NaN, "gol_fatti_subiti": 0.0, "ammonizioni": 0.0, "espulsioni": 0.0, "rigori_parati_segnati": 0.0, "autogol": 0.0, "portiere_imbattuto": 0.0, "nome_giocatore": "vecino m"}, "maksimovic n": {"squadra": "napoli", "ruolo": "D", "fantavoto": 6.0, "voto": 6.0, "gol_fatti_subiti": 0.0, "ammonizioni": 0.0, "espulsioni": 0.0, "rigori_parati_segnati": 0.0, "autogol": 0.0, "portiere_imbattuto": 0.0, "nome_giocatore": "maksimovic n"}, "pellegrini lu": {"squadra": "cagliari", "ruolo": "D", "fantavoto": 6.0, "voto": 6.0, "gol_fatti_subiti": 0.0, "ammonizioni": 0.0, "espulsioni": 0.0, "rigori_parati_segnati": 0.0, "autogol": 0.0, "portiere_imbattuto": 0.0, "nome_giocatore": "pellegrini lu"}, "allegri": {"squadra": "juventus", "ruolo": "0", "fantavoto": 7.0, "voto": 7.0, "gol_fatti_subiti": 0.0, "ammonizioni": 0.0, "espulsioni": 0.0, "rigori_parati_segnati": 0.0, "autogol": 0.0, "portiere_imbattuto": 0.0, "nome_giocatore": "allegri"}, "dzemaili b": {"squadra": "bologna", "ruolo": "C", "fantavoto": 6.0, "voto": 6.0, "gol_fatti_subiti": 0.0, "ammonizioni": 0.0, "espulsioni": 0.0, "rigori_parati_segnati": 0.0, "autogol": 0.0, "portiere_imbattuto": 0.0, "nome_giocatore": "dzemaili b"}, "martinez l": {"squadra": "inter", "ruolo": "A", "fantavoto": 6.5, "voto": 6.5, "gol_fatti_subiti": 0.0, "ammonizioni": 0.0, "espulsioni": 0.0, "rigori_parati_segnati": 0.0, "autogol": 0.0, "portiere_imbattuto": 0.0, "nome_giocatore": "martinez l"}, "boga j": {"squadra": "sassuolo", "ruolo": "C", "fantavoto": 5.5, "voto": 5.5, "gol_fatti_subiti": 0.0, "ammonizioni": 0.0, "espulsioni": 0.0, "rigori_parati_segnati": 0.0, "autogol": 0.0, "portiere_imbattuto": 0.0, "nome_giocatore": "boga j"}, "peluso f": {"squadra": "sassuolo", "ruolo": "D", "fantavoto": 4.5, "voto": 4.5, "gol_fatti_subiti": 0.0, "ammonizioni": 0.0, "espulsioni": 0.0, "rigori_parati_segnati": 0.0, "autogol": 0.0, "portiere_imbattuto": 0.0, "nome_giocatore": "peluso f"}, "edimilson f": {"squadra": "fiorentina", "ruolo": "C", "fantavoto": 9.5, "voto": 7.0, "gol_fatti_subiti": 3.0, "ammonizioni": -0.5, "espulsioni": 0.0, "rigori_parati_segnati": 0.0, "autogol": 0.0, "portiere_imbattuto": 0.0, "nome_giocatore": "edimilson f"}, "ospina d": {"squadra": "napoli", "ruolo": "P", "fantavoto": 7.0, "voto": 6.0, "gol_fatti_subiti": 0.0, "ammonizioni": 0.0, "espulsioni": 0.0, "rigori_parati_segnati": 0.0, "autogol": 0.0, "portiere_imbattuto": 1.0, "nome_giocatore": "ospina d"}, "malcuit k": {"squadra": "napoli", "ruolo": "D", "fantavoto": 6.0, "voto": 6.5, "gol_fatti_subiti": 0.0, "ammonizioni": -0.5, "espulsioni": 0.0, "rigori_parati_segnati": 0.0, "autogol": 0.0, "portiere_imbattuto": 0.0, "nome_giocatore": "malcuit k"}, "ekdal a": {"squadra": "sampdoria", "ruolo": "C", "fantavoto": 6.0, "voto": 6.0, "gol_fatti_subiti": 0.0, "ammonizioni": 0.0, "espulsioni": 0.0, "rigori_parati_segnati": 0.0, "autogol": 0.0, "portiere_imbattuto": 0.0, "nome_giocatore": "ekdal a"}, "verdi s": {"squadra": "napoli", "ruolo": "C", "fantavoto": 5.5, "voto": 5.5, "gol_fatti_subiti": 0.0, "ammonizioni": 0.0, "espulsioni": 0.0, "rigori_parati_segnati": 0.0, "autogol": 0.0, "portiere_imbattuto": 0.0, "nome_giocatore": "verdi s"}, "ceppitelli l": {"squadra": "cagliari", "ruolo": "D", "fantavoto": 5.5, "voto": 5.5, "gol_fatti_subiti": 0.0, "ammonizioni": 0.0, "espulsioni": 0.0, "rigori_parati_segnati": 0.0, "autogol": 0.0, "portiere_imbattuto": 0.0, "nome_giocatore": "ceppitelli l"}, "emre can": {"squadra": "juventus", "ruolo": "C", "fantavoto": 5.5, "voto": 6.0, "gol_fatti_subiti": 0.0, "ammonizioni": -0.5, "espulsioni": 0.0, "rigori_parati_segnati": 0.0, "autogol": 0.0, "portiere_imbattuto": 0.0, "nome_giocatore": "emre can"}, "iachini": {"squadra": "empoli", "ruolo": "0", "fantavoto": 6.5, "voto": 6.5, "gol_fatti_subiti": 0.0, "ammonizioni": 0.0, "espulsioni": 0.0, "rigori_parati_segnati": 0.0, "autogol": 0.0, "portiere_imbattuto": 0.0, "nome_giocatore": "iachini"}, "pereira p": {"squadra": "genoa", "ruolo": "D", "fantavoto": 6.0, "voto": 6.0, "gol_fatti_subiti": 0.0, "ammonizioni": 0.0, "espulsioni": 0.0, "rigori_parati_segnati": 0.0, "autogol": 0.0, "portiere_imbattuto": 0.0, "nome_giocatore": "pereira p"}, "gagliardini r": {"squadra": "inter", "ruolo": "C", "fantavoto": 5.5, "voto": 5.5, "gol_fatti_subiti": 0.0, "ammonizioni": 0.0, "espulsioni": 0.0, "rigori_parati_segnati": 0.0, "autogol": 0.0, "portiere_imbattuto": 0.0, "nome_giocatore": "gagliardini r"}, "manolas k": {"squadra": "roma", "ruolo": "D", "fantavoto": 5.0, "voto": 5.5, "gol_fatti_subiti": 0.0, "ammonizioni": -0.5, "espulsioni": 0.0, "rigori_parati_segnati": 0.0, "autogol": 0.0, "portiere_imbattuto": 0.0, "nome_giocatore": "manolas k"}, "castillejo s": {"squadra": "milan", "ruolo": "A", "fantavoto": NaN, "voto": NaN, "gol_fatti_subiti": 0.0, "ammonizioni": 0.0, "espulsioni": 0.0, "rigori_parati_segnati": 0.0, "autogol": 0.0, "portiere_imbattuto": 0.0, "nome_giocatore": "castillejo s"}, "bernardeschi f": {"squadra": "juventus", "ruolo": "C", "fantavoto": 6.0, "voto": 6.0, "gol_fatti_subiti": 0.0, "ammonizioni": 0.0, "espulsioni": 0.0, "rigori_parati_segnati": 0.0, "autogol": 0.0, "portiere_imbattuto": 0.0, "nome_giocatore": "bernardeschi f"}, "insigne l": {"squadra": "napoli", "ruolo": "A", "fantavoto": 5.5, "voto": 6.0, "gol_fatti_subiti": 0.0, "ammonizioni": -0.5, "espulsioni": 0.0, "rigori_parati_segnati": 0.0, "autogol": 0.0, "portiere_imbattuto": 0.0, "nome_giocatore": "insigne l"}, "larsen s": {"squadra": "udinese", "ruolo": "D", "fantavoto": 5.0, "voto": 5.0, "gol_fatti_subiti": 0.0, "ammonizioni": 0.0, "espulsioni": 0.0, "rigori_parati_segnati": 0.0, "autogol": 0.0, "portiere_imbattuto": 0.0, "nome_giocatore": "larsen s"}, "bentancur r": {"squadra": "juventus", "ruolo": "C", "fantavoto": 5.5, "voto": 5.5, "gol_fatti_subiti": 0.0, "ammonizioni": 0.0, "espulsioni": 0.0, "rigori_parati_segnati": 0.0, "autogol": 0.0, "portiere_imbattuto": 0.0, "nome_giocatore": "bentancur r"}, "bennacer i": {"squadra": "empoli", "ruolo": "C", "fantavoto": 7.5, "voto": 7.5, "gol_fatti_subiti": 0.0, "ammonizioni": 0.0, "espulsioni": 0.0, "rigori_parati_segnati": 0.0, "autogol": 0.0, "portiere_imbattuto": 0.0, "nome_giocatore": "bennacer i"}, "donnarumma g": {"squadra": "milan", "ruolo": "P", "fantavoto": 4.5, "voto": 5.5, "gol_fatti_subiti": -1.0, "ammonizioni": 0.0, "espulsioni": 0.0, "rigori_parati_segnati": 0.0, "autogol": 0.0, "portiere_imbattuto": 0.0, "nome_giocatore": "donnarumma g"}, "ciano c": {"squadra": "frosinone", "ruolo": "A", "fantavoto": 6.0, "voto": 6.0, "gol_fatti_subiti": 0.0, "ammonizioni": 0.0, "espulsioni": 0.0, "rigori_parati_segnati": 0.0, "autogol": 0.0, "portiere_imbattuto": 0.0, "nome_giocatore": "ciano c"}, "hetemaj p": {"squadra": "chievo", "ruolo": "C", "fantavoto": 6.0, "voto": 6.0, "gol_fatti_subiti": 0.0, "ammonizioni": 0.0, "espulsioni": 0.0, "rigori_parati_segnati": 0.0, "autogol": 0.0, "portiere_imbattuto": 0.0, "nome_giocatore": "hetemaj p"}, "koulibaly k": {"squadra": "napoli", "ruolo": "D", "fantavoto": 6.0, "voto": 6.5, "gol_fatti_subiti": 0.0, "ammonizioni": -0.5, "espulsioni": 0.0, "rigori_parati_segnati": 0.0, "autogol": 0.0, "portiere_imbattuto": 0.0, "nome_giocatore": "koulibaly k"}, "de vrij s": {"squadra": "inter", "ruolo": "D", "fantavoto": 6.0, "voto": 6.0, "gol_fatti_subiti": 0.0, "ammonizioni": 0.0, "espulsioni": 0.0, "rigori_parati_segnati": 0.0, "autogol": 0.0, "portiere_imbattuto": 0.0, "nome_giocatore": "de vrij s"}, "milik a": {"squadra": "napoli", "ruolo": "A", "fantavoto": 5.0, "voto": 5.0, "gol_fatti_subiti": 0.0, "ammonizioni": 0.0, "espulsioni": 0.0, "rigori_parati_segnati": 0.0, "autogol": 0.0, "portiere_imbattuto": 0.0, "nome_giocatore": "milik a"}, "stepinski m": {"squadra": "chievo", "ruolo": "A", "fantavoto": 5.0, "voto": 5.0, "gol_fatti_subiti": 0.0, "ammonizioni": 0.0, "espulsioni": 0.0, "rigori_parati_segnati": 0.0, "autogol": 0.0, "portiere_imbattuto": 0.0, "nome_giocatore": "stepinski m"}, "ilicic j": {"squadra": "atalanta", "ruolo": "C", "fantavoto": 6.5, "voto": 6.5, "gol_fatti_subiti": 0.0, "ammonizioni": 0.0, "espulsioni": 0.0, "rigori_parati_segnati": 0.0, "autogol": 0.0, "portiere_imbattuto": 0.0, "nome_giocatore": "ilicic j"}, "svanberg m": {"squadra": "bologna", "ruolo": "C", "fantavoto": 6.0, "voto": 6.0, "gol_fatti_subiti": 0.0, "ammonizioni": 0.0, "espulsioni": 0.0, "rigori_parati_segnati": 0.0, "autogol": 0.0, "portiere_imbattuto": 0.0, "nome_giocatore": "svanberg m"}, "ciofani d": {"squadra": "frosinone", "ruolo": "A", "fantavoto": 5.5, "voto": 5.5, "gol_fatti_subiti": 0.0, "ammonizioni": 0.0, "espulsioni": 0.0, "rigori_parati_segnati": 0.0, "autogol": 0.0, "portiere_imbattuto": 0.0, "nome_giocatore": "ciofani d"}, "radu s": {"squadra": "lazio", "ruolo": "D", "fantavoto": 6.0, "voto": 6.0, "gol_fatti_subiti": 0.0, "ammonizioni": 0.0, "espulsioni": 0.0, "rigori_parati_segnati": 0.0, "autogol": 0.0, "portiere_imbattuto": 0.0, "nome_giocatore": "radu s"}, "ucan s": {"squadra": "empoli", "ruolo": "C", "fantavoto": NaN, "voto": NaN, "gol_fatti_subiti": 0.0, "ammonizioni": 0.0, "espulsioni": 0.0, "rigori_parati_segnati": 0.0, "autogol": 0.0, "portiere_imbattuto": 0.0, "nome_giocatore": "ucan s"}, "berenguer a": {"squadra": "torino", "ruolo": "C", "fantavoto": 5.0, "voto": 5.0, "gol_fatti_subiti": 0.0, "ammonizioni": 0.0, "espulsioni": 0.0, "rigori_parati_segnati": 0.0, "autogol": 0.0, "portiere_imbattuto": 0.0, "nome_giocatore": "berenguer a"}, "suso j": {"squadra": "milan", "ruolo": "A", "fantavoto": 5.0, "voto": 5.5, "gol_fatti_subiti": 0.0, "ammonizioni": -0.5, "espulsioni": 0.0, "rigori_parati_segnati": 0.0, "autogol": 0.0, "portiere_imbattuto": 0.0, "nome_giocatore": "suso j"}, "gerson": {"squadra": "fiorentina", "ruolo": "C", "fantavoto": 9.5, "voto": 6.5, "gol_fatti_subiti": 3.0, "ammonizioni": 0.0, "espulsioni": 0.0, "rigori_parati_segnati": 0.0, "autogol": 0.0, "portiere_imbattuto": 0.0, "nome_giocatore": "gerson"}, "de sciglio m": {"squadra": "juventus", "ruolo": "D", "fantavoto": 7.0, "voto": 7.0, "gol_fatti_subiti": 0.0, "ammonizioni": 0.0, "espulsioni": 0.0, "rigori_parati_segnati": 0.0, "autogol": 0.0, "portiere_imbattuto": 0.0, "nome_giocatore": "de sciglio m"}, "giaccherini e": {"squadra": "chievo", "ruolo": "C", "fantavoto": 5.5, "voto": 6.0, "gol_fatti_subiti": 0.0, "ammonizioni": -0.5, "espulsioni": 0.0, "rigori_parati_segnati": 0.0, "autogol": 0.0, "portiere_imbattuto": 0.0, "nome_giocatore": "giaccherini e"}, "teodorczyk l": {"squadra": "udinese", "ruolo": "A", "fantavoto": 6.0, "voto": 6.5, "gol_fatti_subiti": 3.0, "ammonizioni": -0.5, "espulsioni": 0.0, "rigori_parati_segnati": -3.0, "autogol": 0.0, "portiere_imbattuto": 0.0, "nome_giocatore": "teodorczyk l"}, "gomez a": {"squadra": "atalanta", "ruolo": "C", "fantavoto": 5.5, "voto": 5.5, "gol_fatti_subiti": 0.0, "ammonizioni": 0.0, "espulsioni": 0.0, "rigori_parati_segnati": 0.0, "autogol": 0.0, "portiere_imbattuto": 0.0, "nome_giocatore": "gomez a"}, "valdifiori m": {"squadra": "spal", "ruolo": "C", "fantavoto": 5.0, "voto": 5.0, "gol_fatti_subiti": 0.0, "ammonizioni": 0.0, "espulsioni": 0.0, "rigori_parati_segnati": 0.0, "autogol": 0.0, "portiere_imbattuto": 0.0, "nome_giocatore": "valdifiori m"}, "lirola p": {"squadra": "sassuolo", "ruolo": "D", "fantavoto": 4.5, "voto": 4.5, "gol_fatti_subiti": 0.0, "ammonizioni": 0.0, "espulsioni": 0.0, "rigori_parati_segnati": 0.0, "autogol": 0.0, "portiere_imbattuto": 0.0, "nome_giocatore": "lirola p"}, "ceravolo f": {"squadra": "parma", "ruolo": "A", "fantavoto": NaN, "voto": NaN, "gol_fatti_subiti": 0.0, "ammonizioni": 0.0, "espulsioni": 0.0, "rigori_parati_segnati": 0.0, "autogol": 0.0, "portiere_imbattuto": 0.0, "nome_giocatore": "ceravolo f"}, "de silvestri l": {"squadra": "torino", "ruolo": "D", "fantavoto": 5.5, "voto": 5.5, "gol_fatti_subiti": 0.0, "ammonizioni": 0.0, "espulsioni": 0.0, "rigori_parati_segnati": 0.0, "autogol": 0.0, "portiere_imbattuto": 0.0, "nome_giocatore": "de silvestri l"}, "radu i": {"squadra": "genoa", "ruolo": "P", "fantavoto": 6.0, "voto": 7.0, "gol_fatti_subiti": -1.0, "ammonizioni": 0.0, "espulsioni": 0.0, "rigori_parati_segnati": 0.0, "autogol": 0.0, "portiere_imbattuto": 0.0, "nome_giocatore": "radu i"}, "mertens d": {"squadra": "napoli", "ruolo": "A", "fantavoto": 5.5, "voto": 5.5, "gol_fatti_subiti": 0.0, "ammonizioni": 0.0, "espulsioni": 0.0, "rigori_parati_segnati": 0.0, "autogol": 0.0, "portiere_imbattuto": 0.0, "nome_giocatore": "mertens d"}, "castagne t": {"squadra": "atalanta", "ruolo": "D", "fantavoto": 6.0, "voto": 6.0, "gol_fatti_subiti": 0.0, "ammonizioni": 0.0, "espulsioni": 0.0, "rigori_parati_segnati": 0.0, "autogol": 0.0, "portiere_imbattuto": 0.0, "nome_giocatore": "castagne t"}, "meite s": {"squadra": "torino", "ruolo": "C", "fantavoto": 5.5, "voto": 5.5, "gol_fatti_subiti": 0.0, "ammonizioni": 0.0, "espulsioni": 0.0, "rigori_parati_segnati": 0.0, "autogol": 0.0, "portiere_imbattuto": 0.0, "nome_giocatore": "meite s"}, "laurini v": {"squadra": "fiorentina", "ruolo": "D", "fantavoto": 6.0, "voto": 6.0, "gol_fatti_subiti": 0.0, "ammonizioni": 0.0, "espulsioni": 0.0, "rigori_parati_segnati": 0.0, "autogol": 0.0, "portiere_imbattuto": 0.0, "nome_giocatore": "laurini v"}, "pisacane f": {"squadra": "cagliari", "ruolo": "D", "fantavoto": 6.0, "voto": 6.0, "gol_fatti_subiti": 0.0, "ammonizioni": 0.0, "espulsioni": 0.0, "rigori_parati_segnati": 0.0, "autogol": 0.0, "portiere_imbattuto": 0.0, "nome_giocatore": "pisacane f"}, "ansaldi c": {"squadra": "torino", "ruolo": "D", "fantavoto": 6.0, "voto": 6.0, "gol_fatti_subiti": 0.0, "ammonizioni": 0.0, "espulsioni": 0.0, "rigori_parati_segnati": 0.0, "autogol": 0.0, "portiere_imbattuto": 0.0, "nome_giocatore": "ansaldi c"}, "sepe l": {"squadra": "parma", "ruolo": "P", "fantavoto": 3.5, "voto": 5.5, "gol_fatti_subiti": -2.0, "ammonizioni": 0.0, "espulsioni": 0.0, "rigori_parati_segnati": 0.0, "autogol": 0.0, "portiere_imbattuto": 0.0, "nome_giocatore": "sepe l"}, "olsen r": {"squadra": "roma", "ruolo": "P", "fantavoto": 7.0, "voto": 8.0, "gol_fatti_subiti": -1.0, "ammonizioni": 0.0, "espulsioni": 0.0, "rigori_parati_segnati": 0.0, "autogol": 0.0, "portiere_imbattuto": 0.0, "nome_giocatore": "olsen r"}, "duncan a": {"squadra": "sassuolo", "ruolo": "C", "fantavoto": 4.5, "voto": 4.5, "gol_fatti_subiti": 0.0, "ammonizioni": 0.0, "espulsioni": 0.0, "rigori_parati_segnati": 0.0, "autogol": 0.0, "portiere_imbattuto": 0.0, "nome_giocatore": "duncan a"}, "lasagna k": {"squadra": "udinese", "ruolo": "A", "fantavoto": 5.0, "voto": 5.0, "gol_fatti_subiti": 0.0, "ammonizioni": 0.0, "espulsioni": 0.0, "rigori_parati_segnati": 0.0, "autogol": 0.0, "portiere_imbattuto": 0.0, "nome_giocatore": "lasagna k"}, "bani m": {"squadra": "chievo", "ruolo": "D", "fantavoto": 5.5, "voto": 5.5, "gol_fatti_subiti": 0.0, "ammonizioni": 0.0, "espulsioni": 0.0, "rigori_parati_segnati": 0.0, "autogol": 0.0, "portiere_imbattuto": 0.0, "nome_giocatore": "bani m"}, "cassata f": {"squadra": "frosinone", "ruolo": "C", "fantavoto": 5.0, "voto": 5.5, "gol_fatti_subiti": 0.0, "ammonizioni": -0.5, "espulsioni": 0.0, "rigori_parati_segnati": 0.0, "autogol": 0.0, "portiere_imbattuto": 0.0, "nome_giocatore": "cassata f"}, "babacar k": {"squadra": "sassuolo", "ruolo": "A", "fantavoto": 4.5, "voto": 4.5, "gol_fatti_subiti": 0.0, "ammonizioni": 0.0, "espulsioni": 0.0, "rigori_parati_segnati": 0.0, "autogol": 0.0, "portiere_imbattuto": 0.0, "nome_giocatore": "babacar k"}, "de zerbi": {"squadra": "sassuolo", "ruolo": "0", "fantavoto": 4.5, "voto": 4.5, "gol_fatti_subiti": 0.0, "ammonizioni": 0.0, "espulsioni": 0.0, "rigori_parati_segnati": 0.0, "autogol": 0.0, "portiere_imbattuto": 0.0, "nome_giocatore": "de zerbi"}, "moretti e": {"squadra": "torino", "ruolo": "D", "fantavoto": 4.5, "voto": 5.0, "gol_fatti_subiti": 0.0, "ammonizioni": -0.5, "espulsioni": 0.0, "rigori_parati_segnati": 0.0, "autogol": 0.0, "portiere_imbattuto": 0.0, "nome_giocatore": "moretti e"}, "nuytinck b": {"squadra": "udinese", "ruolo": "D", "fantavoto": 5.5, "voto": 6.0, "gol_fatti_subiti": 0.0, "ammonizioni": -0.5, "espulsioni": 0.0, "rigori_parati_segnati": 0.0, "autogol": 0.0, "portiere_imbattuto": 0.0, "nome_giocatore": "nuytinck b"}, "criscito d": {"squadra": "genoa", "ruolo": "D", "fantavoto": 10.0, "voto": 7.5, "gol_fatti_subiti": 3.0, "ammonizioni": -0.5, "espulsioni": 0.0, "rigori_parati_segnati": 0.0, "autogol": 0.0, "portiere_imbattuto": 0.0, "nome_giocatore": "criscito d"}, "opoku n": {"squadra": "udinese", "ruolo": "D", "fantavoto": 6.0, "voto": 6.0, "gol_fatti_subiti": 0.0, "ammonizioni": 0.0, "espulsioni": 0.0, "rigori_parati_segnati": 0.0, "autogol": 0.0, "portiere_imbattuto": 0.0, "nome_giocatore": "opoku n"}, "barba f": {"squadra": "chievo", "ruolo": "D", "fantavoto": 6.0, "voto": 6.0, "gol_fatti_subiti": 0.0, "ammonizioni": 0.0, "espulsioni": 0.0, "rigori_parati_segnati": 0.0, "autogol": 0.0, "portiere_imbattuto": 0.0, "nome_giocatore": "barba f"}, "antenucci m": {"squadra": "spal", "ruolo": "A", "fantavoto": 5.5, "voto": 5.5, "gol_fatti_subiti": 0.0, "ammonizioni": 0.0, "espulsioni": 0.0, "rigori_parati_segnati": 0.0, "autogol": 0.0, "portiere_imbattuto": 0.0, "nome_giocatore": "antenucci m"}, "brignola e": {"squadra": "sassuolo", "ruolo": "A", "fantavoto": 4.5, "voto": 4.5, "gol_fatti_subiti": 0.0, "ammonizioni": 0.0, "espulsioni": 0.0, "rigori_parati_segnati": 0.0, "autogol": 0.0, "portiere_imbattuto": 0.0, "nome_giocatore": "brignola e"}, "dabo b": {"squadra": "fiorentina", "ruolo": "C", "fantavoto": NaN, "voto": NaN, "gol_fatti_subiti": 0.0, "ammonizioni": 0.0, "espulsioni": 0.0, "rigori_parati_segnati": 0.0, "autogol": 0.0, "portiere_imbattuto": 0.0, "nome_giocatore": "dabo b"}, "candreva a": {"squadra": "inter", "ruolo": "C", "fantavoto": 6.0, "voto": 6.0, "gol_fatti_subiti": 0.0, "ammonizioni": 0.0, "espulsioni": 0.0, "rigori_parati_segnati": 0.0, "autogol": 0.0, "portiere_imbattuto": 0.0, "nome_giocatore": "candreva a"}, "molinaro c": {"squadra": "frosinone", "ruolo": "D", "fantavoto": 5.0, "voto": 5.0, "gol_fatti_subiti": 0.0, "ammonizioni": 0.0, "espulsioni": 0.0, "rigori_parati_segnati": 0.0, "autogol": 0.0, "portiere_imbattuto": 0.0, "nome_giocatore": "molinaro c"}, "cristante b": {"squadra": "roma", "ruolo": "C", "fantavoto": 4.5, "voto": 5.0, "gol_fatti_subiti": 0.0, "ammonizioni": -0.5, "espulsioni": 0.0, "rigori_parati_segnati": 0.0, "autogol": 0.0, "portiere_imbattuto": 0.0, "nome_giocatore": "cristante b"}, "cionek t": {"squadra": "spal", "ruolo": "D", "fantavoto": 5.5, "voto": 6.0, "gol_fatti_subiti": 0.0, "ammonizioni": -0.5, "espulsioni": 0.0, "rigori_parati_segnati": 0.0, "autogol": 0.0, "portiere_imbattuto": 0.0, "nome_giocatore": "cionek t"}, "murru n": {"squadra": "sampdoria", "ruolo": "D", "fantavoto": 5.5, "voto": 5.5, "gol_fatti_subiti": 0.0, "ammonizioni": 0.0, "espulsioni": 0.0, "rigori_parati_segnati": 0.0, "autogol": 0.0, "portiere_imbattuto": 0.0, "nome_giocatore": "murru n"}, "chiesa f": {"squadra": "fiorentina", "ruolo": "C", "fantavoto": 7.0, "voto": 7.0, "gol_fatti_subiti": 0.0, "ammonizioni": 0.0, "espulsioni": 0.0, "rigori_parati_segnati": 0.0, "autogol": 0.0, "portiere_imbattuto": 0.0, "nome_giocatore": "chiesa f"}, "di francesco": {"squadra": "roma", "ruolo": "0", "fantavoto": 6.0, "voto": 6.0, "gol_fatti_subiti": 0.0, "ammonizioni": 0.0, "espulsioni": 0.0, "rigori_parati_segnati": 0.0, "autogol": 0.0, "portiere_imbattuto": 0.0, "nome_giocatore": "di francesco"}, "belotti a": {"squadra": "torino", "ruolo": "A", "fantavoto": 6.0, "voto": 6.0, "gol_fatti_subiti": 0.0, "ammonizioni": 0.0, "espulsioni": 0.0, "rigori_parati_segnati": 0.0, "autogol": 0.0, "portiere_imbattuto": 0.0, "nome_giocatore": "belotti a"}, "musacchio m": {"squadra": "milan", "ruolo": "D", "fantavoto": 6.5, "voto": 6.5, "gol_fatti_subiti": 0.0, "ammonizioni": 0.0, "espulsioni": 0.0, "rigori_parati_segnati": 0.0, "autogol": 0.0, "portiere_imbattuto": 0.0, "nome_giocatore": "musacchio m"}, "lafont a": {"squadra": "fiorentina", "ruolo": "P", "fantavoto": 4.5, "voto": 5.5, "gol_fatti_subiti": -1.0, "ammonizioni": 0.0, "espulsioni": 0.0, "rigori_parati_segnati": 0.0, "autogol": 0.0, "portiere_imbattuto": 0.0, "nome_giocatore": "lafont a"}, "berardi d": {"squadra": "sassuolo", "ruolo": "A", "fantavoto": 4.5, "voto": 5.0, "gol_fatti_subiti": 0.0, "ammonizioni": -0.5, "espulsioni": 0.0, "rigori_parati_segnati": 0.0, "autogol": 0.0, "portiere_imbattuto": 0.0, "nome_giocatore": "berardi d"}, "cigarini l": {"squadra": "cagliari", "ruolo": "C", "fantavoto": 5.5, "voto": 6.0, "gol_fatti_subiti": 0.0, "ammonizioni": -0.5, "espulsioni": 0.0, "rigori_parati_segnati": 0.0, "autogol": 0.0, "portiere_imbattuto": 0.0, "nome_giocatore": "cigarini l"}, "la gumina a": {"squadra": "empoli", "ruolo": "A", "fantavoto": 6.0, "voto": 6.0, "gol_fatti_subiti": 0.0, "ammonizioni": 0.0, "espulsioni": 0.0, "rigori_parati_segnati": 0.0, "autogol": 0.0, "portiere_imbattuto": 0.0, "nome_giocatore": "la gumina a"}, "di carlo": {"squadra": "chievo", "ruolo": "0", "fantavoto": 6.0, "voto": 6.0, "gol_fatti_subiti": 0.0, "ammonizioni": 0.0, "espulsioni": 0.0, "rigori_parati_segnati": 0.0, "autogol": 0.0, "portiere_imbattuto": 0.0, "nome_giocatore": "di carlo"}, "barrow m": {"squadra": "atalanta", "ruolo": "A", "fantavoto": NaN, "voto": NaN, "gol_fatti_subiti": 0.0, "ammonizioni": 0.0, "espulsioni": 0.0, "rigori_parati_segnati": 0.0, "autogol": 0.0, "portiere_imbattuto": 0.0, "nome_giocatore": "barrow m"}, "correa j": {"squadra": "lazio", "ruolo": "C", "fantavoto": 5.0, "voto": 5.0, "gol_fatti_subiti": 0.0, "ammonizioni": 0.0, "espulsioni": 0.0, "rigori_parati_segnati": 0.0, "autogol": 0.0, "portiere_imbattuto": 0.0, "nome_giocatore": "correa j"}, "n koulou n": {"squadra": "torino", "ruolo": "D", "fantavoto": 7.0, "voto": 7.0, "gol_fatti_subiti": 0.0, "ammonizioni": 0.0, "espulsioni": 0.0, "rigori_parati_segnati": 0.0, "autogol": 0.0, "portiere_imbattuto": 0.0, "nome_giocatore": "n koulou n"}, "chibsah r": {"squadra": "frosinone", "ruolo": "C", "fantavoto": 5.0, "voto": 5.0, "gol_fatti_subiti": 0.0, "ammonizioni": 0.0, "espulsioni": 0.0, "rigori_parati_segnati": 0.0, "autogol": 0.0, "portiere_imbattuto": 0.0, "nome_giocatore": "chibsah r"}, "cataldi d": {"squadra": "lazio", "ruolo": "C", "fantavoto": 6.5, "voto": 6.5, "gol_fatti_subiti": 0.0, "ammonizioni": 0.0, "espulsioni": 0.0, "rigori_parati_segnati": 0.0, "autogol": 0.0, "portiere_imbattuto": 0.0, "nome_giocatore": "cataldi d"}, "gasperini": {"squadra": "atalanta", "ruolo": "0", "fantavoto": 5.5, "voto": 5.5, "gol_fatti_subiti": 0.0, "ammonizioni": 0.0, "espulsioni": 0.0, "rigori_parati_segnati": 0.0, "autogol": 0.0, "portiere_imbattuto": 0.0, "nome_giocatore": "gasperini"}, "d aversa": {"squadra": "parma", "ruolo": "0", "fantavoto": 6.0, "voto": 6.0, "gol_fatti_subiti": 0.0, "ammonizioni": 0.0, "espulsioni": 0.0, "rigori_parati_segnati": 0.0, "autogol": 0.0, "portiere_imbattuto": 0.0, "nome_giocatore": "d aversa"}, "veretout j": {"squadra": "fiorentina", "ruolo": "C", "fantavoto": 9.0, "voto": 6.5, "gol_fatti_subiti": 3.0, "ammonizioni": -0.5, "espulsioni": 0.0, "rigori_parati_segnati": 0.0, "autogol": 0.0, "portiere_imbattuto": 0.0, "nome_giocatore": "veretout j"}, "milenkovic n": {"squadra": "fiorentina", "ruolo": "D", "fantavoto": 6.0, "voto": 6.5, "gol_fatti_subiti": 0.0, "ammonizioni": -0.5, "espulsioni": 0.0, "rigori_parati_segnati": 0.0, "autogol": 0.0, "portiere_imbattuto": 0.0, "nome_giocatore": "milenkovic n"}, "caicedo f": {"squadra": "lazio", "ruolo": "A", "fantavoto": 5.0, "voto": 5.0, "gol_fatti_subiti": 0.0, "ammonizioni": 0.0, "espulsioni": 0.0, "rigori_parati_segnati": 0.0, "autogol": 0.0, "portiere_imbattuto": 0.0, "nome_giocatore": "caicedo f"}, "kouame c": {"squadra": "genoa", "ruolo": "A", "fantavoto": 6.0, "voto": 6.0, "gol_fatti_subiti": 0.0, "ammonizioni": 0.0, "espulsioni": 0.0, "rigori_parati_segnati": 0.0, "autogol": 0.0, "portiere_imbattuto": 0.0, "nome_giocatore": "kouame c"}, "gattuso": {"squadra": "milan", "ruolo": "0", "fantavoto": 7.5, "voto": 7.5, "gol_fatti_subiti": 0.0, "ammonizioni": 0.0, "espulsioni": 0.0, "rigori_parati_segnati": 0.0, "autogol": 0.0, "portiere_imbattuto": 0.0, "nome_giocatore": "gattuso"}, "bradaric f": {"squadra": "cagliari", "ruolo": "C", "fantavoto": NaN, "voto": NaN, "gol_fatti_subiti": 0.0, "ammonizioni": 0.0, "espulsioni": 0.0, "rigori_parati_segnati": 0.0, "autogol": 0.0, "portiere_imbattuto": 0.0, "nome_giocatore": "bradaric f"}, "marusic a": {"squadra": "lazio", "ruolo": "D", "fantavoto": 5.5, "voto": 5.5, "gol_fatti_subiti": 0.0, "ammonizioni": 0.0, "espulsioni": 0.0, "rigori_parati_segnati": 0.0, "autogol": 0.0, "portiere_imbattuto": 0.0, "nome_giocatore": "marusic a"}, "pasqual m": {"squadra": "empoli", "ruolo": "D", "fantavoto": 5.5, "voto": 6.0, "gol_fatti_subiti": 0.0, "ammonizioni": -0.5, "espulsioni": 0.0, "rigori_parati_segnati": 0.0, "autogol": 0.0, "portiere_imbattuto": 0.0, "nome_giocatore": "pasqual m"}, "dambrosio d": {"squadra": "inter", "ruolo": "D", "fantavoto": 9.5, "voto": 7.0, "gol_fatti_subiti": 3.0, "ammonizioni": -0.5, "espulsioni": 0.0, "rigori_parati_segnati": 0.0, "autogol": 0.0, "portiere_imbattuto": 0.0, "nome_giocatore": "dambrosio d"}, "brighi m": {"squadra": "empoli", "ruolo": "C", "fantavoto": 6.0, "voto": 6.0, "gol_fatti_subiti": 0.0, "ammonizioni": 0.0, "espulsioni": 0.0, "rigori_parati_segnati": 0.0, "autogol": 0.0, "portiere_imbattuto": 0.0, "nome_giocatore": "brighi m"}, "viviani f": {"squadra": "frosinone", "ruolo": "C", "fantavoto": 5.5, "voto": 5.5, "gol_fatti_subiti": 0.0, "ammonizioni": 0.0, "espulsioni": 0.0, "rigori_parati_segnati": 0.0, "autogol": 0.0, "portiere_imbattuto": 0.0, "nome_giocatore": "viviani f"}, "giampaolo": {"squadra": "sampdoria", "ruolo": "0", "fantavoto": 6.0, "voto": 6.0, "gol_fatti_subiti": 0.0, "ammonizioni": 0.0, "espulsioni": 0.0, "rigori_parati_segnati": 0.0, "autogol": 0.0, "portiere_imbattuto": 0.0, "nome_giocatore": "giampaolo"}, "vieira r": {"squadra": "sampdoria", "ruolo": "C", "fantavoto": NaN, "voto": NaN, "gol_fatti_subiti": 0.0, "ammonizioni": 0.0, "espulsioni": 0.0, "rigori_parati_segnati": 0.0, "autogol": 0.0, "portiere_imbattuto": 0.0, "nome_giocatore": "vieira r"}, "bourabia m": {"squadra": "sassuolo", "ruolo": "C", "fantavoto": 5.0, "voto": 5.5, "gol_fatti_subiti": 0.0, "ammonizioni": -0.5, "espulsioni": 0.0, "rigori_parati_segnati": 0.0, "autogol": 0.0, "portiere_imbattuto": 0.0, "nome_giocatore": "bourabia m"}, "ancelotti": {"squadra": "napoli", "ruolo": "0", "fantavoto": 6.0, "voto": 6.0, "gol_fatti_subiti": 0.0, "ammonizioni": 0.0, "espulsioni": 0.0, "rigori_parati_segnati": 0.0, "autogol": 0.0, "portiere_imbattuto": 0.0, "nome_giocatore": "ancelotti"}, "mandzukic m": {"squadra": "juventus", "ruolo": "A", "fantavoto": 6.5, "voto": 6.5, "gol_fatti_subiti": 0.0, "ammonizioni": 0.0, "espulsioni": 0.0, "rigori_parati_segnati": 0.0, "autogol": 0.0, "portiere_imbattuto": 0.0, "nome_giocatore": "mandzukic m"}, "danilo l": {"squadra": "bologna", "ruolo": "D", "fantavoto": 5.5, "voto": 6.0, "gol_fatti_subiti": 0.0, "ammonizioni": -0.5, "espulsioni": 0.0, "rigori_parati_segnati": 0.0, "autogol": 0.0, "portiere_imbattuto": 0.0, "nome_giocatore": "danilo l"}, "patric": {"squadra": "lazio", "ruolo": "D", "fantavoto": 6.0, "voto": 6.5, "gol_fatti_subiti": 0.0, "ammonizioni": -0.5, "espulsioni": 0.0, "rigori_parati_segnati": 0.0, "autogol": 0.0, "portiere_imbattuto": 0.0, "nome_giocatore": "patric"}, "handanovic s": {"squadra": "inter", "ruolo": "P", "fantavoto": 5.5, "voto": 6.5, "gol_fatti_subiti": -1.0, "ammonizioni": 0.0, "espulsioni": 0.0, "rigori_parati_segnati": 0.0, "autogol": 0.0, "portiere_imbattuto": 0.0, "nome_giocatore": "handanovic s"}, "musso j": {"squadra": "udinese", "ruolo": "P", "fantavoto": 7.5, "voto": 6.5, "gol_fatti_subiti": 0.0, "ammonizioni": 0.0, "espulsioni": 0.0, "rigori_parati_segnati": 0.0, "autogol": 0.0, "portiere_imbattuto": 1.0, "nome_giocatore": "musso j"}, "chiellini g": {"squadra": "juventus", "ruolo": "D", "fantavoto": 6.5, "voto": 6.5, "gol_fatti_subiti": 0.0, "ammonizioni": 0.0, "espulsioni": 0.0, "rigori_parati_segnati": 0.0, "autogol": 0.0, "portiere_imbattuto": 0.0, "nome_giocatore": "chiellini g"}, "zielinski p": {"squadra": "napoli", "ruolo": "C", "fantavoto": 6.5, "voto": 6.5, "gol_fatti_subiti": 0.0, "ammonizioni": 0.0, "espulsioni": 0.0, "rigori_parati_segnati": 0.0, "autogol": 0.0, "portiere_imbattuto": 0.0, "nome_giocatore": "zielinski p"}, "de paul r": {"squadra": "udinese", "ruolo": "C", "fantavoto": 6.0, "voto": 6.0, "gol_fatti_subiti": 0.0, "ammonizioni": 0.0, "espulsioni": 0.0, "rigori_parati_segnati": 0.0, "autogol": 0.0, "portiere_imbattuto": 0.0, "nome_giocatore": "de paul r"}, "de roon m": {"squadra": "atalanta", "ruolo": "C", "fantavoto": 5.5, "voto": 6.0, "gol_fatti_subiti": 0.0, "ammonizioni": -0.5, "espulsioni": 0.0, "rigori_parati_segnati": 0.0, "autogol": 0.0, "portiere_imbattuto": 0.0, "nome_giocatore": "de roon m"}, "leris m": {"squadra": "chievo", "ruolo": "A", "fantavoto": 5.5, "voto": 6.0, "gol_fatti_subiti": 0.0, "ammonizioni": -0.5, "espulsioni": 0.0, "rigori_parati_segnati": 0.0, "autogol": 0.0, "portiere_imbattuto": 0.0, "nome_giocatore": "leris m"}, "dalbert h": {"squadra": "inter", "ruolo": "D", "fantavoto": 5.5, "voto": 5.5, "gol_fatti_subiti": 0.0, "ammonizioni": 0.0, "espulsioni": 0.0, "rigori_parati_segnati": 0.0, "autogol": 0.0, "portiere_imbattuto": 0.0, "nome_giocatore": "dalbert h"}, "mbaye i": {"squadra": "bologna", "ruolo": "D", "fantavoto": 6.0, "voto": 6.0, "gol_fatti_subiti": 0.0, "ammonizioni": 0.0, "espulsioni": 0.0, "rigori_parati_segnati": 0.0, "autogol": 0.0, "portiere_imbattuto": 0.0, "nome_giocatore": "mbaye i"}, "calhanoglu h": {"squadra": "milan", "ruolo": "C", "fantavoto": 10.0, "voto": 7.0, "gol_fatti_subiti": 3.0, "ammonizioni": 0.0, "espulsioni": 0.0, "rigori_parati_segnati": 0.0, "autogol": 0.0, "portiere_imbattuto": 0.0, "nome_giocatore": "calhanoglu h"}, "baroni": {"squadra": "frosinone", "ruolo": "0", "fantavoto": 5.5, "voto": 5.5, "gol_fatti_subiti": 0.0, "ammonizioni": 0.0, "espulsioni": 0.0, "rigori_parati_segnati": 0.0, "autogol": 0.0, "portiere_imbattuto": 0.0, "nome_giocatore": "baroni"}, "palomino j": {"squadra": "atalanta", "ruolo": "D", "fantavoto": 6.0, "voto": 6.0, "gol_fatti_subiti": 0.0, "ammonizioni": 0.0, "espulsioni": 0.0, "rigori_parati_segnati": 0.0, "autogol": 0.0, "portiere_imbattuto": 0.0, "nome_giocatore": "palomino j"}, "zaniolo n": {"squadra": "roma", "ruolo": "C", "fantavoto": 5.5, "voto": 5.5, "gol_fatti_subiti": 0.0, "ammonizioni": 0.0, "espulsioni": 0.0, "rigori_parati_segnati": 0.0, "autogol": 0.0, "portiere_imbattuto": 0.0, "nome_giocatore": "zaniolo n"}, "de rossi d": {"squadra": "roma", "ruolo": "C", "fantavoto": 6.5, "voto": 6.5, "gol_fatti_subiti": 0.0, "ammonizioni": 0.0, "espulsioni": 0.0, "rigori_parati_segnati": 0.0, "autogol": 0.0, "portiere_imbattuto": 0.0, "nome_giocatore": "de rossi d"}, "brozovic m": {"squadra": "inter", "ruolo": "C", "fantavoto": 5.5, "voto": 5.5, "gol_fatti_subiti": 0.0, "ammonizioni": 0.0, "espulsioni": 0.0, "rigori_parati_segnati": 0.0, "autogol": 0.0, "portiere_imbattuto": 0.0, "nome_giocatore": "brozovic m"}, "deiola a": {"squadra": "cagliari", "ruolo": "C", "fantavoto": 5.0, "voto": 5.5, "gol_fatti_subiti": 0.0, "ammonizioni": -0.5, "espulsioni": 0.0, "rigori_parati_segnati": 0.0, "autogol": 0.0, "portiere_imbattuto": 0.0, "nome_giocatore": "deiola a"}, "callejon j": {"squadra": "napoli", "ruolo": "A", "fantavoto": 6.0, "voto": 6.0, "gol_fatti_subiti": 0.0, "ammonizioni": 0.0, "espulsioni": 0.0, "rigori_parati_segnati": 0.0, "autogol": 0.0, "portiere_imbattuto": 0.0, "nome_giocatore": "callejon j"}, "bastoni a": {"squadra": "parma", "ruolo": "D", "fantavoto": 4.5, "voto": 5.0, "gol_fatti_subiti": 0.0, "ammonizioni": -0.5, "espulsioni": 0.0, "rigori_parati_segnati": 0.0, "autogol": 0.0, "portiere_imbattuto": 0.0, "nome_giocatore": "bastoni a"}, "dalessandro m": {"squadra": "udinese", "ruolo": "C", "fantavoto": NaN, "voto": NaN, "gol_fatti_subiti": 0.0, "ammonizioni": 0.0, "espulsioni": 0.0, "rigori_parati_segnati": 0.0, "autogol": 0.0, "portiere_imbattuto": 0.0, "nome_giocatore": "dalessandro m"}, "bereszynski b": {"squadra": "sampdoria", "ruolo": "D", "fantavoto": 5.0, "voto": 5.0, "gol_fatti_subiti": 0.0, "ammonizioni": 0.0, "espulsioni": 0.0, "rigori_parati_segnati": 0.0, "autogol": 0.0, "portiere_imbattuto": 0.0, "nome_giocatore": "bereszynski b"}, "gori m": {"squadra": "frosinone", "ruolo": "C", "fantavoto": NaN, "voto": NaN, "gol_fatti_subiti": 0.0, "ammonizioni": 0.0, "espulsioni": 0.0, "rigori_parati_segnati": 0.0, "autogol": 0.0, "portiere_imbattuto": 0.0, "nome_giocatore": "gori m"}, "benassi m": {"squadra": "fiorentina", "ruolo": "C", "fantavoto": 5.5, "voto": 5.5, "gol_fatti_subiti": 0.0, "ammonizioni": 0.0, "espulsioni": 0.0, "rigori_parati_segnati": 0.0, "autogol": 0.0, "portiere_imbattuto": 0.0, "nome_giocatore": "benassi m"}, "laxalt d": {"squadra": "milan", "ruolo": "C", "fantavoto": NaN, "voto": NaN, "gol_fatti_subiti": 0.0, "ammonizioni": 0.0, "espulsioni": 0.0, "rigori_parati_segnati": 0.0, "autogol": 0.0, "portiere_imbattuto": 0.0, "nome_giocatore": "laxalt d"}, "ronaldo c": {"squadra": "juventus", "ruolo": "A", "fantavoto": 10.5, "voto": 7.5, "gol_fatti_subiti": 3.0, "ammonizioni": 0.0, "espulsioni": 0.0, "rigori_parati_segnati": 0.0, "autogol": 0.0, "portiere_imbattuto": 0.0, "nome_giocatore": "ronaldo c"}, "caceres m": {"squadra": "juventus", "ruolo": "D", "fantavoto": 6.0, "voto": 6.0, "gol_fatti_subiti": 0.0, "ammonizioni": 0.0, "espulsioni": 0.0, "rigori_parati_segnati": 0.0, "autogol": 0.0, "portiere_imbattuto": 0.0, "nome_giocatore": "caceres m"}, "despodov k": {"squadra": "cagliari", "ruolo": "A", "fantavoto": 6.0, "voto": 6.0, "gol_fatti_subiti": 0.0, "ammonizioni": 0.0, "espulsioni": 0.0, "rigori_parati_segnati": 0.0, "autogol": 0.0, "portiere_imbattuto": 0.0, "nome_giocatore": "despodov k"}, "schelotto e": {"squadra": "chievo", "ruolo": "C", "fantavoto": 5.5, "voto": 5.5, "gol_fatti_subiti": 0.0, "ammonizioni": 0.0, "espulsioni": 0.0, "rigori_parati_segnati": 0.0, "autogol": 0.0, "portiere_imbattuto": 0.0, "nome_giocatore": "schelotto e"}, "biraghi c": {"squadra": "fiorentina", "ruolo": "D", "fantavoto": 5.5, "voto": 6.0, "gol_fatti_subiti": 0.0, "ammonizioni": -0.5, "espulsioni": 0.0, "rigori_parati_segnati": 0.0, "autogol": 0.0, "portiere_imbattuto": 0.0, "nome_giocatore": "biraghi c"}, "schiattarella p": {"squadra": "spal", "ruolo": "C", "fantavoto": 4.5, "voto": 5.0, "gol_fatti_subiti": 0.0, "ammonizioni": -0.5, "espulsioni": 0.0, "rigori_parati_segnati": 0.0, "autogol": 0.0, "portiere_imbattuto": 0.0, "nome_giocatore": "schiattarella p"}, "kurtic j": {"squadra": "spal", "ruolo": "C", "fantavoto": 6.0, "voto": 6.0, "gol_fatti_subiti": 0.0, "ammonizioni": 0.0, "espulsioni": 0.0, "rigori_parati_segnati": 0.0, "autogol": 0.0, "portiere_imbattuto": 0.0, "nome_giocatore": "kurtic j"}, "rincon t": {"squadra": "torino", "ruolo": "C", "fantavoto": 5.5, "voto": 6.0, "gol_fatti_subiti": 0.0, "ammonizioni": -0.5, "espulsioni": 0.0, "rigori_parati_segnati": 0.0, "autogol": 0.0, "portiere_imbattuto": 0.0, "nome_giocatore": "rincon t"}, "defrel g": {"squadra": "sampdoria", "ruolo": "A", "fantavoto": 6.0, "voto": 6.0, "gol_fatti_subiti": 0.0, "ammonizioni": 0.0, "espulsioni": 0.0, "rigori_parati_segnati": 0.0, "autogol": 0.0, "portiere_imbattuto": 0.0, "nome_giocatore": "defrel g"}, "romulo ": {"squadra": "lazio", "ruolo": "D", "fantavoto": 6.5, "voto": 6.5, "gol_fatti_subiti": 0.0, "ammonizioni": 0.0, "espulsioni": 0.0, "rigori_parati_segnati": 0.0, "autogol": 0.0, "portiere_imbattuto": 0.0, "nome_giocatore": "romulo "}, "saponara r": {"squadra": "sampdoria", "ruolo": "C", "fantavoto": 6.0, "voto": 6.0, "gol_fatti_subiti": 0.0, "ammonizioni": 0.0, "espulsioni": 0.0, "rigori_parati_segnati": 0.0, "autogol": 0.0, "portiere_imbattuto": 0.0, "nome_giocatore": "saponara r"}, "santander f": {"squadra": "bologna", "ruolo": "A", "fantavoto": 6.0, "voto": 6.0, "gol_fatti_subiti": 0.0, "ammonizioni": 0.0, "espulsioni": 0.0, "rigori_parati_segnati": 0.0, "autogol": 0.0, "portiere_imbattuto": 0.0, "nome_giocatore": "santander f"}, "skorupski l": {"squadra": "bologna", "ruolo": "P", "fantavoto": 4.0, "voto": 6.0, "gol_fatti_subiti": -2.0, "ammonizioni": 0.0, "espulsioni": 0.0, "rigori_parati_segnati": 0.0, "autogol": 0.0, "portiere_imbattuto": 0.0, "nome_giocatore": "skorupski l"}, "hateboer h": {"squadra": "atalanta", "ruolo": "D", "fantavoto": 5.5, "voto": 5.5, "gol_fatti_subiti": 0.0, "ammonizioni": 0.0, "espulsioni": 0.0, "rigori_parati_segnati": 0.0, "autogol": 0.0, "portiere_imbattuto": 0.0, "nome_giocatore": "hateboer h"}, "okaka s": {"squadra": "udinese", "ruolo": "A", "fantavoto": 5.0, "voto": 5.0, "gol_fatti_subiti": 0.0, "ammonizioni": 0.0, "espulsioni": 0.0, "rigori_parati_segnati": 0.0, "autogol": 0.0, "portiere_imbattuto": 0.0, "nome_giocatore": "okaka s"}, "barella n": {"squadra": "cagliari", "ruolo": "C", "fantavoto": 7.0, "voto": 7.0, "gol_fatti_subiti": 0.0, "ammonizioni": 0.0, "espulsioni": 0.0, "rigori_parati_segnati": 0.0, "autogol": 0.0, "portiere_imbattuto": 0.0, "nome_giocatore": "barella n"}, "mihajlovic s": {"squadra": "bologna", "ruolo": "0", "fantavoto": 7.0, "voto": 7.0, "gol_fatti_subiti": 0.0, "ammonizioni": 0.0, "espulsioni": 0.0, "rigori_parati_segnati": 0.0, "autogol": 0.0, "portiere_imbattuto": 0.0, "nome_giocatore": "mihajlovic s"}, "izzo a": {"squadra": "torino", "ruolo": "D", "fantavoto": 5.5, "voto": 5.5, "gol_fatti_subiti": 0.0, "ammonizioni": 0.0, "espulsioni": 0.0, "rigori_parati_segnati": 0.0, "autogol": 0.0, "portiere_imbattuto": 0.0, "nome_giocatore": "izzo a"}, "djordjevic f": {"squadra": "chievo", "ruolo": "A", "fantavoto": 4.5, "voto": 5.0, "gol_fatti_subiti": 0.0, "ammonizioni": -0.5, "espulsioni": 0.0, "rigori_parati_segnati": 0.0, "autogol": 0.0, "portiere_imbattuto": 0.0, "nome_giocatore": "djordjevic f"}, "rigoni n": {"squadra": "chievo", "ruolo": "C", "fantavoto": 6.0, "voto": 6.0, "gol_fatti_subiti": 0.0, "ammonizioni": 0.0, "espulsioni": 0.0, "rigori_parati_segnati": 0.0, "autogol": 0.0, "portiere_imbattuto": 0.0, "nome_giocatore": "rigoni n"}, "kulusevski d": {"squadra": "atalanta", "ruolo": "C", "fantavoto": 5.0, "voto": 5.0, "gol_fatti_subiti": 0.0, "ammonizioni": 0.0, "espulsioni": 0.0, "rigori_parati_segnati": 0.0, "autogol": 0.0, "portiere_imbattuto": 0.0, "nome_giocatore": "kulusevski d"}, "kucka j": {"squadra": "parma", "ruolo": "C", "fantavoto": 9.5, "voto": 6.5, "gol_fatti_subiti": 3.0, "ammonizioni": 0.0, "espulsioni": 0.0, "rigori_parati_segnati": 0.0, "autogol": 0.0, "portiere_imbattuto": 0.0, "nome_giocatore": "kucka j"}, "sportiello m": {"squadra": "frosinone", "ruolo": "P", "fantavoto": 3.0, "voto": 6.0, "gol_fatti_subiti": -3.0, "ammonizioni": 0.0, "espulsioni": 0.0, "rigori_parati_segnati": 0.0, "autogol": 0.0, "portiere_imbattuto": 0.0, "nome_giocatore": "sportiello m"}, "lulic s": {"squadra": "lazio", "ruolo": "C", "fantavoto": 6.0, "voto": 6.0, "gol_fatti_subiti": 0.0, "ammonizioni": 0.0, "espulsioni": 0.0, "rigori_parati_segnati": 0.0, "autogol": 0.0, "portiere_imbattuto": 0.0, "nome_giocatore": "lulic s"}, "iacoponi s": {"squadra": "parma", "ruolo": "D", "fantavoto": 5.5, "voto": 5.5, "gol_fatti_subiti": 0.0, "ammonizioni": 0.0, "espulsioni": 0.0, "rigori_parati_segnati": 0.0, "autogol": 0.0, "portiere_imbattuto": 0.0, "nome_giocatore": "iacoponi s"}, "lukic s": {"squadra": "torino", "ruolo": "C", "fantavoto": 5.0, "voto": 5.0, "gol_fatti_subiti": 0.0, "ammonizioni": 0.0, "espulsioni": 0.0, "rigori_parati_segnati": 0.0, "autogol": 0.0, "portiere_imbattuto": 0.0, "nome_giocatore": "lukic s"}, "lazovic d": {"squadra": "genoa", "ruolo": "C", "fantavoto": 6.0, "voto": 6.0, "gol_fatti_subiti": 0.0, "ammonizioni": 0.0, "espulsioni": 0.0, "rigori_parati_segnati": 0.0, "autogol": 0.0, "portiere_imbattuto": 0.0, "nome_giocatore": "lazovic d"}, "hugo v": {"squadra": "fiorentina", "ruolo": "D", "fantavoto": 5.0, "voto": 5.0, "gol_fatti_subiti": 0.0, "ammonizioni": 0.0, "espulsioni": 0.0, "rigori_parati_segnati": 0.0, "autogol": 0.0, "portiere_imbattuto": 0.0, "nome_giocatore": "hugo v"}, "rolon e": {"squadra": "genoa", "ruolo": "C", "fantavoto": 6.0, "voto": 6.0, "gol_fatti_subiti": 0.0, "ammonizioni": 0.0, "espulsioni": 0.0, "rigori_parati_segnati": 0.0, "autogol": 0.0, "portiere_imbattuto": 0.0, "nome_giocatore": "rolon e"}, "linetty k": {"squadra": "sampdoria", "ruolo": "C", "fantavoto": 6.0, "voto": 6.5, "gol_fatti_subiti": 0.0, "ammonizioni": -0.5, "espulsioni": 0.0, "rigori_parati_segnati": 0.0, "autogol": 0.0, "portiere_imbattuto": 0.0, "nome_giocatore": "linetty k"}, "romero c": {"squadra": "genoa", "ruolo": "D", "fantavoto": 6.0, "voto": 6.5, "gol_fatti_subiti": 0.0, "ammonizioni": -0.5, "espulsioni": 0.0, "rigori_parati_segnati": 0.0, "autogol": 0.0, "portiere_imbattuto": 0.0, "nome_giocatore": "romero c"}, "lerager l": {"squadra": "genoa", "ruolo": "C", "fantavoto": 6.5, "voto": 6.5, "gol_fatti_subiti": 0.0, "ammonizioni": 0.0, "espulsioni": 0.0, "rigori_parati_segnati": 0.0, "autogol": 0.0, "portiere_imbattuto": 0.0, "nome_giocatore": "lerager l"}, "sanabria a": {"squadra": "genoa", "ruolo": "A", "fantavoto": 10.0, "voto": 7.0, "gol_fatti_subiti": 3.0, "ammonizioni": 0.0, "espulsioni": 0.0, "rigori_parati_segnati": 0.0, "autogol": 0.0, "portiere_imbattuto": 0.0, "nome_giocatore": "sanabria a"}, "badelj m": {"squadra": "lazio", "ruolo": "C", "fantavoto": 10.0, "voto": 7.5, "gol_fatti_subiti": 3.0, "ammonizioni": -0.5, "espulsioni": 0.0, "rigori_parati_segnati": 0.0, "autogol": 0.0, "portiere_imbattuto": 0.0, "nome_giocatore": "badelj m"}, "ruiz f": {"squadra": "napoli", "ruolo": "C", "fantavoto": 5.5, "voto": 5.5, "gol_fatti_subiti": 0.0, "ammonizioni": 0.0, "espulsioni": 0.0, "rigori_parati_segnati": 0.0, "autogol": 0.0, "portiere_imbattuto": 0.0, "nome_giocatore": "ruiz f"}, "helander f": {"squadra": "bologna", "ruolo": "D", "fantavoto": 5.0, "voto": 5.0, "gol_fatti_subiti": 0.0, "ammonizioni": 0.0, "espulsioni": 0.0, "rigori_parati_segnati": 0.0, "autogol": 0.0, "portiere_imbattuto": 0.0, "nome_giocatore": "helander f"}, "dijks m": {"squadra": "bologna", "ruolo": "D", "fantavoto": 6.0, "voto": 6.5, "gol_fatti_subiti": 0.0, "ammonizioni": -0.5, "espulsioni": 0.0, "rigori_parati_segnati": 0.0, "autogol": 0.0, "portiere_imbattuto": 0.0, "nome_giocatore": "dijks m"}, "immobile c": {"squadra": "lazio", "ruolo": "A", "fantavoto": 6.0, "voto": 6.0, "gol_fatti_subiti": 0.0, "ammonizioni": 0.0, "espulsioni": 0.0, "rigori_parati_segnati": 0.0, "autogol": 0.0, "portiere_imbattuto": 0.0, "nome_giocatore": "immobile c"}, "sansone n": {"squadra": "bologna", "ruolo": "A", "fantavoto": 10.0, "voto": 7.0, "gol_fatti_subiti": 3.0, "ammonizioni": 0.0, "espulsioni": 0.0, "rigori_parati_segnati": 0.0, "autogol": 0.0, "portiere_imbattuto": 0.0, "nome_giocatore": "sansone n"}, "leiva l": {"squadra": "lazio", "ruolo": "C", "fantavoto": 5.5, "voto": 5.5, "gol_fatti_subiti": 0.0, "ammonizioni": 0.0, "espulsioni": 0.0, "rigori_parati_segnati": 0.0, "autogol": 0.0, "portiere_imbattuto": 0.0, "nome_giocatore": "leiva l"}, "alves b": {"squadra": "parma", "ruolo": "D", "fantavoto": 5.0, "voto": 5.0, "gol_fatti_subiti": 0.0, "ammonizioni": 0.0, "espulsioni": 0.0, "rigori_parati_segnati": 0.0, "autogol": 0.0, "portiere_imbattuto": 0.0, "nome_giocatore": "alves b"}, "lazzari m": {"squadra": "spal", "ruolo": "C", "fantavoto": NaN, "voto": NaN, "gol_fatti_subiti": 0.0, "ammonizioni": 0.0, "espulsioni": 0.0, "rigori_parati_segnati": 0.0, "autogol": 0.0, "portiere_imbattuto": 0.0, "nome_giocatore": "lazzari m"}, "bakayoko t": {"squadra": "milan", "ruolo": "C", "fantavoto": 6.5, "voto": 6.5, "gol_fatti_subiti": 0.0, "ammonizioni": 0.0, "espulsioni": 0.0, "rigori_parati_segnati": 0.0, "autogol": 0.0, "portiere_imbattuto": 0.0, "nome_giocatore": "bakayoko t"}, "allan m": {"squadra": "napoli", "ruolo": "C", "fantavoto": 6.5, "voto": 7.0, "gol_fatti_subiti": 0.0, "ammonizioni": -0.5, "espulsioni": 0.0, "rigori_parati_segnati": 0.0, "autogol": 0.0, "portiere_imbattuto": 0.0, "nome_giocatore": "allan m"}, "hysaj e": {"squadra": "napoli", "ruolo": "D", "fantavoto": 5.5, "voto": 6.0, "gol_fatti_subiti": 0.0, "ammonizioni": -0.5, "espulsioni": 0.0, "rigori_parati_segnati": 0.0, "autogol": 0.0, "portiere_imbattuto": 0.0, "nome_giocatore": "hysaj e"}, "locatelli m": {"squadra": "sassuolo", "ruolo": "C", "fantavoto": 6.0, "voto": 6.0, "gol_fatti_subiti": 0.0, "ammonizioni": 0.0, "espulsioni": 0.0, "rigori_parati_segnati": 0.0, "autogol": 0.0, "portiere_imbattuto": 0.0, "nome_giocatore": "locatelli m"}, "kolarov a": {"squadra": "roma", "ruolo": "D", "fantavoto": 9.5, "voto": 6.5, "gol_fatti_subiti": 3.0, "ammonizioni": 0.0, "espulsioni": 0.0, "rigori_parati_segnati": 0.0, "autogol": 0.0, "portiere_imbattuto": 0.0, "nome_giocatore": "kolarov a"}, "romagnoli a": {"squadra": "milan", "ruolo": "D", "fantavoto": 7.0, "voto": 7.0, "gol_fatti_subiti": 0.0, "ammonizioni": 0.0, "espulsioni": 0.0, "rigori_parati_segnati": 0.0, "autogol": 0.0, "portiere_imbattuto": 0.0, "nome_giocatore": "romagnoli a"}, "nicola": {"squadra": "udinese", "ruolo": "0", "fantavoto": 6.0, "voto": 6.0, "gol_fatti_subiti": 0.0, "ammonizioni": 0.0, "espulsioni": 0.0, "rigori_parati_segnati": 0.0, "autogol": 0.0, "portiere_imbattuto": 0.0, "nome_giocatore": "nicola"}, "di lorenzo g": {"squadra": "empoli", "ruolo": "D", "fantavoto": 6.5, "voto": 6.5, "gol_fatti_subiti": 0.0, "ammonizioni": 0.0, "espulsioni": 0.0, "rigori_parati_segnati": 0.0, "autogol": 0.0, "portiere_imbattuto": 0.0, "nome_giocatore": "di lorenzo g"}, "dybala p": {"squadra": "juventus", "ruolo": "A", "fantavoto": 10.5, "voto": 7.5, "gol_fatti_subiti": 3.0, "ammonizioni": 0.0, "espulsioni": 0.0, "rigori_parati_segnati": 0.0, "autogol": 0.0, "portiere_imbattuto": 0.0, "nome_giocatore": "dybala p"}, "pioli": {"squadra": "fiorentina", "ruolo": "0", "fantavoto": 6.5, "voto": 6.5, "gol_fatti_subiti": 0.0, "ammonizioni": 0.0, "espulsioni": 0.0, "rigori_parati_segnati": 0.0, "autogol": 0.0, "portiere_imbattuto": 0.0, "nome_giocatore": "pioli"}, "quagliarella f": {"squadra": "sampdoria", "ruolo": "A", "fantavoto": 6.0, "voto": 6.0, "gol_fatti_subiti": 0.0, "ammonizioni": 0.0, "espulsioni": 0.0, "rigori_parati_segnati": 0.0, "autogol": 0.0, "portiere_imbattuto": 0.0, "nome_giocatore": "quagliarella f"}, "barilla a": {"squadra": "parma", "ruolo": "C", "fantavoto": 6.5, "voto": 6.5, "gol_fatti_subiti": 0.0, "ammonizioni": 0.0, "espulsioni": 0.0, "rigori_parati_segnati": 0.0, "autogol": 0.0, "portiere_imbattuto": 0.0, "nome_giocatore": "barilla a"}, "sorrentino s": {"squadra": "chievo", "ruolo": "P", "fantavoto": 8.5, "voto": 6.5, "gol_fatti_subiti": -1.0, "ammonizioni": 0.0, "espulsioni": 0.0, "rigori_parati_segnati": 3.0, "autogol": 0.0, "portiere_imbattuto": 0.0, "nome_giocatore": "sorrentino s"}, "cragno a": {"squadra": "cagliari", "ruolo": "P", "fantavoto": 5.0, "voto": 6.0, "gol_fatti_subiti": -1.0, "ammonizioni": 0.0, "espulsioni": 0.0, "rigori_parati_segnati": 0.0, "autogol": 0.0, "portiere_imbattuto": 0.0, "nome_giocatore": "cragno a"}, "kessie f": {"squadra": "milan", "ruolo": "C", "fantavoto": 5.5, "voto": 5.5, "gol_fatti_subiti": 0.0, "ammonizioni": 0.0, "espulsioni": 0.0, "rigori_parati_segnati": 0.0, "autogol": 0.0, "portiere_imbattuto": 0.0, "nome_giocatore": "kessie f"}, "dell orco c": {"squadra": "empoli", "ruolo": "D", "fantavoto": 6.5, "voto": 6.5, "gol_fatti_subiti": 0.0, "ammonizioni": 0.0, "espulsioni": 0.0, "rigori_parati_segnati": 0.0, "autogol": 0.0, "portiere_imbattuto": 0.0, "nome_giocatore": "dell orco c"}, "depaoli f": {"squadra": "chievo", "ruolo": "D", "fantavoto": 4.5, "voto": 5.0, "gol_fatti_subiti": 0.0, "ammonizioni": -0.5, "espulsioni": 0.0, "rigori_parati_segnati": 0.0, "autogol": 0.0, "portiere_imbattuto": 0.0, "nome_giocatore": "depaoli f"}, "semplici": {"squadra": "spal", "ruolo": "0", "fantavoto": 5.5, "voto": 5.5, "gol_fatti_subiti": 0.0, "ammonizioni": 0.0, "espulsioni": 0.0, "rigori_parati_segnati": 0.0, "autogol": 0.0, "portiere_imbattuto": 0.0, "nome_giocatore": "semplici"}, "soriano r": {"squadra": "bologna", "ruolo": "C", "fantavoto": 5.0, "voto": 5.0, "gol_fatti_subiti": 0.0, "ammonizioni": 0.0, "espulsioni": 0.0, "rigori_parati_segnati": 0.0, "autogol": 0.0, "portiere_imbattuto": 0.0, "nome_giocatore": "soriano r"}, "djimsiti b": {"squadra": "atalanta", "ruolo": "D", "fantavoto": 5.0, "voto": 5.0, "gol_fatti_subiti": 0.0, "ammonizioni": 0.0, "espulsioni": 0.0, "rigori_parati_segnati": 0.0, "autogol": 0.0, "portiere_imbattuto": 0.0, "nome_giocatore": "djimsiti b"}, "jordao b": {"squadra": "lazio", "ruolo": "C", "fantavoto": 6.0, "voto": 6.0, "gol_fatti_subiti": 0.0, "ammonizioni": 0.0, "espulsioni": 0.0, "rigori_parati_segnati": 0.0, "autogol": 0.0, "portiere_imbattuto": 0.0, "nome_giocatore": "jordao b"}, "simeone g": {"squadra": "fiorentina", "ruolo": "A", "fantavoto": 9.5, "voto": 6.5, "gol_fatti_subiti": 3.0, "ammonizioni": 0.0, "espulsioni": 0.0, "rigori_parati_segnati": 0.0, "autogol": 0.0, "portiere_imbattuto": 0.0, "nome_giocatore": "simeone g"}, "inglese r": {"squadra": "parma", "ruolo": "A", "fantavoto": 6.0, "voto": 6.0, "gol_fatti_subiti": 0.0, "ammonizioni": 0.0, "espulsioni": 0.0, "rigori_parati_segnati": 0.0, "autogol": 0.0, "portiere_imbattuto": 0.0, "nome_giocatore": "inglese r"}, "j mario": {"squadra": "inter", "ruolo": "C", "fantavoto": 6.0, "voto": 6.0, "gol_fatti_subiti": 0.0, "ammonizioni": 0.0, "espulsioni": 0.0, "rigori_parati_segnati": 0.0, "autogol": 0.0, "portiere_imbattuto": 0.0, "nome_giocatore": "j mario"}, "siligardi l": {"squadra": "parma", "ruolo": "A", "fantavoto": NaN, "voto": NaN, "gol_fatti_subiti": 0.0, "ammonizioni": 0.0, "espulsioni": 0.0, "rigori_parati_segnati": 0.0, "autogol": 0.0, "portiere_imbattuto": 0.0, "nome_giocatore": "siligardi l"}, "edera s": {"squadra": "bologna", "ruolo": "A", "fantavoto": 5.5, "voto": 6.0, "gol_fatti_subiti": 0.0, "ammonizioni": -0.5, "espulsioni": 0.0, "rigori_parati_segnati": 0.0, "autogol": 0.0, "portiere_imbattuto": 0.0, "nome_giocatore": "edera s"}, "krunic r": {"squadra": "empoli", "ruolo": "C", "fantavoto": 10.5, "voto": 7.5, "gol_fatti_subiti": 3.0, "ammonizioni": 0.0, "espulsioni": 0.0, "rigori_parati_segnati": 0.0, "autogol": 0.0, "portiere_imbattuto": 0.0, "nome_giocatore": "krunic r"}, "zeegelaar m": {"squadra": "udinese", "ruolo": "D", "fantavoto": 5.5, "voto": 6.0, "gol_fatti_subiti": 0.0, "ammonizioni": -0.5, "espulsioni": 0.0, "rigori_parati_segnati": 0.0, "autogol": 0.0, "portiere_imbattuto": 0.0, "nome_giocatore": "zeegelaar m"}, "joao pedro": {"squadra": "cagliari", "ruolo": "C", "fantavoto": 4.0, "voto": 5.0, "gol_fatti_subiti": 0.0, "ammonizioni": 0.0, "espulsioni": -1.0, "rigori_parati_segnati": 0.0, "autogol": 0.0, "portiere_imbattuto": 0.0, "nome_giocatore": "joao pedro"}, "mandragora r": {"squadra": "udinese", "ruolo": "C", "fantavoto": 6.0, "voto": 6.0, "gol_fatti_subiti": 0.0, "ammonizioni": 0.0, "espulsioni": 0.0, "rigori_parati_segnati": 0.0, "autogol": 0.0, "portiere_imbattuto": 0.0, "nome_giocatore": "mandragora r"}, "andersen j": {"squadra": "sampdoria", "ruolo": "D", "fantavoto": 6.0, "voto": 6.0, "gol_fatti_subiti": 0.0, "ammonizioni": 0.0, "espulsioni": 0.0, "rigori_parati_segnati": 0.0, "autogol": 0.0, "portiere_imbattuto": 0.0, "nome_giocatore": "andersen j"}, "gosens r": {"squadra": "atalanta", "ruolo": "D", "fantavoto": 5.5, "voto": 5.5, "gol_fatti_subiti": 0.0, "ammonizioni": 0.0, "espulsioni": 0.0, "rigori_parati_segnati": 0.0, "autogol": 0.0, "portiere_imbattuto": 0.0, "nome_giocatore": "gosens r"}, "consigli a": {"squadra": "sassuolo", "ruolo": "P", "fantavoto": 1.5, "voto": 4.5, "gol_fatti_subiti": -3.0, "ammonizioni": 0.0, "espulsioni": 0.0, "rigori_parati_segnati": 0.0, "autogol": 0.0, "portiere_imbattuto": 0.0, "nome_giocatore": "consigli a"}, "maran": {"squadra": "cagliari", "ruolo": "0", "fantavoto": 6.5, "voto": 6.5, "gol_fatti_subiti": 0.0, "ammonizioni": 0.0, "espulsioni": 0.0, "rigori_parati_segnati": 0.0, "autogol": 0.0, "portiere_imbattuto": 0.0, "nome_giocatore": "maran"}, "cancelo j": {"squadra": "juventus", "ruolo": "D", "fantavoto": 5.5, "voto": 6.0, "gol_fatti_subiti": 0.0, "ammonizioni": -0.5, "espulsioni": 0.0, "rigori_parati_segnati": 0.0, "autogol": 0.0, "portiere_imbattuto": 0.0, "nome_giocatore": "cancelo j"}, "cutrone p": {"squadra": "milan", "ruolo": "A", "fantavoto": 6.0, "voto": 6.0, "gol_fatti_subiti": 0.0, "ammonizioni": 0.0, "espulsioni": 0.0, "rigori_parati_segnati": 0.0, "autogol": 0.0, "portiere_imbattuto": 0.0, "nome_giocatore": "cutrone p"}, "dzeko e": {"squadra": "roma", "ruolo": "A", "fantavoto": 5.5, "voto": 5.5, "gol_fatti_subiti": 0.0, "ammonizioni": 0.0, "espulsioni": 0.0, "rigori_parati_segnati": 0.0, "autogol": 0.0, "portiere_imbattuto": 0.0, "nome_giocatore": "dzeko e"}, "zukanovic e": {"squadra": "genoa", "ruolo": "D", "fantavoto": 6.5, "voto": 6.5, "gol_fatti_subiti": 0.0, "ammonizioni": 0.0, "espulsioni": 0.0, "rigori_parati_segnati": 0.0, "autogol": 0.0, "portiere_imbattuto": 0.0, "nome_giocatore": "zukanovic e"}, "sirigu s": {"squadra": "torino", "ruolo": "P", "fantavoto": 8.5, "voto": 7.5, "gol_fatti_subiti": 0.0, "ammonizioni": 0.0, "espulsioni": 0.0, "rigori_parati_segnati": 0.0, "autogol": 0.0, "portiere_imbattuto": 1.0, "nome_giocatore": "sirigu s"}, "calabria d": {"squadra": "milan", "ruolo": "D", "fantavoto": 6.5, "voto": 6.5, "gol_fatti_subiti": 0.0, "ammonizioni": 0.0, "espulsioni": 0.0, "rigori_parati_segnati": 0.0, "autogol": 0.0, "portiere_imbattuto": 0.0, "nome_giocatore": "calabria d"}, "goldaniga e": {"squadra": "frosinone", "ruolo": "D", "fantavoto": 5.5, "voto": 5.5, "gol_fatti_subiti": 0.0, "ammonizioni": 0.0, "espulsioni": 0.0, "rigori_parati_segnati": 0.0, "autogol": 0.0, "portiere_imbattuto": 0.0, "nome_giocatore": "goldaniga e"}, "sensi s": {"squadra": "sassuolo", "ruolo": "C", "fantavoto": 4.5, "voto": 5.0, "gol_fatti_subiti": 0.0, "ammonizioni": -0.5, "espulsioni": 0.0, "rigori_parati_segnati": 0.0, "autogol": 0.0, "portiere_imbattuto": 0.0, "nome_giocatore": "sensi s"}, "muriel l": {"squadra": "fiorentina", "ruolo": "A", "fantavoto": 5.5, "voto": 5.5, "gol_fatti_subiti": 0.0, "ammonizioni": 0.0, "espulsioni": 0.0, "rigori_parati_segnati": 0.0, "autogol": 0.0, "portiere_imbattuto": 0.0, "nome_giocatore": "muriel l"}, "ionita a": {"squadra": "cagliari", "ruolo": "C", "fantavoto": 6.5, "voto": 6.5, "gol_fatti_subiti": 0.0, "ammonizioni": 0.0, "espulsioni": 0.0, "rigori_parati_segnati": 0.0, "autogol": 0.0, "portiere_imbattuto": 0.0, "nome_giocatore": "ionita a"}, "prandelli": {"squadra": "genoa", "ruolo": "0", "fantavoto": 7.0, "voto": 7.0, "gol_fatti_subiti": 0.0, "ammonizioni": 0.0, "espulsioni": 0.0, "rigori_parati_segnati": 0.0, "autogol": 0.0, "portiere_imbattuto": 0.0, "nome_giocatore": "prandelli"}, "capuano m": {"squadra": "frosinone", "ruolo": "D", "fantavoto": 5.0, "voto": 5.5, "gol_fatti_subiti": 0.0, "ammonizioni": -0.5, "espulsioni": 0.0, "rigori_parati_segnati": 0.0, "autogol": 0.0, "portiere_imbattuto": 0.0, "nome_giocatore": "capuano m"}, "baselli d": {"squadra": "torino", "ruolo": "C", "fantavoto": 5.5, "voto": 5.5, "gol_fatti_subiti": 0.0, "ammonizioni": 0.0, "espulsioni": 0.0, "rigori_parati_segnati": 0.0, "autogol": 0.0, "portiere_imbattuto": 0.0, "nome_giocatore": "baselli d"}, "pussetto i": {"squadra": "udinese", "ruolo": "A", "fantavoto": 6.0, "voto": 6.5, "gol_fatti_subiti": 0.0, "ammonizioni": -0.5, "espulsioni": 0.0, "rigori_parati_segnati": 0.0, "autogol": 0.0, "portiere_imbattuto": 0.0, "nome_giocatore": "pussetto i"}, "rigoni l": {"squadra": "parma", "ruolo": "C", "fantavoto": 6.0, "voto": 6.0, "gol_fatti_subiti": 0.0, "ammonizioni": 0.0, "espulsioni": 0.0, "rigori_parati_segnati": 0.0, "autogol": 0.0, "portiere_imbattuto": 0.0, "nome_giocatore": "rigoni l"}, "khedira s": {"squadra": "juventus", "ruolo": "C", "fantavoto": 6.0, "voto": 6.0, "gol_fatti_subiti": 0.0, "ammonizioni": 0.0, "espulsioni": 0.0, "rigori_parati_segnati": 0.0, "autogol": 0.0, "portiere_imbattuto": 0.0, "nome_giocatore": "khedira s"}, "acquah a": {"squadra": "empoli", "ruolo": "C", "fantavoto": 10.0, "voto": 7.0, "gol_fatti_subiti": 3.0, "ammonizioni": 0.0, "espulsioni": 0.0, "rigori_parati_segnati": 0.0, "autogol": 0.0, "portiere_imbattuto": 0.0, "nome_giocatore": "acquah a"}, "rogerio o": {"squadra": "sassuolo", "ruolo": "D", "fantavoto": 4.5, "voto": 4.5, "gol_fatti_subiti": 0.0, "ammonizioni": 0.0, "espulsioni": 0.0, "rigori_parati_segnati": 0.0, "autogol": 0.0, "portiere_imbattuto": 0.0, "nome_giocatore": "rogerio o"}, "mazzarri": {"squadra": "torino", "ruolo": "0", "fantavoto": 6.0, "voto": 6.0, "gol_fatti_subiti": 0.0, "ammonizioni": 0.0, "espulsioni": 0.0, "rigori_parati_segnati": 0.0, "autogol": 0.0, "portiere_imbattuto": 0.0, "nome_giocatore": "mazzarri"}, "jaroszynski p": {"squadra": "chievo", "ruolo": "D", "fantavoto": 6.0, "voto": 6.0, "gol_fatti_subiti": 0.0, "ammonizioni": 0.0, "espulsioni": 0.0, "rigori_parati_segnati": 0.0, "autogol": 0.0, "portiere_imbattuto": 0.0, "nome_giocatore": "jaroszynski p"}, "rodriguez r": {"squadra": "milan", "ruolo": "D", "fantavoto": 6.0, "voto": 6.5, "gol_fatti_subiti": 0.0, "ammonizioni": -0.5, "espulsioni": 0.0, "rigori_parati_segnati": 0.0, "autogol": 0.0, "portiere_imbattuto": 0.0, "nome_giocatore": "rodriguez r"}}}}